Workbook

Sheet Fee Schedule 2025-26
A1: HIGHCREST SCHOOL — 2025/26 FEE SCHEDULE
A2: Oxford International Curriculum • Adentan, Accra • All fees quoted in GHS
A4: Class Level | B4: Bird House | C4: Annual Fee | D4: Termly Fee | E4: Staff OIC Fee | F4: Programme | G4: Weeks | H4: Monthly Equiv.
A5: Crèche | B5: Robins | C5: 10000 | D5: 2550 | E5: 800 | F5: Year-Round | G5: 52 | H5: =C5/12 -> 833.33333
A6: Nursery 1 | B6: Starlings | C6: 9400 | D6: 2400 | E6: 800 | F6: Year-Round | G6: 52 | H6: =C6/12 -> 783.33333
A7: Nursery 2 | B7: Goldfinches | C7: 9400 | D7: 2400 | E7: 800 | F7: Year-Round | G7: 52 | H7: =C7/12 -> 783.33333
A8: KG 1 | B8: Kingfishers | C8: 7350 | D8: 2550 | E8: 850 | F8: 3-Term | G8: 39 | H8: =C8/12 -> 612.5
A9: KG 2 | B9: Hawks | C9: 7350 | D9: 2550 | E9: 850 | F9: 3-Term | G9: 39 | H9: =C9/12 -> 612.5
A10: Grade 1 | B10: Skylarks | C10: 8500 | D10: 3000 | E10: 1200 | F10: 3-Term | G10: 39 | H10: =C10/12 -> 708.33333
A11: Grade 2 | B11: Kestrels | C11: 8500 | D11: 3000 | E11: 1200 | F11: 3-Term | G11: 39 | H11: =C11/12 -> 708.33333
A12: Grade 3 | B12: Woodpeckers | C12: 8500 | D12: 3000 | E12: 1300 | F12: 3-Term | G12: 39 | H12: =C12/12 -> 708.33333
A13: Grade 4 | B13: Nightingales | C13: 8500 | D13: 3000 | E13: 1300 | F13: 3-Term | G13: 39 | H13: =C13/12 -> 708.33333
A14: Grade 5 | B14: Falcons | C14: 8500 | D14: 3000 | E14: 1300 | F14: 3-Term | G14: 39 | H14: =C14/12 -> 708.33333
A17: DISCOUNT POLICY
A18: Discount Type | B18: Rate | C18: Eligibility | D18: Notes
A19: Founding Family | B19: 5% | C19: Enrolled during inaugural year | D19: Ongoing loyalty benefit
A20: Sibling (2nd child) | B20: 5% | C20: Second child from same family | D20: Applied to 2nd child's fee
A21: Sibling (3rd child) | B21: 10% | C21: Third child from same family | D21: Applied to 3rd child's fee
A22: Staff Child | B22: OIC Only | C22: Teaching & non-teaching staff | D22: Max 2 children; T3 fully covered
A23: Compassionate Waiver | B23: Case-by-case | C23: Proprietor's discretion | D23: Documented; reviewed each term
A25: IMPORTANT: Only the highest single discount applies. Discounts cannot be stacked.
A27: TERM 3 ARRANGEMENTS
A28: Staff children: Term 3 fees fully covered — no payment due.
A29: Non-staff pupils: Fresh termly fee charged for Term 3, plus any arrears from Terms 1 and 2.
A30: Crèche to Nursery 2 (year-round): Term 3 = remaining 2 quarters (Apr–Aug). Crèche: GHS 5,100 (Quarterly: 2,550 × 2 / Monthly: 1,020 × 5 / Lump sum 3% off: 4,947). Nursery: GHS 4,800 (Quarterly: 2,400 × 2 / Monthly: 960 × 5 / Lump sum 3% off: 4,656). Monthly rate = remaining balance ÷ 5 months. All standard options total the same.
A31: KG 1 to Grade 5 (3-term): Standard termly fee applies for Term 3.
A32: All outstanding balances must be cleared before re-enrolment for the 2026/27 academic year.
A33: 5% late payment surcharge applies to arrears carried from Term 2 into Term 3.

Sheet Summary
A1: HIGHCREST SCHOOL — 2025/26 FULL YEAR FEE REGISTER (Terms 1, 2 & 3)
A3: CLASS INFO | E3: TERM 1 | I3: TERM 2 | N3: TERM 3 (TEMPLATE)
A4: Class | B4: Bird House | C4: Enrolled | D4: Annual Fee | E4: T1 Due | F4: T1 Paid | G4: T1 Balance | H4: T1 Rate% | I4: T2 Due | J4: T2 Discount | K4: T2 Paid | L4: T2 Balance | M4: T2 Rate% | N4: T3 Fee | O4: T3 Discount | P4: T3 Arrears | Q4: T3 Net Due
A5: Crèche | B5: Robins | C5: 8 | D5: 10000 | E5: 12495 | F5: 12495 | G5: 0 | H5: =IF(E5=0,1,F5/E5) -> 1 | I5: 15300 | J5: 2805 | K5: 12495 | L5: 0 | M5: =IF(I5-J5=0,1,K5/(I5-J5)) -> 1 | N5: 12750 | O5: 2550 | P5: 0 | Q5: =N5-O5+P5 -> 10200
A6: Nursery 1 | B6: Starlings | C6: 13 | D6: 9400 | E6: 26515 | F6: 21140 | G6: 5375 | H6: =IF(E6=0,1,F6/E6) -> 0.79728456 | I6: 32900 | J6: 8640 | K6: 19820 | L6: 4440 | M6: =IF(I6-J6=0,1,K6/(I6-J6)) -> 0.81698269 | N6: 12000 | O6: 16800 | P6: 4440 | Q6: =N6-O6+P6 -> -360
A7: Nursery 2 | B7: Goldfinches | C7: 12 | D7: 9400 | E7: 22160 | F7: 21260 | G7: 900 | H7: =IF(E7=0,1,F7/E7) -> 0.95938628 | I7: 30800 | J7: 4040 | K7: 26210 | L7: 550 | M7: =IF(I7-J7=0,1,K7/(I7-J7)) -> 0.97944694 | N7: 26400 | O7: 2400 | P7: 550 | Q7: =N7-O7+P7 -> 24550
A8: KG 1 | B8: Kingfishers | C8: 6 | D8: 7350 | E8: 33927.5 | F8: 24522.5 | G8: 9405 | H8: =IF(E8=0,1,F8/E8) -> 0.72279125 | I8: 38810 | J8: 5482.5 | K8: 27395 | L8: 5932.5 | M8: =IF(I8-J8=0,1,K8/(I8-J8)) -> 0.82199385 | N8: 28050 | O8: 5100 | P8: 5932.5 | Q8: =N8-O8+P8 -> 28882.5
A9: KG 2 | B9: Hawks | C9: 10 | D9: 7350 | E9: 8252.5 | F9: 5750 | G9: 2502.5 | H9: =IF(E9=0,1,F9/E9) -> 0.69675856 | I9: 9152.5 | J9: 127.5 | K9: 7972.5 | L9: 1052.5 | M9: =IF(I9-J9=0,1,K9/(I9-J9)) -> 0.8833795 | N9: 7650 | O9: 0 | P9: 1052.5 | Q9: =N9-O9+P9 -> 8702.5
A10: Grade 1 | B10: Skylarks | C10: 10 | D10: 8500 | E10: 25000 | F10: 21716.67 | G10: 3283.33 | H10: =IF(E10=0,1,F10/E10) -> 0.8686668 | I10: 30650 | J10: 4600 | K10: 23772.5 | L10: 2427.5 | M10: =IF(I10-J10=0,1,K10/(I10-J10)) -> 0.91257198 | N10: 30000 | O10: 0 | P10: 2427.5 | Q10: =N10-O10+P10 -> 32427.5
A11: Grade 2 | B11: Kestrels | C11: 8 | D11: 8500 | E11: 25450 | F11: 20350 | G11: 5100 | H11: =IF(E11=0,1,F11/E11) -> 0.79960707 | I11: 23100 | J11: 2150 | K11: 17077.5 | L11: 3872.5 | M11: =IF(I11-J11=0,1,K11/(I11-J11)) -> 0.81515513 | N11: 24000 | O11: 0 | P11: 3872.5 | Q11: =N11-O11+P11 -> 27872.5
A12: Grade 3 | B12: Woodpeckers | C12: 6 | D12: 8500 | E12: 18890 | F12: 10250 | G12: 8640 | H12: =IF(E12=0,1,F12/E12) -> 0.54261514 | I12: 17970 | J12: 3300 | K12: 5350 | L12: 9320 | M12: =IF(I12-J12=0,1,K12/(I12-J12)) -> 0.36468984 | N12: 15000 | O12: 3000 | P12: 9320 | Q12: =N12-O12+P12 -> 21320
A13: Grade 4 | B13: Nightingales | C13: 4 | D13: 8500 | E13: 15700 | F13: 12566.67 | G13: 3133.33 | H13: =IF(E13=0,1,F13/E13) -> 0.80042484 | I13: 11420 | J13: 150 | K13: 8850 | L13: 2420 | M13: =IF(I13-J13=0,1,K13/(I13-J13)) -> 0.78527063 | N13: 12000 | O13: 0 | P13: 2420 | Q13: =N13-O13+P13 -> 14420
A14: Grade 5 | B14: Falcons | C14: 3 | D14: 8500 | E14: 7900 | F14: 5816.67 | G14: 2083.33 | H14: =IF(E14=0,1,F14/E14) -> 0.73628734 | I14: 10000 | J14: 3000 | K14: 7000 | L14: 0 | M14: =IF(I14-J14=0,1,K14/(I14-J14)) -> 1 | N14: 6000 | O14: 3000 | P14: 0 | Q14: =N14-O14+P14 -> 3000
A15: TOTALS | C15: =SUM(C5:C14) -> 80 | E15: =SUM(E5:E14) -> 196290 | F15: =SUM(F5:F14) -> 155867.51 | G15: =SUM(G5:G14) -> 40422.49 | H15: =IF(E15=0,1,F15/E15) -> 0.7940675 | I15: =SUM(I5:I14) -> 220102.5 | J15: =SUM(J5:J14) -> 34295 | K15: =SUM(K5:K14) -> 155942.5 | L15: =SUM(L5:L14) -> 30015 | M15: =IF(I15-J15=0,1,K15/(I15-J15)) -> 0.83926914 | N15: =SUM(N5:N14) -> 173850 | O15: =SUM(O5:O14) -> 32850 | P15: =SUM(P5:P14) -> 30015 | Q15: =SUM(Q5:Q14) -> 171015
A18: ARREARS TRACKER — Pupils with Outstanding Balances at End of Term 2
A19: Arrears added to Term 3 bill. All must be cleared before 2026/27 re-enrolment. Colour: Red = critical (>GHS 3,000) | Amber = high (>GHS 1,000) | Grey = to settle
A20: No. | B20: Pupil Name | C20: Class | D20: T1 Balance | E20: T2 Balance | F20: Arrears into T3 | G20: Discount | H20: Status / Action Required
A21: 1 | B21: Azasoo Jayden-Elyon Elikem | C21: Grade 3 | D21: 2800 | E21: 4300 | F21: 4300 | G21: — | H21: CRITICAL — only GHS 700 paid T1; zero T2
A22: 2 | B22: Ayeh-Kumi Jomari Paakow | C22: KG 1 | D22: 3160 | E22: 4210 | F22: 4210 | G22: — | H22: CRITICAL — prior year BF; growing arrears
A23: 3 | B23: Ayeh-Kumi Fiifi Jody | C23: Nursery 1 | D23: 3600 | E23: 3380 | F23: 3380 | G23: Sibling | H23: CRITICAL — prior year BF GHS 3,820
A24: 4 | B24: Owusu Okyem Emmanuella | C24: Grade 4 | D24: 2600 | E24: 2420 | F24: 2420 | G24: — | H24: HIGH — prior year BF; no T2 fee charged
A25: 5 | B25: Owusu Katakyie Nana Kwame | C25: Grade 3 | D25: 2590 | E25: 2270 | F25: 2270 | G25: Sibling | H25: HIGH — prior year BF GHS 3,140
A26: 6 | B26: Morkeh Michelle | C26: Grade 2 | D26: 3200 | E26: 2122.5 | F26: 1522.5 | G26: — | H26: CRITICAL — never paid T1 or T2
A27: 7 | B27: Ampofo Yirenkyi Papa Kofi | C27: Grade 3 | D27: 1650 | E27: 1650 | F27: 1650 | G27: — | H27: HIGH — prior year BF; no fees charged
A28: 8 | B28: Appiah Zakiel Nana Kwame | C28: Grade 2 | D28: 300 | E28: 1350 | F28: 0 | G28: — | H28: Growing arrears
A29: 9 | B29: Asare Okaine Bismark | C29: Grade 1 | D29: 1200 | E29: 1200 | F29: 1200 | G29: — | H29: T1 partial; no T2 fee charged
A30: 10 | B30: Mensah-Aborampah Ayeyi Yeboah | C30: Grade 3 | D30: 1600 | E30: 1100 | F30: 1100 | G30: — | H30: Consistent partial payer
A31: 11 | B31: Morkeh Bradley | C31: KG 2 | D31: 2422.5 | E31: 922.5 | F31: 422.5 | G31: Sibling | H31: Never paid T1; partial T2
A32: 12 | B32: Appiah Serwaa Senam | C32: KG 1 | D32: 622.5 | E32: 872.5 | F32: 0 | G32: Sibling | H32: Partial payer both terms
... A43: 23 | B43: Kanati Ava Bubune | C43: Nursery 1 | D43: 0 | E43: 0 | F43: 0 | G43: Sibling | H43: Minor balance after credit
B44: TOTAL ARREARS | D44: =SUM(D21:D43) -> 32370 | E44: =SUM(E21:E43) -> 30015 | F44: =SUM(F21:F43) -> 25082.5
B45: 23 pupils with arrears out of 71 enrolled
B47: KEY FAMILY GROUPS (combined arrears):
B48: Ayeh-Kumi (Fiifi Jody + Jomari Paakow) | F48: GHS 7,590
B49: Owusu (Katakyie + Emmanuella) | F49: GHS 4,690
B50: Morkeh (Bradley + Michelle) | F50: GHS 3,045
B51: Mensah-Aborampah (Asa + Ayeyi) | F51: GHS 1,950

Sheet Crèche - Robins
A1: Crèche: Robins — Community | Cheerfulness | Annual: GHS 10,000 | Termly: GHS 2,550
A3: PUPIL DETAILS | D3: TERM 1 (COMPLETED) | H3: TERM 2 (COMPLETED) | M3: TERM 3 (ACTIVE — covers remainder of year; arrears included) | Q3: NOTES
A4: No. | B4: Pupil Name | C4: Discount Type | D4: T1 Fee | E4: T1 Arrears BF | F4: T1 Paid | G4: T1 Balance | H4: T2 Fee | I4: T2 Arrears BF | J4: T2 Discount | K4: T2 Paid | L4: T2 Balance | M4: T3 Fee | N4: T3 Discount | O4: T3 Paid | P4: T3 Balance | Q4: Remarks / Waiver Notes
A5: 1 | B5: Agyapong Awuraba Avril Phoebe | C5: Sibling | D5: 2422.5 | F5: 2422.5 | G5: =IF(B5="","",IF(D5="",0,D5)+IF(E5="",0,E5)-IF(F5="",0,F5)) -> 0 | H5: 2550 | J5: 127.5 | K5: 2422.5 | L5: =IF(B5="","",IF(H5="",0,H5)+IF(I5="",0,I5)-IF(J5="",0,J5)-IF(K5="",0,K5)) -> 0 | M5: 0 | N5: 0 | O5: =SUMIF('Crèche - Payments'!C5:C154,B5,'Crèche - Payments'!F5:F154) -> 0 | P5: =IF(B5="","",IF(M5="",0,M5)-IF(N5="",0,N5)+IF(L5<0,0,IF(L5="",0,L5))-IF(O5="",0,O5)) -> 0 | Q5: T3 options: Lump GHS 4,947 (by 21 Apr) / Quarterly GHS 2,550 × 2 / Monthly GHS 1,020 × 5
A6: 2 | B6: Ansu-Boamah Othniel | D6: 2550 | F6: 2550 | G6: =IF(B6="","",IF(D6="",0,D6)+IF(E6="",0,E6)-IF(F6="",0,F6)) -> 0 | H6: 2550 | K6: 2550 | L6: =IF(B6="","",IF(H6="",0,H6)+IF(I6="",0,I6)-IF(J6="",0,J6)-IF(K6="",0,K6)) -> 0 | M6: 5100 | O6: =SUMIF('Crèche - Payments'!C5:C154,B6,'Crèche - Payments'!F5:F154) -> 5100 | P6: =IF(B6="","",IF(M6="",0,M6)-IF(N6="",0,N6)+IF(L6<0,0,IF(L6="",0,L6))-IF(O6="",0,O6)) -> 0 | Q6: T3 options: Lump GHS 4,947 (by 21 Apr) / Quarterly GHS 2,550 × 2 / Monthly GHS 1,020 × 5
A7: 3 | B7: Diko Nana Pokuah Elshaddai | C7: Sibling | D7: 2422.5 | F7: 2422.5 | G7: =IF(B7="","",IF(D7="",0,D7)+IF(E7="",0,E7)-IF(F7="",0,F7)) -> 0 | H7: 2550 | J7: 127.5 | K7: 2422.5 | L7: =IF(B7="","",IF(H7="",0,H7)+IF(I7="",0,I7)-IF(J7="",0,J7)-IF(K7="",0,K7)) -> 0 | M7: 2422.5 | N7: 127.5 | O7: =SUMIF('Crèche - Payments'!C5:C154,B7,'Crèche - Payments'!F5:F154) -> 2422.5 | P7: 0 | Q7: T3 options: Lump GHS 4,947 (by 21 Apr) / Quarterly GHS 2,550 × 2 / Monthly GHS 1,020 × 5
A8: 4 | B8: Lartey Akua Victoria | C8: Staff Child | G8: =IF(B8="","",IF(D8="",0,D8)+IF(E8="",0,E8)-IF(F8="",0,F8)) -> 0 | H8: 2550 | J8: 2550 | L8: =IF(B8="","",IF(H8="",0,H8)+IF(I8="",0,I8)-IF(J8="",0,J8)-IF(K8="",0,K8)) -> 0 | M8: 5100 | N8: 5100 | O8: =SUMIF('Crèche - Payments'!C5:C154,B8,'Crèche - Payments'!F5:F154) -> 0 | P8: =IF(B8="","",IF(M8="",0,M8)-IF(N8="",0,N8)+IF(L8<0,0,IF(L8="",0,L8))-IF(O8="",0,O8)) -> 0 | Q8: Staff child — fees fully covered all terms
A9: 5 | B9: Nera Jasmine Owusu Mensah | D9: 2550 | F9: 2550 | G9: =IF(B9="","",IF(D9="",0,D9)+IF(E9="",0,E9)-IF(F9="",0,F9)) -> 0 | H9: 2550 | K9: 2550 | L9: =IF(B9="","",IF(H9="",0,H9)+IF(I9="",0,I9)-IF(J9="",0,J9)-IF(K9="",0,K9)) -> 0 | M9: 5100 | O9: 5100 | P9: =IF(B9="","",IF(M9="",0,M9)-IF(N9="",0,N9)+IF(L9<0,0,IF(L9="",0,L9))-IF(O9="",0,O9)) -> 0 | Q9: T3 options: Lump GHS 4,947 (by 21 Apr) / Quarterly GHS 2,550 × 2 / Monthly GHS 1,020 × 5
A10: 6 | B10: Twum Kwao Barima | D10: 2550 | F10: 2550 | G10: =IF(B10="","",IF(D10="",0,D10)+IF(E10="",0,E10)-IF(F10="",0,F10)) -> 0 | H10: 2550 | K10: 2550 | L10: =IF(B10="","",IF(H10="",0,H10)+IF(I10="",0,I10)-IF(J10="",0,J10)-IF(K10="",0,K10)) -> 0 | M10: 5100 | O10: 2550 | P10: =IF(B10="","",IF(M10="",0,M10)-IF(N10="",0,N10)+IF(L10<0,0,IF(L10="",0,L10))-IF(O10="",0,O10)) -> 2550 | Q10: T3 options: Lump GHS 4,947 (by 21 Apr) / Quarterly GHS 2,550 × 2 / Monthly GHS 1,020 × 5
A11: 7 | B11: Adelia Alhassan | G11: =IF(B11="","",0) -> 0 | L11: =IF(B11="","",0) -> 0 | M11: 4842.5 | N11: 127.5 | O11: 5422.5 | P11: -580
A12: 8 | B12: Arthur Janice Ayeyi | G12: =IF(B12="","",0) -> 0 | I12: 0 | L12: =IF(B12="","",0) -> 0 | M12: 6250 | O12: 6250 | P12: =IF(B12="","",IF(M12="",0,M12)-IF(N12="",0,N12)+IF(L12<0,0,IF(L12="",0,L12))-IF(O12="",0,O12)) -> 0
A13: 9 | G13: =IF(B13="","",0) | L13: =IF(B13="","",0) | P13: =IF(B13="","",0)
A14: 10 | G14: =IF(B14="","",0) | L14: =IF(B14="","",0) | P14: =IF(B14="","",0)
A15: 11 | G15: =IF(B15="","",0) | L15: =IF(B15="","",0) | P15: =IF(B15="","",0)
A16: 12 | G16: =IF(B16="","",0) | L16: =IF(B16="","",0) | P16: =IF(B16="","",0)
A17: 13 | G17: =IF(B17="","",0) | L17: =IF(B17="","",0) | P17: =IF(B17="","",0)
A18: 14 | G18: =IF(B18="","",0) | L18: =IF(B18="","",0) | P18: =IF(B18="","",0)
A19: 15 | G19: =IF(B19="","",0) | L19: =IF(B19="","",0) | P19: =IF(B19="","",0)
A20: 16 | G20: =IF(B20="","",0) | L20: =IF(B20="","",0) | P20: =IF(B20="","",0)
B21: TOTALS | D21: =SUM(D5:D20) -> 12495 | E21: =SUM(E5:E20) -> 0 | F21: =SUM(F5:F20) -> 12495 | G21: =SUM(G5:G20) -> 0 | H21: =SUM(H5:H20) -> 15300 | I21: =SUM(I5:I20) -> 0 | J21: =SUM(J5:J20) -> 2805 | K21: =SUM(K5:K20) -> 12495 | ... P21: =SUM(P5:P20) -> 1970
B22: Collection Rate: | F22: T1: | G22: =IF(D21+E21=0,1,F21/(D21+E21)) -> 1 | K22: T2: | L22: =IF(H21+I21-J21=0,1,K21/(H21+I21-J21)) -> 1 | O22: =SUMIF('Crèche - Payments'!C5:C154,B22,'Crèche - Payments'!F5:F154) -> 0

Sheet Crèche - Payments
A1: Crèche: Robins — PAYMENT RECEIPTS LOG (Term 3, 2025/26: 21 Apr – 24 Jul 2026) | P1: Agyapong Awuraba Avril Phoebe
A2: Payment deadline: 30 June 2026 | Enter one row per payment | T3 Paid on class register auto-updates via SUMIFS | P2: Ansu-Boamah Othniel
A3: TRANSACTION DETAILS | G3: PAYMENT | J3: VERIFICATION | P3: Diko Nana Pokuah Elshaddai
A4: Date | B4: Receipt No. | C4: Pupil Name | D4: Term | E4: Week | F4: Amount (GHS) | G4: Payment Method | H4: Received By | I4: Running Total | J4: Verified | K4: Notes | P4: Lartey Akua Victoria
A5: 46120 | B5: 1031 | C5: Owusu Mensah Nera Jasmine | D5: Term 3 | F5: 2000 | G5: MTN MoMo | H5: Other | I5: =IF(F5="","",F5) -> 2000 | P5: Owusu Mensah Nera Jasmine
A6: 46120 | B6: 1032 | C6: Arthur Janice Ayeyi | D6: Term 3 | F6: 5000 | G6: MTN MoMo | H6: Other | I6: =IF(F6="","",IF(I5="",F6,I5+F6)) -> 7000 | P6: Twum Kwao Barima
A7: 46121 | B7: 1033 | C7: Arthur Janice Ayeyi | D7: Term 3 | F7: 1250 | G7: MTN MoMo | H7: Other | I7: =IF(F7="","",IF(I6="",F7,I6+F7)) -> 8250
A8: 20/24/2026 | B8: 1043 | C8: Twum Kwao Barima | D8: Term 3 | E8: Wk 1 (21 Apr) | F8: 2550 | G8: Cash | H8: Dorcas Matilda Akosua Kusi | I8: =IF(F8="","",IF(I7="",F8,I7+F8)) -> 10800
A9: 46140 | B9: 1057 | C9: Ansu-Boamah Othniel | D9: Term 3 | E9: Wk 2 (28 Apr) | F9: 2110.5 | G9: MTN MoMo | H9: Dorcas Matilda Akosua Kusi | I9: =IF(F9="","",IF(I8="",F9,I8+F9)) -> 12910.5
A10: 46167 | B10: 1086 | C10: Ansu-Boamah Othniel | D10: Term 3 | E10: Wk 6 (26 May) | F10: 1000 | G10: MTN MoMo | H10: Dorcas Matilda Akosua Kusi | I10: =IF(F10="","",IF(I9="",F10,I9+F10)) -> 13910.5
A11: 46167 | B11: 1087 | C11: Alhassan Adelia | D11: Term 3 | E11: Wk 6 (26 May) | F11: 1000 | G11: MTN MoMo | H11: Dorcas Matilda Akosua Kusi | I11: =IF(F11="","",IF(I10="",F11,I10+F11)) -> 14910.5
A12: 46168 | B12: 1090 | C12: Owusu Mensah Nera Jasmine | D12: Term 3 | E12: Wk 6 (26 May) | F12: 1000 | G12: Cash | H12: Other | I12: =IF(F12="","",IF(I11="",F12,I11+F12)) -> 15910.5
A13: 46171 | B13: 1095 | C13: Diko Nana Pokuah Elshaddai | D13: Term 3 | E13: Wk 6 (26 May) | F13: 1500 | G13: Bank Transfer | H13: Dorcas Matilda Akosua Kusi | I13: =IF(F13="","",IF(I12="",F13,I12+F13)) -> 17410.5
A14: 46188 | B14: 1116 | C14: Alhassan Adelia | D14: Term 3 | E14: Wk 9 (16 Jun) | F14: 2400 | G14: MTN MoMo | H14: Other | I14: =IF(F14="","",IF(I13="",F14,I13+F14)) -> 19810.5
A15: 46209 | B15: 1124 | C15: Ansu-Boamah Othniel | D15: Term 3 | E15: Wk 12 (07 Jul) | F15: 1989.5 | G15: MTN MoMo | H15: Other | I15: =IF(F15="","",IF(I14="",F15,I14+F15)) -> 21800
A16: 46241 | B16: 1132 | C16: Diko Nana Pokuah Elshaddai | D16: Term 3 | E16: Wk 12 (07 Jul) | F16: 922.5 | G16: Bank Transfer | H16: Dorcas Matilda Akosua Kusi | I16: =IF(F16="","",IF(I15="",F16,I15+F16)) -> 22722.5
A17: 46217 | B17: 1139 | C17: Owusu Mensah Nera Jasmine | D17: Term 3 | E17: Wk 13 (14 Jul) | F17: 2100 | G17: Bank Transfer | H17: Other | I17: =IF(F17="","",IF(I16="",F17,I16+F17)) -> 24822.5
I18: =IF(F18="","",IF(I17="",F18,I17+F18))
I19: =IF(F19="","",IF(I18="",F19,I18+F19))
I20: =IF(F20="","",IF(I19="",F20,I19+F20))
I21: =IF(F21="","",IF(I20="",F21,I20+F21))
I22: =IF(F22="","",IF(I21="",F22,I21+F22))
I23: =IF(F23="","",IF(I22="",F23,I22+F23))
I24: =IF(F24="","",IF(I23="",F24,I23+F24))
I25: =IF(F25="","",IF(I24="",F25,I24+F25))
I26: =IF(F26="","",IF(I25="",F26,I25+F26))
I27: =IF(F27="","",IF(I26="",F27,I26+F27))
I28: =IF(F28="","",IF(I27="",F28,I27+F28))
I29: =IF(F29="","",IF(I28="",F29,I28+F29))
... I154: =IF(F154="","",IF(I153="",F154,I153+F154))
A157: WEEKLY COLLECTION SUMMARY (auto-calculated from payment log)
A158: Week | B158: Week Starting | C158: Entries | D158: Cash | E158: MoMo (All) | F158: Bank Transfer | G158: Cheque | H158: Week Total | I158: Cumulative | J158: vs Deadline | K158: Notes
A159: Wk 1 (21 Apr) | B159: 46133 | C159: =COUNTIF(E5:E154,"Wk 1 (21 Apr)") -> 1 | D159: =SUMPRODUCT((E5:E154="Wk 1 (21 Apr)")*(G5:G154="Cash")*(F5:F154)) -> 2550 | E159: =SUMPRODUCT((E5:E154="Wk 1 (21 Apr)")*((G5:G154="MTN MoMo")+(G5:G154="Vodafone Cash")+(G5:G154="AirtelTigo Money"))*(F5:F154)) -> 0 | F159: =SUMPRODUCT((E5:E154="Wk 1 (21 Apr)")*(G5:G154="Bank Transfer")*(F5:F154)) -> 0 | G159: =SUMPRODUCT((E5:E154="Wk 1 (21 Apr)")*(G5:G154="Cheque")*(F5:F154)) -> 0 | H159: =SUM(D159:G159) -> 2550 | I159: =H159 -> 2550
A160: Wk 2 (28 Apr) | B160: 46140 | C160: =COUNTIF(E5:E154,"Wk 2 (28 Apr)") -> 1 | D160: =SUMPRODUCT((E5:E154="Wk 2 (28 Apr)")*(G5:G154="Cash")*(F5:F154)) -> 0 | E160: =SUMPRODUCT((E5:E154="Wk 2 (28 Apr)")*((G5:G154="MTN MoMo")+(G5:G154="Vodafone Cash")+(G5:G154="AirtelTigo Money"))*(F5:F154)) -> 2110.5 | F160: =SUMPRODUCT((E5:E154="Wk 2 (28 Apr)")*(G5:G154="Bank Transfer")*(F5:F154)) -> 0 | G160: =SUMPRODUCT((E5:E154="Wk 2 (28 Apr)")*(G5:G154="Cheque")*(F5:F154)) -> 0 | H160: =SUM(D160:G160) -> 2110.5 | I160: =I159+H160 -> 4660.5
A161: Wk 3 (05 May) | B161: 46147 | C161: =COUNTIF(E5:E154,"Wk 3 (05 May)") -> 0 | D161: =SUMPRODUCT((E5:E154="Wk 3 (05 May)")*(G5:G154="Cash")*(F5:F154)) -> 0 | E161: =SUMPRODUCT((E5:E154="Wk 3 (05 May)")*((G5:G154="MTN MoMo")+(G5:G154="Vodafone Cash")+(G5:G154="AirtelTigo Money"))*(F5:F154)) -> 0 | F161: =SUMPRODUCT((E5:E154="Wk 3 (05 May)")*(G5:G154="Bank Transfer")*(F5:F154)) -> 0 | G161: =SUMPRODUCT((E5:E154="Wk 3 (05 May)")*(G5:G154="Cheque")*(F5:F154)) -> 0 | H161: =SUM(D161:G161) -> 0 | I161: =I160+H161 -> 4660.5
A162: Wk 4 (12 May) | B162: 46154 | C162: =COUNTIF(E5:E154,"Wk 4 (12 May)") -> 0 | D162: =SUMPRODUCT((E5:E154="Wk 4 (12 May)")*(G5:G154="Cash")*(F5:F154)) -> 0 | E162: =SUMPRODUCT((E5:E154="Wk 4 (12 May)")*((G5:G154="MTN MoMo")+(G5:G154="Vodafone Cash")+(G5:G154="AirtelTigo Money"))*(F5:F154)) -> 0 | F162: =SUMPRODUCT((E5:E154="Wk 4 (12 May)")*(G5:G154="Bank Transfer")*(F5:F154)) -> 0 | G162: =SUMPRODUCT((E5:E154="Wk 4 (12 May)")*(G5:G154="Cheque")*(F5:F154)) -> 0 | H162: =SUM(D162:G162) -> 0 | I162: =I161+H162 -> 4660.5
A163: Wk 5 (19 May) | B163: 46161 | C163: =COUNTIF(E5:E154,"Wk 5 (19 May)") -> 0 | D163: =SUMPRODUCT((E5:E154="Wk 5 (19 May)")*(G5:G154="Cash")*(F5:F154)) -> 0 | E163: =SUMPRODUCT((E5:E154="Wk 5 (19 May)")*((G5:G154="MTN MoMo")+(G5:G154="Vodafone Cash")+(G5:G154="AirtelTigo Money"))*(F5:F154)) -> 0 | F163: =SUMPRODUCT((E5:E154="Wk 5 (19 May)")*(G5:G154="Bank Transfer")*(F5:F154)) -> 0 | G163: =SUMPRODUCT((E5:E154="Wk 5 (19 May)")*(G5:G154="Cheque")*(F5:F154)) -> 0 | H163: =SUM(D163:G163) -> 0 | I163: =I162+H163 -> 4660.5
A164: Wk 6 (26 May) | B164: 46168 | C164: =COUNTIF(E5:E154,"Wk 6 (26 May)") -> 4 | D164: =SUMPRODUCT((E5:E154="Wk 6 (26 May)")*(G5:G154="Cash")*(F5:F154)) -> 1000 | E164: =SUMPRODUCT((E5:E154="Wk 6 (26 May)")*((G5:G154="MTN MoMo")+(G5:G154="Vodafone Cash")+(G5:G154="AirtelTigo Money"))*(F5:F154)) -> 2000 | F164: =SUMPRODUCT((E5:E154="Wk 6 (26 May)")*(G5:G154="Bank Transfer")*(F5:F154)) -> 1500 | G164: =SUMPRODUCT((E5:E154="Wk 6 (26 May)")*(G5:G154="Cheque")*(F5:F154)) -> 0 | H164: =SUM(D164:G164) -> 4500 | I164: =I163+H164 -> 9160.5
A165: Wk 7 (02 Jun) | B165: 46175 | C165: =COUNTIF(E5:E154,"Wk 7 (02 Jun)") -> 0 | D165: =SUMPRODUCT((E5:E154="Wk 7 (02 Jun)")*(G5:G154="Cash")*(F5:F154)) -> 0 | E165: =SUMPRODUCT((E5:E154="Wk 7 (02 Jun)")*((G5:G154="MTN MoMo")+(G5:G154="Vodafone Cash")+(G5:G154="AirtelTigo Money"))*(F5:F154)) -> 0 | F165: =SUMPRODUCT((E5:E154="Wk 7 (02 Jun)")*(G5:G154="Bank Transfer")*(F5:F154)) -> 0 | G165: =SUMPRODUCT((E5:E154="Wk 7 (02 Jun)")*(G5:G154="Cheque")*(F5:F154)) -> 0 | H165: =SUM(D165:G165) -> 0 | I165: =I164+H165 -> 9160.5
A166: Wk 8 (09 Jun) | B166: 46182 | C166: =COUNTIF(E5:E154,"Wk 8 (09 Jun)") -> 0 | D166: =SUMPRODUCT((E5:E154="Wk 8 (09 Jun)")*(G5:G154="Cash")*(F5:F154)) -> 0 | E166: =SUMPRODUCT((E5:E154="Wk 8 (09 Jun)")*((G5:G154="MTN MoMo")+(G5:G154="Vodafone Cash")+(G5:G154="AirtelTigo Money"))*(F5:F154)) -> 0 | F166: =SUMPRODUCT((E5:E154="Wk 8 (09 Jun)")*(G5:G154="Bank Transfer")*(F5:F154)) -> 0 | G166: =SUMPRODUCT((E5:E154="Wk 8 (09 Jun)")*(G5:G154="Cheque")*(F5:F154)) -> 0 | H166: =SUM(D166:G166) -> 0 | I166: =I165+H166 -> 9160.5
A167: Wk 9 (16 Jun) | B167: 46189 | C167: =COUNTIF(E5:E154,"Wk 9 (16 Jun)") -> 1 | D167: =SUMPRODUCT((E5:E154="Wk 9 (16 Jun)")*(G5:G154="Cash")*(F5:F154)) -> 0 | E167: =SUMPRODUCT((E5:E154="Wk 9 (16 Jun)")*((G5:G154="MTN MoMo")+(G5:G154="Vodafone Cash")+(G5:G154="AirtelTigo Money"))*(F5:F154)) -> 2400 | F167: =SUMPRODUCT((E5:E154="Wk 9 (16 Jun)")*(G5:G154="Bank Transfer")*(F5:F154)) -> 0 | G167: =SUMPRODUCT((E5:E154="Wk 9 (16 Jun)")*(G5:G154="Cheque")*(F5:F154)) -> 0 | H167: =SUM(D167:G167) -> 2400 | I167: =I166+H167 -> 11560.5
A168: Wk 10 (23 Jun) | B168: 46196 | C168: =COUNTIF(E5:E154,"Wk 10 (23 Jun)") -> 0 | D168: =SUMPRODUCT((E5:E154="Wk 10 (23 Jun)")*(G5:G154="Cash")*(F5:F154)) -> 0 | E168: =SUMPRODUCT((E5:E154="Wk 10 (23 Jun)")*((G5:G154="MTN MoMo")+(G5:G154="Vodafone Cash")+(G5:G154="AirtelTigo Money"))*(F5:F154)) -> 0 | F168: =SUMPRODUCT((E5:E154="Wk 10 (23 Jun)")*(G5:G154="Bank Transfer")*(F5:F154)) -> 0 | G168: =SUMPRODUCT((E5:E154="Wk 10 (23 Jun)")*(G5:G154="Cheque")*(F5:F154)) -> 0 | H168: =SUM(D168:G168) -> 0 | I168: =I167+H168 -> 11560.5
A169: Wk 11 (30 Jun) | B169: 46203 | C169: =COUNTIF(E5:E154,"Wk 11 (30 Jun)") -> 0 | D169: =SUMPRODUCT((E5:E154="Wk 11 (30 Jun)")*(G5:G154="Cash")*(F5:F154)) -> 0 | E169: =SUMPRODUCT((E5:E154="Wk 11 (30 Jun)")*((G5:G154="MTN MoMo")+(G5:G154="Vodafone Cash")+(G5:G154="AirtelTigo Money"))*(F5:F154)) -> 0 | F169: =SUMPRODUCT((E5:E154="Wk 11 (30 Jun)")*(G5:G154="Bank Transfer")*(F5:F154)) -> 0 | G169: =SUMPRODUCT((E5:E154="Wk 11 (30 Jun)")*(G5:G154="Cheque")*(F5:F154)) -> 0 | H169: =SUM(D169:G169) -> 0 | I169: =I168+H169 -> 11560.5
A170: Wk 12 (07 Jul) | B170: 46210 | C170: =COUNTIF(E5:E154,"Wk 12 (07 Jul)") -> 2 | D170: =SUMPRODUCT((E5:E154="Wk 12 (07 Jul)")*(G5:G154="Cash")*(F5:F154)) -> 0 | E170: =SUMPRODUCT((E5:E154="Wk 12 (07 Jul)")*((G5:G154="MTN MoMo")+(G5:G154="Vodafone Cash")+(G5:G154="AirtelTigo Money"))*(F5:F154)) -> 1989.5 | F170: =SUMPRODUCT((E5:E154="Wk 12 (07 Jul)")*(G5:G154="Bank Transfer")*(F5:F154)) -> 922.5 | G170: =SUMPRODUCT((E5:E154="Wk 12 (07 Jul)")*(G5:G154="Cheque")*(F5:F154)) -> 0 | H170: =SUM(D170:G170) -> 2912 | I170: =I169+H170 -> 14472.5 | J170: PAST DEADLINE
A171: Wk 13 (14 Jul) | B171: 46217 | C171: =COUNTIF(E5:E154,"Wk 13 (14 Jul)") -> 1 | D171: =SUMPRODUCT((E5:E154="Wk 13 (14 Jul)")*(G5:G154="Cash")*(F5:F154)) -> 0 | E171: =SUMPRODUCT((E5:E154="Wk 13 (14 Jul)")*((G5:G154="MTN MoMo")+(G5:G154="Vodafone Cash")+(G5:G154="AirtelTigo Money"))*(F5:F154)) -> 0 | F171: =SUMPRODUCT((E5:E154="Wk 13 (14 Jul)")*(G5:G154="Bank Transfer")*(F5:F154)) -> 2100 | G171: =SUMPRODUCT((E5:E154="Wk 13 (14 Jul)")*(G5:G154="Cheque")*(F5:F154)) -> 0 | H171: =SUM(D171:G171) -> 2100 | I171: =I170+H171 -> 16572.5 | J171: PAST DEADLINE
A172: Wk 14 (21 Jul) | B172: 46224 | C172: =COUNTIF(E5:E154,"Wk 14 (21 Jul)") -> 0 | D172: =SUMPRODUCT((E5:E154="Wk 14 (21 Jul)")*(G5:G154="Cash")*(F5:F154)) -> 0 | E172: =SUMPRODUCT((E5:E154="Wk 14 (21 Jul)")*((G5:G154="MTN MoMo")+(G5:G154="Vodafone Cash")+(G5:G154="AirtelTigo Money"))*(F5:F154)) -> 0 | F172: =SUMPRODUCT((E5:E154="Wk 14 (21 Jul)")*(G5:G154="Bank Transfer")*(F5:F154)) -> 0 | G172: =SUMPRODUCT((E5:E154="Wk 14 (21 Jul)")*(G5:G154="Cheque")*(F5:F154)) -> 0 | H172: =SUM(D172:G172) -> 0 | I172: =I171+H172 -> 16572.5 | J172: PAST DEADLINE
A173: TERM 3 TOTAL | C173: =SUM(C159:C172) -> 10 | D173: =SUM(D159:D172) -> 3550 | E173: =SUM(E159:E172) -> 8500 | F173: =SUM(F159:F172) -> 4522.5 | G173: =SUM(G159:G172) -> 0 | H173: =SUM(H159:H172) -> 16572.5
A176: MONTHLY COLLECTION SUMMARY
A177: Month | B177: No. of Payments | C177: Cash | D177: MoMo (All) | E177: Bank Transfer | F177: Cheque | G177: Month Total | H177: Cumulative | I177: Target % | J177: Actual % | K177: Notes
A178: Apr | B178: =SUMPRODUCT((MONTH(A5:A154)=4)*(A5:A154<>"")) -> #VALUE! | C178: =SUMPRODUCT((MONTH(A5:A154)=4)*(G5:G154="Cash")*(F5:F154)) -> #VALUE! | D178: =SUMPRODUCT((MONTH(A5:A154)=4)*((G5:G154="MTN MoMo")+(G5:G154="Vodafone Cash")+(G5:G154="AirtelTigo Money"))*(F5:F154)) -> #VALUE! | E178: =SUMPRODUCT((MONTH(A5:A154)=4)*(G5:G154="Bank Transfer")*(F5:F154)) -> #VALUE! | F178: =SUMPRODUCT((MONTH(A5:A154)=4)*(G5:G154="Cheque")*(F5:F154)) -> #VALUE! | G178: =SUM(C178:F178) -> #VALUE! | H178: =G178 -> #VALUE! | I178: 0.3
A179: May | B179: =SUMPRODUCT((MONTH(A5:A154)=5)*(A5:A154<>"")) -> #VALUE! | C179: =SUMPRODUCT((MONTH(A5:A154)=5)*(G5:G154="Cash")*(F5:F154)) -> #VALUE! | D179: =SUMPRODUCT((MONTH(A5:A154)=5)*((G5:G154="MTN MoMo")+(G5:G154="Vodafone Cash")+(G5:G154="AirtelTigo Money"))*(F5:F154)) -> #VALUE! | E179: =SUMPRODUCT((MONTH(A5:A154)=5)*(G5:G154="Bank Transfer")*(F5:F154)) -> #VALUE! | F179: =SUMPRODUCT((MONTH(A5:A154)=5)*(G5:G154="Cheque")*(F5:F154)) -> #VALUE! | G179: =SUM(C179:F179) -> #VALUE! | H179: =H178+G179 -> #VALUE! | I179: 0.65
A180: Jun | B180: =SUMPRODUCT((MONTH(A5:A154)=6)*(A5:A154<>"")) -> #VALUE! | C180: =SUMPRODUCT((MONTH(A5:A154)=6)*(G5:G154="Cash")*(F5:F154)) -> #VALUE! | D180: =SUMPRODUCT((MONTH(A5:A154)=6)*((G5:G154="MTN MoMo")+(G5:G154="Vodafone Cash")+(G5:G154="AirtelTigo Money"))*(F5:F154)) -> #VALUE! | E180: =SUMPRODUCT((MONTH(A5:A154)=6)*(G5:G154="Bank Transfer")*(F5:F154)) -> #VALUE! | F180: =SUMPRODUCT((MONTH(A5:A154)=6)*(G5:G154="Cheque")*(F5:F154)) -> #VALUE! | G180: =SUM(C180:F180) -> #VALUE! | H180: =H179+G180 -> #VALUE! | I180: 1
A181: Jul | B181: =SUMPRODUCT((MONTH(A5:A154)=7)*(A5:A154<>"")) -> #VALUE! | C181: =SUMPRODUCT((MONTH(A5:A154)=7)*(G5:G154="Cash")*(F5:F154)) -> #VALUE! | D181: =SUMPRODUCT((MONTH(A5:A154)=7)*((G5:G154="MTN MoMo")+(G5:G154="Vodafone Cash")+(G5:G154="AirtelTigo Money"))*(F5:F154)) -> #VALUE! | E181: =SUMPRODUCT((MONTH(A5:A154)=7)*(G5:G154="Bank Transfer")*(F5:F154)) -> #VALUE! | F181: =SUMPRODUCT((MONTH(A5:A154)=7)*(G5:G154="Cheque")*(F5:F154)) -> #VALUE! | G181: =SUM(C181:F181) -> #VALUE! | H181: =H180+G181 -> #VALUE! | I181: 1
A182: TOTAL | B182: =SUM(B178:B181) -> #VALUE! | C182: =SUM(C178:C181) -> #VALUE! | D182: =SUM(D178:D181) -> #VALUE! | E182: =SUM(E178:E181) -> #VALUE! | F182: =SUM(F178:F181) -> #VALUE! | G182: =SUM(G178:G181) -> #VALUE!

Sheet Nursery 1 - Starlings
A1: Nursery 1: Starlings — Teamwork | Adaptability | Annual: GHS 9,400 | Termly: GHS 2,400
A3: PUPIL DETAILS | D3: TERM 1 (COMPLETED) | H3: TERM 2 (COMPLETED) | M3: TERM 3 (ACTIVE — covers remainder of year; arrears included) | Q3: NOTES
A4: No. | B4: Pupil Name | C4: Discount Type | D4: T1 Fee | E4: T1 Arrears BF | F4: T1 Paid | G4: T1 Balance | H4: T2 Fee | I4: T2 Arrears BF | J4: T2 Discount | K4: T2 Paid | L4: T2 Balance | M4: T3 Fee | N4: T3 Discount | O4: T3 Paid | P4: T3 Balance | Q4: Remarks / Waiver Notes
A5: 1 | B5: Appiah Eno | C5: Staff Child | D5: 2295 | F5: 1800 | G5: =IF(B5="","",IF(D5="",0,D5)+IF(E5="",0,E5)-IF(F5="",0,F5)) -> 495 | H5: 2400 | J5: 240 | K5: 2160 | L5: =IF(B5="","",IF(H5="",0,H5)+IF(I5="",0,I5)-IF(J5="",0,J5)-IF(K5="",0,K5)) -> 0 | M5: 2160 | N5: 120 | O5: 2160 | P5: 0 | Q5: Staff child — T1 partial payment (GHS 495 short); T2 arrears GHS 360
A6: 2 | B6: Ayeh-Kumi Fiifi Jody | C6: Sibling | D6: 2280 | E6: 3820 | F6: 2500 | G6: =IF(B6="","",IF(D6="",0,D6)+IF(E6="",0,E6)-IF(F6="",0,F6)) -> 3600 | H6: 2400 | I6: 3100 | J6: 120 | K6: 2000 | L6: =IF(B6="","",IF(H6="",0,H6)+IF(I6="",0,I6)-IF(J6="",0,J6)-IF(K6="",0,K6)) -> 3380 | M6: 2280 | N6: 240 | O6: =SUMIF('Nursery 1 - Payments'!C5:C154,B6,'Nursery 1 - Payments'!F5:F154) -> 2500 | P6: =IF(B6="","",IF(M6="",0,M6)-IF(N6="",0,N6)+IF(L6<0,0,IF(L6="",0,L6))-IF(O6="",0,O6)) -> 2920 | Q6: Sibling discount — chronic arrears carried from prior year; GHS 3,820 BF into T1
A7: 3 | B7: Bakari Kuuku Curtis | C7: Sibling | D7: 2280 | F7: 2280 | G7: =IF(B7="","",IF(D7="",0,D7)+IF(E7="",0,E7)-IF(F7="",0,F7)) -> 0 | H7: 2400 | J7: 120 | K7: 2280 | L7: =IF(B7="","",IF(H7="",0,H7)+IF(I7="",0,I7)-IF(J7="",0,J7)-IF(K7="",0,K7)) -> 0 | M7: 2400 | N7: 120 | O7: =SUMIF('Nursery 1 - Payments'!C5:C154,B7,'Nursery 1 - Payments'!F5:F154) -> 2280 | P7: =IF(B7="","",IF(M7="",0,M7)-IF(N7="",0,N7)+IF(L7<0,0,IF(L7="",0,L7))-IF(O7="",0,O7)) -> 0 | Q7: T3 options: Lump GHS 4,656 (by 21 Apr) / Quarterly GHS 2,400 × 2 / Monthly GHS 960 × 5
A8: 4 | B8: Benneh Laura | M8: 2400 | N8: 2400 | O8: 0 | P8: 0 | Q8: Staff child — T1 partial; T2 settled
A9: 5 | B9: Boamah Nakie Pearl | C9: Staff Child | D9: 800 | F9: 450 | G9: =IF(B9="","",IF(D9="",0,D9)+IF(E9="",0,E9)-IF(F9="",0,F9)) -> 350 | H9: 2400 | I9: 350 | J9: 2400 | L9: =IF(B9="","",IF(H9="",0,H9)+IF(I9="",0,I9)-IF(J9="",0,J9)-IF(K9="",0,K9)) -> 350 | M9: 2400 | N9: 2400 | O9: =SUMIF('Nursery 1 - Payments'!C5:C154,B9,'Nursery 1 - Payments'!F5:F154) -> 0 | P9: =IF(B9="","",IF(M9="",0,M9)-IF(N9="",0,N9)+IF(L9<0,0,IF(L9="",0,L9))-IF(O9="",0,O9)) -> 350 | Q9: Staff child — T1 partial (GHS 350 outstanding); T2 arrears persisting
A10: 6 | B10: Boamah Nakour Perpetual | C10: Staff Child | D10: 800 | F10: 450 | G10: =IF(B10="","",IF(D10="",0,D10)+IF(E10="",0,E10)-IF(F10="",0,F10)) -> 350 | H10: 2400 | I10: 350 | J10: 2400 | L10: =IF(B10="","",IF(H10="",0,H10)+IF(I10="",0,I10)-IF(J10="",0,J10)-IF(K10="",0,K10)) -> 350 | M10: 2400 | N10: 2400 | O10: =SUMIF('Nursery 1 - Payments'!C5:C154,B10,'Nursery 1 - Payments'!F5:F154) -> 0 | P10: =IF(B10="","",IF(M10="",0,M10)-IF(N10="",0,N10)+IF(L10<0,0,IF(L10="",0,L10))-IF(O10="",0,O10)) -> 350 | Q10: Staff child — T1 partial (GHS 350 outstanding); T2 arrears persisting
A11: 7 | B11: Kanati Ava Bubune | C11: Sibling | D11: 2160 | F11: 2160 | G11: =IF(B11="","",IF(D11="",0,D11)+IF(E11="",0,E11)-IF(F11="",0,F11)) -> 0 | H11: 2400 | J11: 120 | K11: 2160 | L11: 0 | M11: 2400 | N11: 1240 | O11: =SUMIF('Nursery 1 - Payments'!C5:C154,B11,'Nursery 1 - Payments'!F5:F154) -> 1160 | P11: =IF(B11="","",IF(M11="",0,M11)-IF(N11="",0,N11)+IF(L11<0,0,IF(L11="",0,L11))-IF(O11="",0,O11)) -> 0 | Q11: Sibling 5% (GHS 240.0) + GHS 1,000 credit. Net: GHS 3,560.00. Options: Quarterly GHS 2400 × 2 / Monthly GHS 800 × 5
A12: 8 | B12: Lartey Madeeha Larley | D12: 2400 | F12: 2400 | G12: =IF(B12="","",IF(D12="",0,D12)+IF(E12="",0,E12)-IF(F12="",0,F12)) -> 0 | H12: 2400 | K12: 2400 | L12: =IF(B12="","",IF(H12="",0,H12)+IF(I12="",0,I12)-IF(J12="",0,J12)-IF(K12="",0,K12)) -> 0 | M12: 2400 | O12: =SUMIF('Nursery 1 - Payments'!C5:C154,B12,'Nursery 1 - Payments'!F5:F154) -> 2400 | P12: 0 | Q12: T3 options: Lump GHS 4,656 (by 21 Apr) / Quarterly GHS 2,400 × 2 / Monthly GHS 960 × 5
A13: 9 | B13: Monney Aseda | C13: Staff Child | D13: 2160 | F13: 2160 | G13: =IF(B13="","",IF(D13="",0,D13)+IF(E13="",0,E13)-IF(F13="",0,F13)) -> 0 | H13: 2400 | J13: 240 | K13: 2160 | L13: =IF(B13="","",IF(H13="",0,H13)+IF(I13="",0,I13)-IF(J13="",0,J13)-IF(K13="",0,K13)) -> 0 | M13: 2400 | N13: 240 | O13: =SUMIF('Nursery 1 - Payments'!C5:C154,B13,'Nursery 1 - Payments'!F5:F154) -> 2160 | P13: =IF(B13="","",IF(M13="",0,M13)-IF(N13="",0,N13)+IF(L13<0,0,IF(L13="",0,L13))-IF(O13="",0,O13)) -> 0 | Q13: Staff child — fully settled
A14: 10 | B14: Obeng Nana Osei Kwasi Agyemang Jayden | C14: Staff Child | D14: 800 | F14: 500 | G14: =IF(B14="","",IF(D14="",0,D14)+IF(E14="",0,E14)-IF(F14="",0,F14)) -> 300 | H14: 2400 | I14: 300 | J14: 2400 | K14: 300 | L14: =IF(B14="","",IF(H14="",0,H14)+IF(I14="",0,I14)-IF(J14="",0,J14)-IF(K14="",0,K14)) -> 0 | M14: 2400 | N14: 2400 | O14: =SUMIF('Nursery 1 - Payments'!C5:C154,B14,'Nursery 1 - Payments'!F5:F154) -> 0 | P14: =IF(B14="","",IF(M14="",0,M14)-IF(N14="",0,N14)+IF(L14<0,0,IF(L14="",0,L14))-IF(O14="",0,O14)) -> 0 | Q14: Staff child — T1 partial; T2 settled
A15: 11 | B15: Rufai Rafui Junior Kobby | C15: Sibling | D15: 2280 | F15: 2000 | G15: =IF(B15="","",IF(D15="",0,D15)+IF(E15="",0,E15)-IF(F15="",0,F15)) -> 280 | H15: 2400 | J15: 120 | K15: 2280 | L15: =IF(B15="","",IF(H15="",0,H15)+IF(I15="",0,I15)-IF(J15="",0,J15)-IF(K15="",0,K15)) -> 0 | M15: 4800 | N15: 240 | O15: =SUMIF('Nursery 1 - Payments'!C5:C154,B15,'Nursery 1 - Payments'!F5:F154) -> 4560 | P15: =IF(B15="","",IF(M15="",0,M15)-IF(N15="",0,N15)+IF(L15<0,0,IF(L15="",0,L15))-IF(O15="",0,O15)) -> 0 | Q15: T3 options: Lump GHS 4,656 (by 21 Apr) / Quarterly GHS 2,400 × 2 / Monthly GHS 960 × 5
A16: 12 | B16: Sangber-Dery Nuornon Peter-Claver | C16: Sibling | D16: 2280 | F16: 2280 | G16: =IF(B16="","",IF(D16="",0,D16)+IF(E16="",0,E16)-IF(F16="",0,F16)) -> 0 | H16: 2400 | J16: 120 | K16: 2280 | L16: =IF(B16="","",IF(H16="",0,H16)+IF(I16="",0,I16)-IF(J16="",0,J16)-IF(K16="",0,K16)) -> 0 | M16: 2400 | N16: 120 | O16: 2280 | P16: =IF(B16="","",IF(M16="",0,M16)-IF(N16="",0,N16)+IF(L16<0,0,IF(L16="",0,L16))-IF(O16="",0,O16)) -> 0 | Q16: T3 options: Lump GHS 4,656 (by 21 Apr) / Quarterly GHS 2,400 × 2 / Monthly GHS 960 × 5
A17: 13 | G17: =IF(B17="","",0) | L17: =IF(B17="","",0) | P17: =IF(B17="","",0)
A18: 14 | G18: =IF(B18="","",0) | L18: =IF(B18="","",0) | P18: =IF(B18="","",0)
A19: 15 | G19: =IF(B19="","",0) | L19: =IF(B19="","",0) | P19: =IF(B19="","",0)
A20: 16 | G20: =IF(B20="","",0) | L20: =IF(B20="","",0) | P20: =IF(B20="","",0)
A21: 17 | G21: =IF(B21="","",0) | L21: =IF(B21="","",0) | P21: =IF(B21="","",0)
A22: 18 | G22: =IF(B22="","",0) | L22: =IF(B22="","",0) | P22: =IF(B22="","",0)
A23: 19 | G23: =IF(B23="","",0) | L23: =IF(B23="","",0) | P23: =IF(B23="","",0)
A24: 20 | G24: =IF(B24="","",0) | L24: =IF(B24="","",0) | P24: =IF(B24="","",0)
A25: 21 | G25: =IF(B25="","",0) | L25: =IF(B25="","",0) | P25: =IF(B25="","",0)
A26: 22 | G26: =IF(B26="","",0) | L26: =IF(B26="","",0) | P26: =IF(B26="","",0)
B27: TOTALS | D27: =SUM(D5:D26) -> 20535 | E27: =SUM(E5:E26) -> 3820 | F27: =SUM(F5:F26) -> 18980 | G27: =SUM(G5:G26) -> 5375 | H27: =SUM(H5:H26) -> 26400 | I27: =SUM(I5:I26) -> 4100 | J27: =SUM(J5:J26) -> 8280 | K27: =SUM(K5:K26) -> 18020 | ... P27: =SUM(P5:P26) -> 3620
B28: Collection Rate: | F28: T1: | G28: =IF(D27+E27=0,1,F27/(D27+E27)) -> 0.7793061 | K28: T2: | L28: =IF(H27+I27-J27=0,1,K27/(H27+I27-J27)) -> 0.8109811 | O28: =SUMIF('Nursery 1 - Payments'!C5:C154,B28,'Nursery 1 - Payments'!F5:F154) -> 0

Sheet Nursery 1 - Payments
A1: Nursery 1: Starlings — PAYMENT RECEIPTS LOG (Term 3, 2025/26: 21 Apr – 24 Jul 2026) | P1: Appiah Eno
A2: Payment deadline: 30 June 2026 | Enter one row per payment | T3 Paid on class register auto-updates via SUMIFS | P2: Ayeh-Kumi Fiifi Jody
A3: TRANSACTION DETAILS | G3: PAYMENT | J3: VERIFICATION | P3: Bakari Kuuku Curtis
A4: Date | B4: Receipt No. | C4: Pupil Name | D4: Term | E4: Week | F4: Amount (GHS) | G4: Payment Method | H4: Received By | I4: Running Total | J4: Verified | K4: Notes | P4: Boamah Nakie Pearl
A5: 46114 | B5: 1028 | C5: Appiah Eno | D5: Term 2 Arrears | F5: 360 | G5: Cash | H5: Dorcas Matilda Akosua Kusi | I5: =IF(F5="","",F5) -> 360 | P5: Boamah Nakour Perpetual
A6: 46122 | B6: 1036 | C6: Kanati Ava Bubune | D6: Term 3 | E6: Vacation | F6: 1000 | G6: Bank Transfer | H6: Dorcas Matilda Akosua Kusi | I6: =IF(F6="","",IF(I5="",F6,I5+F6)) -> 1360 | P6: Boakye Wren Okatakyie
A7: 46127 | B7: 1039 | C7: Kanati Ava Bubune | D7: Term 3 | E7: Vacation | F7: 160 | G7: Bank Transfer | H7: Dorcas Matilda Akosua Kusi | I7: =IF(F7="","",IF(I6="",F7,I6+F7)) -> 1520 | P7: Kanati Ava Bubune
A8: 46132 | B8: 1045 | C8: Bakari Kuuku Curtis | D8: Term 3 | E8: Wk 1 (21 Apr) | F8: 2280 | G8: Bank Transfer | H8: Dorcas Matilda Akosua Kusi | I8: =IF(F8="","",IF(I7="",F8,I7+F8)) -> 3800 | P8: Lartey Madeeha Larley
A9: 46139 | B9: 1054 | C9: Sangber-Dery N. Peter-Claver | D9: Term 3 | E9: Wk 1 (21 Apr) | F9: 2280 | G9: Bank Transfer | H9: Dorcas Matilda Akosua Kusi | I9: =IF(F9="","",IF(I8="",F9,I8+F9)) -> 6080 | P9: Monney Aseda
A10: 46149 | B10: 1068 | C10: Laura Benneh | D10: Term 3 | E10: Wk 3 (05 May) | F10: 650 | G10: Cash | H10: Dorcas Matilda Akosua Kusi | I10: =IF(F10="","",IF(I9="",F10,I9+F10)) -> 6730 | P10: Obeng N.O.K.A. Jayden
A11: 46162 | B11: 1080 | C11: Rufai Rafui Junior Kobby | D11: Term 3 | E11: Wk 5 (19 May) | F11: 2450 | G11: Bank Transfer | H11: Dorcas Matilda Akosua Kusi | I11: =IF(F11="","",IF(I10="",F11,I10+F11)) -> 9180 | P11: Rufai Rafui Junior Kobby
A12: 46163 | B12: 1083 | C12: Lartey Madeeha Larley | D12: Term 3 | E12: Wk 5 (19 May) | F12: 2400 | G12: Bank Transfer | H12: Dorcas Matilda Akosua Kusi | I12: =IF(F12="","",IF(I11="",F12,I11+F12)) -> 11580 | P12: Sangber-Dery N. Peter-Claver
A13: 46175 | B13: 1104 | C13: Boakye Wren Okatakyie | D13: Term 3 | E13: Wk 7 (02 Jun) | F13: 1000 | G13: Cash | H13: Dorcas Matilda Akosua Kusi | I13: =IF(F13="","",IF(I12="",F13,I12+F13)) -> 12580
A14: 46166 | B14: 1103 | C14: Monney Aseda | D14: Term 3 | E14: Wk 6 (26 May) | F14: 1000 | G14: Bank Transfer | H14: Dorcas Matilda Akosua Kusi | I14: =IF(F14="","",IF(I13="",F14,I13+F14)) -> 13580
A15: 46182 | B15: 1110 | C15: Boakye Wren Okatakyie | D15: Term 3 | E15: Wk 8 (09 Jun) | F15: 1000 | G15: MTN MoMo | H15: Dorcas Matilda Akosua Kusi | I15: =IF(F15="","",IF(I14="",F15,I14+F15)) -> 14580
A16: 25/05/2026 | B16: 1100 | C16: Monney Aseda | D16: Term 3 | E16: Wk 6 (26 May) | F16: 1160 | G16: Bank Transfer | H16: Dorcas Matilda Akosua Kusi | I16: =IF(F16="","",IF(I15="",F16,I15+F16)) -> 15740
A17: 46197 | B17: 1130 | C17: Rufai Rafui Junior Kobby | D17: Term 3 | E17: Wk 12 (07 Jul) | F17: 2110 | G17: Bank Transfer | H17: Other | I17: =IF(F17="","",IF(I16="",F17,I16+F17)) -> 17850
A18: 46209 | B18: 1127 | C18: Appiah Eno | D18: Term 3 | E18: Wk 12 (07 Jul) | F18: 1500 | G18: Cash | H18: Other | I18: =IF(F18="","",IF(I17="",F18,I17+F18)) -> 19350
A19: 13/07/2026 | B19: 1135 | C19: Ayeh-Kumi Fiifi Jody | D19: Term 2 Arrears | E19: Wk 12 (07 Jul) | F19: 1500 | G19: MTN MoMo | H19: Dorcas Matilda Akosua Kusi | I19: =IF(F19="","",IF(I18="",F19,I18+F19)) -> 20850
A20: 15/07/2026 | B20: 1143 | C20: Appiah Eno | D20: Term 3 | E20: Wk 13 (14 Jul) | F20: 400 | G20: Cash | H20: Dorcas Matilda Akosua Kusi | I20: =IF(F20="","",IF(I19="",F20,I19+F20)) -> 21250
A21: 46225 | B21: 1148 | C21: Appiah Eno | D21: Term 3 | E21: Wk 14 (21 Jul) | F21: 260 | G21: MTN MoMo | H21: Other | I21: =IF(F21="","",IF(I20="",F21,I20+F21)) -> 21510
A22: 23/07/206 | B22: 1148 | C22: Ayeh-Kumi Fiifi Jody | D22: Term 2 Arrears | E22: Wk 14 (21 Jul) | F22: 1000 | G22: Cash | H22: Other | I22: =IF(F22="","",IF(I21="",F22,I21+F22)) -> 22510
I23: =IF(F23="","",IF(I22="",F23,I22+F23))
I24: =IF(F24="","",IF(I23="",F24,I23+F24))
I25: =IF(F25="","",IF(I24="",F25,I24+F25))
I26: =IF(F26="","",IF(I25="",F26,I25+F26))
I27: =IF(F27="","",IF(I26="",F27,I26+F27))
I28: =IF(F28="","",IF(I27="",F28,I27+F28))
I29: =IF(F29="","",IF(I28="",F29,I28+F29))
I30: =IF(F30="","",IF(I29="",F30,I29+F30))
I31: =IF(F31="","",IF(I30="",F31,I30+F31))
I32: =IF(F32="","",IF(I31="",F32,I31+F32))
I33: =IF(F33="","",IF(I32="",F33,I32+F33))
I34: =IF(F34="","",IF(I33="",F34,I33+F34))
... I154: =IF(F154="","",IF(I153="",F154,I153+F154))
A157: WEEKLY COLLECTION SUMMARY (auto-calculated from payment log)
A158: Week | B158: Week Starting | C158: Entries | D158: Cash | E158: MoMo (All) | F158: Bank Transfer | G158: Cheque | H158: Week Total | I158: Cumulative | J158: vs Deadline | K158: Notes
A159: Wk 1 (21 Apr) | B159: 46133 | C159: =COUNTIF(E5:E154,"Wk 1 (21 Apr)") -> 2 | D159: =SUMPRODUCT((E5:E154="Wk 1 (21 Apr)")*(G5:G154="Cash")*(F5:F154)) -> 0 | E159: =SUMPRODUCT((E5:E154="Wk 1 (21 Apr)")*((G5:G154="MTN MoMo")+(G5:G154="Vodafone Cash")+(G5:G154="AirtelTigo Money"))*(F5:F154)) -> 0 | F159: =SUMPRODUCT((E5:E154="Wk 1 (21 Apr)")*(G5:G154="Bank Transfer")*(F5:F154)) -> 4560 | G159: =SUMPRODUCT((E5:E154="Wk 1 (21 Apr)")*(G5:G154="Cheque")*(F5:F154)) -> 0 | H159: =SUM(D159:G159) -> 4560 | I159: =H159 -> 4560
A160: Wk 2 (28 Apr) | B160: 46140 | C160: =COUNTIF(E5:E154,"Wk 2 (28 Apr)") -> 0 | D160: =SUMPRODUCT((E5:E154="Wk 2 (28 Apr)")*(G5:G154="Cash")*(F5:F154)) -> 0 | E160: =SUMPRODUCT((E5:E154="Wk 2 (28 Apr)")*((G5:G154="MTN MoMo")+(G5:G154="Vodafone Cash")+(G5:G154="AirtelTigo Money"))*(F5:F154)) -> 0 | F160: =SUMPRODUCT((E5:E154="Wk 2 (28 Apr)")*(G5:G154="Bank Transfer")*(F5:F154)) -> 0 | G160: =SUMPRODUCT((E5:E154="Wk 2 (28 Apr)")*(G5:G154="Cheque")*(F5:F154)) -> 0 | H160: =SUM(D160:G160) -> 0 | I160: =I159+H160 -> 4560
A161: Wk 3 (05 May) | B161: 46147 | C161: =COUNTIF(E5:E154,"Wk 3 (05 May)") -> 1 | D161: =SUMPRODUCT((E5:E154="Wk 3 (05 May)")*(G5:G154="Cash")*(F5:F154)) -> 650 | E161: =SUMPRODUCT((E5:E154="Wk 3 (05 May)")*((G5:G154="MTN MoMo")+(G5:G154="Vodafone Cash")+(G5:G154="AirtelTigo Money"))*(F5:F154)) -> 0 | F161: =SUMPRODUCT((E5:E154="Wk 3 (05 May)")*(G5:G154="Bank Transfer")*(F5:F154)) -> 0 | G161: =SUMPRODUCT((E5:E154="Wk 3 (05 May)")*(G5:G154="Cheque")*(F5:F154)) -> 0 | H161: =SUM(D161:G161) -> 650 | I161: =I160+H161 -> 5210
A162: Wk 4 (12 May) | B162: 46154 | C162: =COUNTIF(E5:E154,"Wk 4 (12 May)") -> 0 | D162: =SUMPRODUCT((E5:E154="Wk 4 (12 May)")*(G5:G154="Cash")*(F5:F154)) -> 0 | E162: =SUMPRODUCT((E5:E154="Wk 4 (12 May)")*((G5:G154="MTN MoMo")+(G5:G154="Vodafone Cash")+(G5:G154="AirtelTigo Money"))*(F5:F154)) -> 0 | F162: =SUMPRODUCT((E5:E154="Wk 4 (12 May)")*(G5:G154="Bank Transfer")*(F5:F154)) -> 0 | G162: =SUMPRODUCT((E5:E154="Wk 4 (12 May)")*(G5:G154="Cheque")*(F5:F154)) -> 0 | H162: =SUM(D162:G162) -> 0 | I162: =I161+H162 -> 5210
A163: Wk 5 (19 May) | B163: 46161 | C163: =COUNTIF(E5:E154,"Wk 5 (19 May)") -> 2 | D163: =SUMPRODUCT((E5:E154="Wk 5 (19 May)")*(G5:G154="Cash")*(F5:F154)) -> 0 | E163: =SUMPRODUCT((E5:E154="Wk 5 (19 May)")*((G5:G154="MTN MoMo")+(G5:G154="Vodafone Cash")+(G5:G154="AirtelTigo Money"))*(F5:F154)) -> 0 | F163: =SUMPRODUCT((E5:E154="Wk 5 (19 May)")*(G5:G154="Bank Transfer")*(F5:F154)) -> 4850 | G163: =SUMPRODUCT((E5:E154="Wk 5 (19 May)")*(G5:G154="Cheque")*(F5:F154)) -> 0 | H163: =SUM(D163:G163) -> 4850 | I163: =I162+H163 -> 10060
A164: Wk 6 (26 May) | B164: 46168 | C164: =COUNTIF(E5:E154,"Wk 6 (26 May)") -> 2 | D164: =SUMPRODUCT((E5:E154="Wk 6 (26 May)")*(G5:G154="Cash")*(F5:F154)) -> 0 | E164: =SUMPRODUCT((E5:E154="Wk 6 (26 May)")*((G5:G154="MTN MoMo")+(G5:G154="Vodafone Cash")+(G5:G154="AirtelTigo Money"))*(F5:F154)) -> 0 | F164: =SUMPRODUCT((E5:E154="Wk 6 (26 May)")*(G5:G154="Bank Transfer")*(F5:F154)) -> 2160 | G164: =SUMPRODUCT((E5:E154="Wk 6 (26 May)")*(G5:G154="Cheque")*(F5:F154)) -> 0 | H164: =SUM(D164:G164) -> 2160 | I164: =I163+H164 -> 12220
A165: Wk 7 (02 Jun) | B165: 46175 | C165: =COUNTIF(E5:E154,"Wk 7 (02 Jun)") -> 1 | D165: =SUMPRODUCT((E5:E154="Wk 7 (02 Jun)")*(G5:G154="Cash")*(F5:F154)) -> 1000 | E165: =SUMPRODUCT((E5:E154="Wk 7 (02 Jun)")*((G5:G154="MTN MoMo")+(G5:G154="Vodafone Cash")+(G5:G154="AirtelTigo Money"))*(F5:F154)) -> 0 | F165: =SUMPRODUCT((E5:E154="Wk 7 (02 Jun)")*(G5:G154="Bank Transfer")*(F5:F154)) -> 0 | G165: =SUMPRODUCT((E5:E154="Wk 7 (02 Jun)")*(G5:G154="Cheque")*(F5:F154)) -> 0 | H165: =SUM(D165:G165) -> 1000 | I165: =I164+H165 -> 13220
A166: Wk 8 (09 Jun) | B166: 46182 | C166: =COUNTIF(E5:E154,"Wk 8 (09 Jun)") -> 1 | D166: =SUMPRODUCT((E5:E154="Wk 8 (09 Jun)")*(G5:G154="Cash")*(F5:F154)) -> 0 | E166: =SUMPRODUCT((E5:E154="Wk 8 (09 Jun)")*((G5:G154="MTN MoMo")+(G5:G154="Vodafone Cash")+(G5:G154="AirtelTigo Money"))*(F5:F154)) -> 1000 | F166: =SUMPRODUCT((E5:E154="Wk 8 (09 Jun)")*(G5:G154="Bank Transfer")*(F5:F154)) -> 0 | G166: =SUMPRODUCT((E5:E154="Wk 8 (09 Jun)")*(G5:G154="Cheque")*(F5:F154)) -> 0 | H166: =SUM(D166:G166) -> 1000 | I166: =I165+H166 -> 14220
A167: Wk 9 (16 Jun) | B167: 46189 | C167: =COUNTIF(E5:E154,"Wk 9 (16 Jun)") -> 0 | D167: =SUMPRODUCT((E5:E154="Wk 9 (16 Jun)")*(G5:G154="Cash")*(F5:F154)) -> 0 | E167: =SUMPRODUCT((E5:E154="Wk 9 (16 Jun)")*((G5:G154="MTN MoMo")+(G5:G154="Vodafone Cash")+(G5:G154="AirtelTigo Money"))*(F5:F154)) -> 0 | F167: =SUMPRODUCT((E5:E154="Wk 9 (16 Jun)")*(G5:G154="Bank Transfer")*(F5:F154)) -> 0 | G167: =SUMPRODUCT((E5:E154="Wk 9 (16 Jun)")*(G5:G154="Cheque")*(F5:F154)) -> 0 | H167: =SUM(D167:G167) -> 0 | I167: =I166+H167 -> 14220
A168: Wk 10 (23 Jun) | B168: 46196 | C168: =COUNTIF(E5:E154,"Wk 10 (23 Jun)") -> 0 | D168: =SUMPRODUCT((E5:E154="Wk 10 (23 Jun)")*(G5:G154="Cash")*(F5:F154)) -> 0 | E168: =SUMPRODUCT((E5:E154="Wk 10 (23 Jun)")*((G5:G154="MTN MoMo")+(G5:G154="Vodafone Cash")+(G5:G154="AirtelTigo Money"))*(F5:F154)) -> 0 | F168: =SUMPRODUCT((E5:E154="Wk 10 (23 Jun)")*(G5:G154="Bank Transfer")*(F5:F154)) -> 0 | G168: =SUMPRODUCT((E5:E154="Wk 10 (23 Jun)")*(G5:G154="Cheque")*(F5:F154)) -> 0 | H168: =SUM(D168:G168) -> 0 | I168: =I167+H168 -> 14220
A169: Wk 11 (30 Jun) | B169: 46203 | C169: =COUNTIF(E5:E154,"Wk 11 (30 Jun)") -> 0 | D169: =SUMPRODUCT((E5:E154="Wk 11 (30 Jun)")*(G5:G154="Cash")*(F5:F154)) -> 0 | E169: =SUMPRODUCT((E5:E154="Wk 11 (30 Jun)")*((G5:G154="MTN MoMo")+(G5:G154="Vodafone Cash")+(G5:G154="AirtelTigo Money"))*(F5:F154)) -> 0 | F169: =SUMPRODUCT((E5:E154="Wk 11 (30 Jun)")*(G5:G154="Bank Transfer")*(F5:F154)) -> 0 | G169: =SUMPRODUCT((E5:E154="Wk 11 (30 Jun)")*(G5:G154="Cheque")*(F5:F154)) -> 0 | H169: =SUM(D169:G169) -> 0 | I169: =I168+H169 -> 14220
A170: Wk 12 (07 Jul) | B170: 46210 | C170: =COUNTIF(E5:E154,"Wk 12 (07 Jul)") -> 3 | D170: =SUMPRODUCT((E5:E154="Wk 12 (07 Jul)")*(G5:G154="Cash")*(F5:F154)) -> 1500 | E170: =SUMPRODUCT((E5:E154="Wk 12 (07 Jul)")*((G5:G154="MTN MoMo")+(G5:G154="Vodafone Cash")+(G5:G154="AirtelTigo Money"))*(F5:F154)) -> 1500 | F170: =SUMPRODUCT((E5:E154="Wk 12 (07 Jul)")*(G5:G154="Bank Transfer")*(F5:F154)) -> 2110 | G170: =SUMPRODUCT((E5:E154="Wk 12 (07 Jul)")*(G5:G154="Cheque")*(F5:F154)) -> 0 | H170: =SUM(D170:G170) -> 5110 | I170: =I169+H170 -> 19330 | J170: PAST DEADLINE
A171: Wk 13 (14 Jul) | B171: 46217 | C171: =COUNTIF(E5:E154,"Wk 13 (14 Jul)") -> 1 | D171: =SUMPRODUCT((E5:E154="Wk 13 (14 Jul)")*(G5:G154="Cash")*(F5:F154)) -> 400 | E171: =SUMPRODUCT((E5:E154="Wk 13 (14 Jul)")*((G5:G154="MTN MoMo")+(G5:G154="Vodafone Cash")+(G5:G154="AirtelTigo Money"))*(F5:F154)) -> 0 | F171: =SUMPRODUCT((E5:E154="Wk 13 (14 Jul)")*(G5:G154="Bank Transfer")*(F5:F154)) -> 0 | G171: =SUMPRODUCT((E5:E154="Wk 13 (14 Jul)")*(G5:G154="Cheque")*(F5:F154)) -> 0 | H171: =SUM(D171:G171) -> 400 | I171: =I170+H171 -> 19730 | J171: PAST DEADLINE
A172: Wk 14 (21 Jul) | B172: 46224 | C172: =COUNTIF(E5:E154,"Wk 14 (21 Jul)") -> 2 | D172: =SUMPRODUCT((E5:E154="Wk 14 (21 Jul)")*(G5:G154="Cash")*(F5:F154)) -> 1000 | E172: =SUMPRODUCT((E5:E154="Wk 14 (21 Jul)")*((G5:G154="MTN MoMo")+(G5:G154="Vodafone Cash")+(G5:G154="AirtelTigo Money"))*(F5:F154)) -> 260 | F172: =SUMPRODUCT((E5:E154="Wk 14 (21 Jul)")*(G5:G154="Bank Transfer")*(F5:F154)) -> 0 | G172: =SUMPRODUCT((E5:E154="Wk 14 (21 Jul)")*(G5:G154="Cheque")*(F5:F154)) -> 0 | H172: =SUM(D172:G172) -> 1260 | I172: =I171+H172 -> 20990 | J172: PAST DEADLINE
A173: TERM 3 TOTAL | C173: =SUM(C159:C172) -> 15 | D173: =SUM(D159:D172) -> 4550 | E173: =SUM(E159:E172) -> 2760 | F173: =SUM(F159:F172) -> 13680 | G173: =SUM(G159:G172) -> 0 | H173: =SUM(H159:H172) -> 20990
A176: MONTHLY COLLECTION SUMMARY
A177: Month | B177: No. of Payments | C177: Cash | D177: MoMo (All) | E177: Bank Transfer | F177: Cheque | G177: Month Total | H177: Cumulative | I177: Target % | J177: Actual % | K177: Notes
A178: Apr | B178: =SUMPRODUCT((MONTH(A5:A154)=4)*(A5:A154<>"")) -> #VALUE! | C178: =SUMPRODUCT((MONTH(A5:A154)=4)*(G5:G154="Cash")*(F5:F154)) -> #VALUE! | D178: =SUMPRODUCT((MONTH(A5:A154)=4)*((G5:G154="MTN MoMo")+(G5:G154="Vodafone Cash")+(G5:G154="AirtelTigo Money"))*(F5:F154)) -> #VALUE! | E178: =SUMPRODUCT((MONTH(A5:A154)=4)*(G5:G154="Bank Transfer")*(F5:F154)) -> #VALUE! | F178: =SUMPRODUCT((MONTH(A5:A154)=4)*(G5:G154="Cheque")*(F5:F154)) -> #VALUE! | G178: =SUM(C178:F178) -> #VALUE! | H178: =G178 -> #VALUE! | I178: 0.3
A179: May | B179: =SUMPRODUCT((MONTH(A5:A154)=5)*(A5:A154<>"")) -> #VALUE! | C179: =SUMPRODUCT((MONTH(A5:A154)=5)*(G5:G154="Cash")*(F5:F154)) -> #VALUE! | D179: =SUMPRODUCT((MONTH(A5:A154)=5)*((G5:G154="MTN MoMo")+(G5:G154="Vodafone Cash")+(G5:G154="AirtelTigo Money"))*(F5:F154)) -> #VALUE! | E179: =SUMPRODUCT((MONTH(A5:A154)=5)*(G5:G154="Bank Transfer")*(F5:F154)) -> #VALUE! | F179: =SUMPRODUCT((MONTH(A5:A154)=5)*(G5:G154="Cheque")*(F5:F154)) -> #VALUE! | G179: =SUM(C179:F179) -> #VALUE! | H179: =H178+G179 -> #VALUE! | I179: 0.65
A180: Jun | B180: =SUMPRODUCT((MONTH(A5:A154)=6)*(A5:A154<>"")) -> #VALUE! | C180: =SUMPRODUCT((MONTH(A5:A154)=6)*(G5:G154="Cash")*(F5:F154)) -> #VALUE! | D180: =SUMPRODUCT((MONTH(A5:A154)=6)*((G5:G154="MTN MoMo")+(G5:G154="Vodafone Cash")+(G5:G154="AirtelTigo Money"))*(F5:F154)) -> #VALUE! | E180: =SUMPRODUCT((MONTH(A5:A154)=6)*(G5:G154="Bank Transfer")*(F5:F154)) -> #VALUE! | F180: =SUMPRODUCT((MONTH(A5:A154)=6)*(G5:G154="Cheque")*(F5:F154)) -> #VALUE! | G180: =SUM(C180:F180) -> #VALUE! | H180: =H179+G180 -> #VALUE! | I180: 1
A181: Jul | B181: =SUMPRODUCT((MONTH(A5:A154)=7)*(A5:A154<>"")) -> #VALUE! | C181: =SUMPRODUCT((MONTH(A5:A154)=7)*(G5:G154="Cash")*(F5:F154)) -> #VALUE! | D181: =SUMPRODUCT((MONTH(A5:A154)=7)*((G5:G154="MTN MoMo")+(G5:G154="Vodafone Cash")+(G5:G154="AirtelTigo Money"))*(F5:F154)) -> #VALUE! | E181: =SUMPRODUCT((MONTH(A5:A154)=7)*(G5:G154="Bank Transfer")*(F5:F154)) -> #VALUE! | F181: =SUMPRODUCT((MONTH(A5:A154)=7)*(G5:G154="Cheque")*(F5:F154)) -> #VALUE! | G181: =SUM(C181:F181) -> #VALUE! | H181: =H180+G181 -> #VALUE! | I181: 1
A182: TOTAL | B182: =SUM(B178:B181) -> #VALUE! | C182: =SUM(C178:C181) -> #VALUE! | D182: =SUM(D178:D181) -> #VALUE! | E182: =SUM(E178:E181) -> #VALUE! | F182: =SUM(F178:F181) -> #VALUE! | G182: =SUM(G178:G181) -> #VALUE!

Sheet Nursery 2 - Goldfinches
A1: Nursery 2: Goldfinches — Creativity | Beauty | Annual: GHS 9,400 | Termly: GHS 2,400
A3: PUPIL DETAILS | D3: TERM 1 (COMPLETED) | H3: TERM 2 (COMPLETED) | M3: TERM 3 (ACTIVE — covers remainder of year; arrears included) | Q3: NOTES
A4: No. | B4: Pupil Name | C4: Discount Type | D4: T1 Fee | E4: T1 Arrears BF | F4: T1 Paid | G4: T1 Balance | H4: T2 Fee | I4: T2 Arrears BF | J4: T2 Discount | K4: T2 Paid | L4: T2 Balance | M4: T3 Fee | N4: T3 Discount | O4: T3 Paid | P4: T3 Balance | Q4: Remarks / Waiver Notes
A5: 1 | B5: Agyemang Nunana Khloe | C5: Staff Child | D5: 800 | F5: 800 | G5: =IF(B5="","",IF(D5="",0,D5)+IF(E5="",0,E5)-IF(F5="",0,F5)) -> 0 | H5: 2400 | J5: 2400 | L5: =IF(B5="","",IF(H5="",0,H5)+IF(I5="",0,I5)-IF(J5="",0,J5)-IF(K5="",0,K5)) -> 0 | M5: 4800 | N5: 4800 | O5: =SUMIF('Nursery 2 - Payments'!C5:C154,B5,'Nursery 2 - Payments'!F5:F154) -> 0 | P5: =IF(B5="","",IF(M5="",0,M5)-IF(N5="",0,N5)+IF(L5<0,0,IF(L5="",0,L5))-IF(O5="",0,O5)) -> 0 | Q5: Staff child — fees fully covered
A6: 2 | B6: Alhassan Bubune Y.A.B.A Faith Kaylan | D6: 2400 | F6: 2400 | G6: =IF(B6="","",IF(D6="",0,D6)+IF(E6="",0,E6)-IF(F6="",0,F6)) -> 0 | H6: 2400 | K6: 2400 | L6: =IF(B6="","",IF(H6="",0,H6)+IF(I6="",0,I6)-IF(J6="",0,J6)-IF(K6="",0,K6)) -> 0 | M6: 2400 | O6: =SUMIF('Nursery 2 - Payments'!C5:C154,B6,'Nursery 2 - Payments'!F5:F154) -> 0 | P6: =IF(B6="","",IF(M6="",0,M6)-IF(N6="",0,N6)+IF(L6<0,0,IF(L6="",0,L6))-IF(O6="",0,O6)) -> 2400 | Q6: T3 options: Lump GHS 4,656 (by 21 Apr) / Quarterly GHS 2,400 × 2 / Monthly GHS 960 × 5
A7: 3 | B7: Ansah-Darko Chris-David | C7: Sibling | D7: 2280 | F7: 2280 | G7: =IF(B7="","",IF(D7="",0,D7)+IF(E7="",0,E7)-IF(F7="",0,F7)) -> 0 | H7: 2400 | J7: 120 | K7: 2280 | L7: =IF(B7="","",IF(H7="",0,H7)+IF(I7="",0,I7)-IF(J7="",0,J7)-IF(K7="",0,K7)) -> 0 | M7: 4800 | N7: 240 | O7: =SUMIF('Nursery 2 - Payments'!C5:C154,B7,'Nursery 2 - Payments'!F5:F154) -> 2280 | P7: =IF(B7="","",IF(M7="",0,M7)-IF(N7="",0,N7)+IF(L7<0,0,IF(L7="",0,L7))-IF(O7="",0,O7)) -> 2280 | Q7: T3 options: Lump GHS 4,656 (by 21 Apr) / Quarterly GHS 2,400 × 2 / Monthly GHS 960 × 5
A8: 4 | B8: Boakye Wren Okatakyie | D8: 2160 | F8: 2160 | G8: =IF(B8="","",IF(D8="",0,D8)+IF(E8="",0,E8)-IF(F8="",0,F8)) -> 0 | H8: 2400 | J8: 240 | K8: 2160 | L8: =IF(B8="","",IF(H8="",0,H8)+IF(I8="",0,I8)-IF(J8="",0,J8)-IF(K8="",0,K8)) -> 0 | M8: 2400 | N8: 240 | O8: =SUMIF('Nursery 1 - Payments'!C5:C154,B8,'Nursery 1 - Payments'!F5:F154) -> 2000 | P8: =IF(B8="","",IF(M8="",0,M8)-IF(N8="",0,N8)+IF(L8<0,0,IF(L8="",0,L8))-IF(O8="",0,O8)) -> 160 | Q8: Staff child — fully settled
A9: 5 | B9: Campbell Fathia Elinam | C9: Waiver | D9: 2280 | F9: 2280 | G9: =IF(B9="","",IF(D9="",0,D9)+IF(E9="",0,E9)-IF(F9="",0,F9)) -> 0 | H9: 2400 | J9: 1400 | K9: 1000 | L9: =IF(B9="","",IF(H9="",0,H9)+IF(I9="",0,I9)-IF(J9="",0,J9)-IF(K9="",0,K9)) -> 0 | M9: 2400 | N9: 240 | O9: =SUMIF('Nursery 2 - Payments'!C5:C154,B9,'Nursery 2 - Payments'!F5:F154) -> 2180 | P9: =IF(B9="","",IF(M9="",0,M9)-IF(N9="",0,N9)+IF(L9<0,0,IF(L9="",0,L9))-IF(O9="",0,O9)) -> -20 | Q9: Waiver — parent's condition; GHS 1,400 waived T2
A10: 6 | B10: Diko Eliana Amponsah | D10: 2400 | F10: 2400 | G10: =IF(B10="","",IF(D10="",0,D10)+IF(E10="",0,E10)-IF(F10="",0,F10)) -> 0 | H10: 2400 | K10: 2400 | L10: =IF(B10="","",IF(H10="",0,H10)+IF(I10="",0,I10)-IF(J10="",0,J10)-IF(K10="",0,K10)) -> 0 | M10: 2400 | O10: =SUMIF('Nursery 2 - Payments'!C5:C154,B10,'Nursery 2 - Payments'!F5:F154) -> 2400 | P10: =IF(B10="","",IF(M10="",0,M10)-IF(N10="",0,N10)+IF(L10<0,0,IF(L10="",0,L10))-IF(O10="",0,O10)) -> 0 | Q10: T3 options: Lump GHS 4,656 (by 21 Apr) / Quarterly GHS 2,400 × 2 / Monthly GHS 960 × 5
A11: 7 | B11: Obenewaa Ariel | D11: 2400 | F11: 2400 | G11: =IF(B11="","",IF(D11="",0,D11)+IF(E11="",0,E11)-IF(F11="",0,F11)) -> 0 | H11: 2400 | K11: 2400 | L11: =IF(B11="","",IF(H11="",0,H11)+IF(I11="",0,I11)-IF(J11="",0,J11)-IF(K11="",0,K11)) -> 0 | M11: 2400 | O11: =SUMIF('Nursery 2 - Payments'!C5:C154,B11,'Nursery 2 - Payments'!F5:F154) -> 2400 | P11: =IF(B11="","",IF(M11="",0,M11)-IF(N11="",0,N11)+IF(L11<0,0,IF(L11="",0,L11))-IF(O11="",0,O11)) -> 0 | Q11: T3 options: Lump GHS 4,656 (by 21 Apr) / Quarterly GHS 2,400 × 2 / Monthly GHS 960 × 5
A12: 8 | B12: Oussainu Kassim | D12: 2400 | F12: 2400 | G12: =IF(B12="","",IF(D12="",0,D12)+IF(E12="",0,E12)-IF(F12="",0,F12)) -> 0 | H12: 2400 | K12: 2400 | L12: =IF(B12="","",IF(H12="",0,H12)+IF(I12="",0,I12)-IF(J12="",0,J12)-IF(K12="",0,K12)) -> 0 | M12: 2400 | O12: =SUMIF('Nursery 2 - Payments'!C5:C154,B12,'Nursery 2 - Payments'!F5:F154) -> 2400 | P12: =IF(B12="","",IF(M12="",0,M12)-IF(N12="",0,N12)+IF(L12<0,0,IF(L12="",0,L12))-IF(O12="",0,O12)) -> 0 | Q12: T3 options: Lump GHS 4,656 (by 21 Apr) / Quarterly GHS 2,400 × 2 / Monthly GHS 960 × 5
A13: 9 | B13: Munkaila Tasmiyah | D13: 2400 | F13: 1500 | G13: =IF(B13="","",IF(D13="",0,D13)+IF(E13="",0,E13)-IF(F13="",0,F13)) -> 900 | H13: 2400 | K13: 2400 | L13: =IF(B13="","",IF(H13="",0,H13)+IF(I13="",0,I13)-IF(J13="",0,J13)-IF(K13="",0,K13)) -> 0 | M13: 2400 | O13: =SUMIF('Nursery 2 - Payments'!C5:C154,B13,'Nursery 2 - Payments'!F5:F154) -> 4800 | P13: =IF(B13="","",IF(M13="",0,M13)-IF(N13="",0,N13)+IF(L13<0,0,IF(L13="",0,L13))-IF(O13="",0,O13)) -> -2400 | Q13: T1 arrears GHS 900 cleared in T2
A14: 10 | B14: Mubarik Jamil | D14: 2400 | F14: 2400 | G14: =IF(B14="","",IF(D14="",0,D14)+IF(E14="",0,E14)-IF(F14="",0,F14)) -> 0 | H14: 2400 | K14: 2400 | L14: =IF(B14="","",IF(H14="",0,H14)+IF(I14="",0,I14)-IF(J14="",0,J14)-IF(K14="",0,K14)) -> 0 | M14: 2400 | O14: =SUMIF('Nursery 2 - Payments'!C5:C154,B14,'Nursery 2 - Payments'!F5:F154) -> 2800 | P14: =IF(B14="","",IF(M14="",0,M14)-IF(N14="",0,N14)+IF(L14<0,0,IF(L14="",0,L14))-IF(O14="",0,O14)) -> -400 | Q14: T3 options: Lump GHS 4,656 (by 21 Apr) / Quarterly GHS 2,400 × 2 / Monthly GHS 960 × 5
A15: 11 | B15: Sangber-Dery Jayden Mwinviel | D15: 2400 | F15: 2400 | G15: =IF(B15="","",IF(D15="",0,D15)+IF(E15="",0,E15)-IF(F15="",0,F15)) -> 0 | H15: 2400 | K15: 2400 | L15: =IF(B15="","",IF(H15="",0,H15)+IF(I15="",0,I15)-IF(J15="",0,J15)-IF(K15="",0,K15)) -> 0 | M15: 2400 | O15: 2400 | P15: =IF(B15="","",IF(M15="",0,M15)-IF(N15="",0,N15)+IF(L15<0,0,IF(L15="",0,L15))-IF(O15="",0,O15)) -> 0 | Q15: T3 options: Lump GHS 4,656 (by 21 Apr) / Quarterly GHS 2,400 × 2 / Monthly GHS 960 × 5
A16: 12 | B16: Bekoe Nana Yaa | C16: Sibling | G16: =IF(B16="","",IF(D16="",0,D16)+IF(E16="",0,E16)-IF(F16="",0,F16)) -> 0 | H16: 4400 | J16: 120 | K16: 4280 | L16: =IF(B16="","",IF(H16="",0,H16)+IF(I16="",0,I16)-IF(J16="",0,J16)-IF(K16="",0,K16)) -> 0 | M16: 4800 | N16: 240 | O16: =SUMIF('Nursery 2 - Payments'!C5:C154,B16,'Nursery 2 - Payments'!F5:F154) -> 2280 | P16: =IF(B16="","",IF(M16="",0,M16)-IF(N16="",0,N16)+IF(L16<0,0,IF(L16="",0,L16))-IF(O16="",0,O16)) -> 2280 | Q16: Sibling — joined mid-year; higher fee includes catch-up
A17: 13 | B17: Adugbire Mbo Ibiza | G17: =IF(B17="","",IF(D17="",0,D17)+IF(E17="",0,E17)-IF(F17="",0,F17)) -> 0 | H17: 2400 | K17: 2400 | L17: 0 | M17: 2400 | O17: =SUMIF('Nursery 2 - Payments'!C5:C154,B17,'Nursery 2 - Payments'!F5:F154) -> 1500 | P17: =IF(B17="","",IF(M17="",0,M17)-IF(N17="",0,N17)+IF(L17<0,0,IF(L17="",0,L17))-IF(O17="",0,O17)) -> 900 | Q17: New enrolment — T2 arrears GHS 550 outstanding
A18: 14 | G18: =IF(B18="","",0) | L18: =IF(B18="","",0) | P18: =IF(B18="","",0)
A19: 15 | G19: =IF(B19="","",0) | L19: =IF(B19="","",0) | P19: =IF(B19="","",0)
A20: 16 | G20: =IF(B20="","",0) | L20: =IF(B20="","",0) | P20: =IF(B20="","",0)
A21: 17 | G21: =IF(B21="","",0) | L21: =IF(B21="","",0) | P21: =IF(B21="","",0)
A22: 18 | G22: =IF(B22="","",0) | L22: =IF(B22="","",0) | P22: =IF(B22="","",0)
A23: 19 | G23: =IF(B23="","",0) | L23: =IF(B23="","",0) | P23: =IF(B23="","",0)
A24: 20 | G24: =IF(B24="","",0) | L24: =IF(B24="","",0) | P24: =IF(B24="","",0)
A25: 21 | G25: =IF(B25="","",0) | L25: =IF(B25="","",0) | P25: =IF(B25="","",0)
A26: 22 | G26: =IF(B26="","",0) | L26: =IF(B26="","",0) | P26: =IF(B26="","",0)
A27: 23 | G27: =IF(B27="","",0) | L27: =IF(B27="","",0) | P27: =IF(B27="","",0)
B28: TOTALS | D28: =SUM(D5:D27) -> 24320 | E28: =SUM(E5:E27) -> 0 | F28: =SUM(F5:F27) -> 23420 | G28: =SUM(G5:G27) -> 900 | H28: =SUM(H5:H27) -> 33200 | I28: =SUM(I5:I27) -> 0 | J28: =SUM(J5:J27) -> 4280 | K28: =SUM(K5:K27) -> 28920 | ... P28: =SUM(P5:P27) -> 5200
B29: Collection Rate: | F29: T1: | G29: =IF(D28+E28=0,1,F28/(D28+E28)) -> 0.96299342 | K29: T2: | L29: =IF(H28+I28-J28=0,1,K28/(H28+I28-J28)) -> 1 | O29: =SUMIF('Nursery 2 - Payments'!C5:C154,B29,'Nursery 2 - Payments'!F5:F154) -> 0

Sheet Nursery 2 - Payments
A1: Nursery 2: Goldfinches — PAYMENT RECEIPTS LOG (Term 3, 2025/26: 21 Apr – 24 Jul 2026) | P1: Agyemang Nunana Khloe
A2: Payment deadline: 30 June 2026 | Enter one row per payment | T3 Paid on class register auto-updates via SUMIFS | P2: Alhassan B. Faith Kaylan
A3: TRANSACTION DETAILS | G3: PAYMENT | J3: VERIFICATION | P3: Ansah-Darko Chris-David
A4: Date | B4: Receipt No. | C4: Pupil Name | D4: Term | E4: Week | F4: Amount (GHS) | G4: Payment Method | H4: Received By | I4: Running Total | J4: Verified | K4: Notes | P4: Campbell Fathia Elinam
A5: 46111 | B5: 1026 | C5: Adugbira Mbo Ibiza | D5: Term 2 Arrears | F5: 550 | G5: Cash | H5: Dorcas Matilda Akosua Kusi | I5: =IF(F5="","",F5) -> 550 | P5: Diko Eliana Amponsah
A6: 46112 | B6: 1027 | C6: Mubarik Jamil | D6: Term 2 Arrears | F6: 400 | G6: Cash | H6: Dorcas Matilda Akosua Kusi | I6: =IF(F6="","",IF(I5="",F6,I5+F6)) -> 950 | P6: Obenewaa Ariel
A7: 46139 | B7: 1051 | C7: Campbell Fathia Elinam | D7: Term 3 | E7: Wk 2 (28 Apr) | F7: 1000 | G7: MTN MoMo | H7: Dorcas Matilda Akosua Kusi | I7: =IF(F7="","",IF(I6="",F7,I6+F7)) -> 1950 | P7: Oussainu Kassim
A8: 46139 | B8: 1053 | C8: Sangber-Dery Jayden M. | D8: Term 3 | E8: Wk 2 (28 Apr) | F8: 2400 | G8: Bank Transfer | H8: Dorcas Matilda Akosua Kusi | I8: =IF(F8="","",IF(I7="",F8,I7+F8)) -> 4350 | P8: Munkaila Tasmiyah
A9: 46146 | B9: 1062 | C9: Campbell Fathia Elinam | D9: Term 3 | E9: Wk 3 (05 May) | F9: 749.5 | G9: MTN MoMo | H9: Other | I9: =IF(F9="","",IF(I8="",F9,I8+F9)) -> 5099.5 | P9: Mubarik Jamil
A10: 46149 | B10: 1066 | C10: Oussainu Kassim | D10: Term 3 | E10: Wk 3 (05 May) | F10: 2400 | G10: Cash | H10: Dorcas Matilda Akosua Kusi | I10: =IF(F10="","",IF(I9="",F10,I9+F10)) -> 7499.5 | P10: Sangber-Dery Jayden M.
A11: 46157 | B11: 1074 | C11: Obenewaa Ariel | D11: Term 3 | E11: Wk 4 (12 May) | F11: 1500 | G11: MTN MoMo | H11: Dorcas Matilda Akosua Kusi | I11: =IF(F11="","",IF(I10="",F11,I10+F11)) -> 8999.5 | P11: Bekoe Nana Yaa
A12: 46157 | B12: 1075 | C12: Ansah-Darko Chris-David | D12: Term 3 | E12: Wk 4 (12 May) | F12: 2280 | G12: Bank Transfer | H12: Dorcas Matilda Akosua Kusi | I12: =IF(F12="","",IF(I11="",F12,I11+F12)) -> 11279.5 | P12: Adugbira Mbo Ibiza
A13: 46157 | B13: 1076 | C13: Bekoe Nana Yaa | D13: Term 3 | E13: Wk 4 (12 May) | F13: 2280 | G13: Bank Transfer | H13: Dorcas Matilda Akosua Kusi | I13: =IF(F13="","",IF(I12="",F13,I12+F13)) -> 13559.5
A14: 46168 | B14: 1089 | C14: Campbell Fathia Elinam | D14: Term 3 | E14: Wk 6 (26 May) | F14: 430.5 | G14: MTN MoMo | H14: Dorcas Matilda Akosua Kusi | I14: =IF(F14="","",IF(I13="",F14,I13+F14)) -> 13990
A15: 46171 | B15: 1093 | C15: Munkaila Tasmiyah | D15: Term 3 | E15: Wk 6 (26 May) | F15: 4800 | G15: MTN MoMo | H15: Dorcas Matilda Akosua Kusi | I15: =IF(F15="","",IF(I14="",F15,I14+F15)) -> 18790
A16: 46171 | B16: 1094 | C16: Diko Eliana Amponsah | D16: Term 3 | E16: Wk 6 (26 May) | F16: 1500 | G16: Bank Transfer | H16: Dorcas Matilda Akosua Kusi | I16: =IF(F16="","",IF(I15="",F16,I15+F16)) -> 20290
A17: 46181 | B17: 1109 | C17: Mubarik Jamil | D17: Term 3 | E17: Wk 8 (09 Jun) | F17: 2400 | G17: MTN MoMo | H17: Dorcas Matilda Akosua Kusi | I17: =IF(F17="","",IF(I16="",F17,I16+F17)) -> 22690
A18: 46192 | B18: 1118 | C18: Adugbire Mbo Ibiza | D18: Term 3 | E18: Wk 9 (16 Jun) | F18: 1500 | G18: MTN MoMo | H18: Other | I18: =IF(F18="","",IF(I17="",F18,I17+F18)) -> 24190
A19: 46241 | B19: 1131 | C19: Diko Eliana Amponsah | D19: Term 3 | E19: Wk 12 (07 Jul) | F19: 900 | G19: Bank Transfer | H19: Dorcas Matilda Akosua Kusi | I19: =IF(F19="","",IF(I18="",F19,I18+F19)) -> 25090
A20: 46272 | B20: 1133 | C20: Obenewaa Ariel | D20: Term 3 | E20: Wk 12 (07 Jul) | F20: 900 | G20: MTN MoMo | H20: Dorcas Matilda Akosua Kusi | I20: =IF(F20="","",IF(I19="",F20,I19+F20)) -> 25990
A21: 46217 | B21: 1140 | C21: Alhassan B. Faith Kaylan | D21: Term 3 | E21: Wk 13 (14 Jul) | F21: 2400 | G21: MTN MoMo | H21: Other | I21: =IF(F21="","",IF(I20="",F21,I20+F21)) -> 28390
I22: =IF(F22="","",IF(I21="",F22,I21+F22))
I23: =IF(F23="","",IF(I22="",F23,I22+F23))
I24: =IF(F24="","",IF(I23="",F24,I23+F24))
I25: =IF(F25="","",IF(I24="",F25,I24+F25))
I26: =IF(F26="","",IF(I25="",F26,I25+F26))
I27: =IF(F27="","",IF(I26="",F27,I26+F27))
I28: =IF(F28="","",IF(I27="",F28,I27+F28))
I29: =IF(F29="","",IF(I28="",F29,I28+F29))
I30: =IF(F30="","",IF(I29="",F30,I29+F30))
I31: =IF(F31="","",IF(I30="",F31,I30+F31))
I32: =IF(F32="","",IF(I31="",F32,I31+F32))
I33: =IF(F33="","",IF(I32="",F33,I32+F33))
... I154: =IF(F154="","",IF(I153="",F154,I153+F154))
A157: WEEKLY COLLECTION SUMMARY (auto-calculated from payment log)
A158: Week | B158: Week Starting | C158: Entries | D158: Cash | E158: MoMo (All) | F158: Bank Transfer | G158: Cheque | H158: Week Total | I158: Cumulative | J158: vs Deadline | K158: Notes
A159: Wk 1 (21 Apr) | B159: 46133 | C159: =COUNTIF(E5:E154,"Wk 1 (21 Apr)") -> 0 | D159: =SUMPRODUCT((E5:E154="Wk 1 (21 Apr)")*(G5:G154="Cash")*(F5:F154)) -> 0 | E159: =SUMPRODUCT((E5:E154="Wk 1 (21 Apr)")*((G5:G154="MTN MoMo")+(G5:G154="Vodafone Cash")+(G5:G154="AirtelTigo Money"))*(F5:F154)) -> 0 | F159: =SUMPRODUCT((E5:E154="Wk 1 (21 Apr)")*(G5:G154="Bank Transfer")*(F5:F154)) -> 0 | G159: =SUMPRODUCT((E5:E154="Wk 1 (21 Apr)")*(G5:G154="Cheque")*(F5:F154)) -> 0 | H159: =SUM(D159:G159) -> 0 | I159: =H159 -> 0
A160: Wk 2 (28 Apr) | B160: 46140 | C160: =COUNTIF(E5:E154,"Wk 2 (28 Apr)") -> 2 | D160: =SUMPRODUCT((E5:E154="Wk 2 (28 Apr)")*(G5:G154="Cash")*(F5:F154)) -> 0 | E160: =SUMPRODUCT((E5:E154="Wk 2 (28 Apr)")*((G5:G154="MTN MoMo")+(G5:G154="Vodafone Cash")+(G5:G154="AirtelTigo Money"))*(F5:F154)) -> 1000 | F160: =SUMPRODUCT((E5:E154="Wk 2 (28 Apr)")*(G5:G154="Bank Transfer")*(F5:F154)) -> 2400 | G160: =SUMPRODUCT((E5:E154="Wk 2 (28 Apr)")*(G5:G154="Cheque")*(F5:F154)) -> 0 | H160: =SUM(D160:G160) -> 3400 | I160: =I159+H160 -> 3400
A161: Wk 3 (05 May) | B161: 46147 | C161: =COUNTIF(E5:E154,"Wk 3 (05 May)") -> 2 | D161: =SUMPRODUCT((E5:E154="Wk 3 (05 May)")*(G5:G154="Cash")*(F5:F154)) -> 2400 | E161: =SUMPRODUCT((E5:E154="Wk 3 (05 May)")*((G5:G154="MTN MoMo")+(G5:G154="Vodafone Cash")+(G5:G154="AirtelTigo Money"))*(F5:F154)) -> 749.5 | F161: =SUMPRODUCT((E5:E154="Wk 3 (05 May)")*(G5:G154="Bank Transfer")*(F5:F154)) -> 0 | G161: =SUMPRODUCT((E5:E154="Wk 3 (05 May)")*(G5:G154="Cheque")*(F5:F154)) -> 0 | H161: =SUM(D161:G161) -> 3149.5 | I161: =I160+H161 -> 6549.5
A162: Wk 4 (12 May) | B162: 46154 | C162: =COUNTIF(E5:E154,"Wk 4 (12 May)") -> 3 | D162: =SUMPRODUCT((E5:E154="Wk 4 (12 May)")*(G5:G154="Cash")*(F5:F154)) -> 0 | E162: =SUMPRODUCT((E5:E154="Wk 4 (12 May)")*((G5:G154="MTN MoMo")+(G5:G154="Vodafone Cash")+(G5:G154="AirtelTigo Money"))*(F5:F154)) -> 1500 | F162: =SUMPRODUCT((E5:E154="Wk 4 (12 May)")*(G5:G154="Bank Transfer")*(F5:F154)) -> 4560 | G162: =SUMPRODUCT((E5:E154="Wk 4 (12 May)")*(G5:G154="Cheque")*(F5:F154)) -> 0 | H162: =SUM(D162:G162) -> 6060 | I162: =I161+H162 -> 12609.5
A163: Wk 5 (19 May) | B163: 46161 | C163: =COUNTIF(E5:E154,"Wk 5 (19 May)") -> 0 | D163: =SUMPRODUCT((E5:E154="Wk 5 (19 May)")*(G5:G154="Cash")*(F5:F154)) -> 0 | E163: =SUMPRODUCT((E5:E154="Wk 5 (19 May)")*((G5:G154="MTN MoMo")+(G5:G154="Vodafone Cash")+(G5:G154="AirtelTigo Money"))*(F5:F154)) -> 0 | F163: =SUMPRODUCT((E5:E154="Wk 5 (19 May)")*(G5:G154="Bank Transfer")*(F5:F154)) -> 0 | G163: =SUMPRODUCT((E5:E154="Wk 5 (19 May)")*(G5:G154="Cheque")*(F5:F154)) -> 0 | H163: =SUM(D163:G163) -> 0 | I163: =I162+H163 -> 12609.5
A164: Wk 6 (26 May) | B164: 46168 | C164: =COUNTIF(E5:E154,"Wk 6 (26 May)") -> 3 | D164: =SUMPRODUCT((E5:E154="Wk 6 (26 May)")*(G5:G154="Cash")*(F5:F154)) -> 0 | E164: =SUMPRODUCT((E5:E154="Wk 6 (26 May)")*((G5:G154="MTN MoMo")+(G5:G154="Vodafone Cash")+(G5:G154="AirtelTigo Money"))*(F5:F154)) -> 5230.5 | F164: =SUMPRODUCT((E5:E154="Wk 6 (26 May)")*(G5:G154="Bank Transfer")*(F5:F154)) -> 1500 | G164: =SUMPRODUCT((E5:E154="Wk 6 (26 May)")*(G5:G154="Cheque")*(F5:F154)) -> 0 | H164: =SUM(D164:G164) -> 6730.5 | I164: =I163+H164 -> 19340
A165: Wk 7 (02 Jun) | B165: 46175 | C165: =COUNTIF(E5:E154,"Wk 7 (02 Jun)") -> 0 | D165: =SUMPRODUCT((E5:E154="Wk 7 (02 Jun)")*(G5:G154="Cash")*(F5:F154)) -> 0 | E165: =SUMPRODUCT((E5:E154="Wk 7 (02 Jun)")*((G5:G154="MTN MoMo")+(G5:G154="Vodafone Cash")+(G5:G154="AirtelTigo Money"))*(F5:F154)) -> 0 | F165: =SUMPRODUCT((E5:E154="Wk 7 (02 Jun)")*(G5:G154="Bank Transfer")*(F5:F154)) -> 0 | G165: =SUMPRODUCT((E5:E154="Wk 7 (02 Jun)")*(G5:G154="Cheque")*(F5:F154)) -> 0 | H165: =SUM(D165:G165) -> 0 | I165: =I164+H165 -> 19340
A166: Wk 8 (09 Jun) | B166: 46182 | C166: =COUNTIF(E5:E154,"Wk 8 (09 Jun)") -> 1 | D166: =SUMPRODUCT((E5:E154="Wk 8 (09 Jun)")*(G5:G154="Cash")*(F5:F154)) -> 0 | E166: =SUMPRODUCT((E5:E154="Wk 8 (09 Jun)")*((G5:G154="MTN MoMo")+(G5:G154="Vodafone Cash")+(G5:G154="AirtelTigo Money"))*(F5:F154)) -> 2400 | F166: =SUMPRODUCT((E5:E154="Wk 8 (09 Jun)")*(G5:G154="Bank Transfer")*(F5:F154)) -> 0 | G166: =SUMPRODUCT((E5:E154="Wk 8 (09 Jun)")*(G5:G154="Cheque")*(F5:F154)) -> 0 | H166: =SUM(D166:G166) -> 2400 | I166: =I165+H166 -> 21740
A167: Wk 9 (16 Jun) | B167: 46189 | C167: =COUNTIF(E5:E154,"Wk 9 (16 Jun)") -> 1 | D167: =SUMPRODUCT((E5:E154="Wk 9 (16 Jun)")*(G5:G154="Cash")*(F5:F154)) -> 0 | E167: =SUMPRODUCT((E5:E154="Wk 9 (16 Jun)")*((G5:G154="MTN MoMo")+(G5:G154="Vodafone Cash")+(G5:G154="AirtelTigo Money"))*(F5:F154)) -> 1500 | F167: =SUMPRODUCT((E5:E154="Wk 9 (16 Jun)")*(G5:G154="Bank Transfer")*(F5:F154)) -> 0 | G167: =SUMPRODUCT((E5:E154="Wk 9 (16 Jun)")*(G5:G154="Cheque")*(F5:F154)) -> 0 | H167: =SUM(D167:G167) -> 1500 | I167: =I166+H167 -> 23240
A168: Wk 10 (23 Jun) | B168: 46196 | C168: =COUNTIF(E5:E154,"Wk 10 (23 Jun)") -> 0 | D168: =SUMPRODUCT((E5:E154="Wk 10 (23 Jun)")*(G5:G154="Cash")*(F5:F154)) -> 0 | E168: =SUMPRODUCT((E5:E154="Wk 10 (23 Jun)")*((G5:G154="MTN MoMo")+(G5:G154="Vodafone Cash")+(G5:G154="AirtelTigo Money"))*(F5:F154)) -> 0 | F168: =SUMPRODUCT((E5:E154="Wk 10 (23 Jun)")*(G5:G154="Bank Transfer")*(F5:F154)) -> 0 | G168: =SUMPRODUCT((E5:E154="Wk 10 (23 Jun)")*(G5:G154="Cheque")*(F5:F154)) -> 0 | H168: =SUM(D168:G168) -> 0 | I168: =I167+H168 -> 23240
A169: Wk 11 (30 Jun) | B169: 46203 | C169: =COUNTIF(E5:E154,"Wk 11 (30 Jun)") -> 0 | D169: =SUMPRODUCT((E5:E154="Wk 11 (30 Jun)")*(G5:G154="Cash")*(F5:F154)) -> 0 | E169: =SUMPRODUCT((E5:E154="Wk 11 (30 Jun)")*((G5:G154="MTN MoMo")+(G5:G154="Vodafone Cash")+(G5:G154="AirtelTigo Money"))*(F5:F154)) -> 0 | F169: =SUMPRODUCT((E5:E154="Wk 11 (30 Jun)")*(G5:G154="Bank Transfer")*(F5:F154)) -> 0 | G169: =SUMPRODUCT((E5:E154="Wk 11 (30 Jun)")*(G5:G154="Cheque")*(F5:F154)) -> 0 | H169: =SUM(D169:G169) -> 0 | I169: =I168+H169 -> 23240
A170: Wk 12 (07 Jul) | B170: 46210 | C170: =COUNTIF(E5:E154,"Wk 12 (07 Jul)") -> 2 | D170: =SUMPRODUCT((E5:E154="Wk 12 (07 Jul)")*(G5:G154="Cash")*(F5:F154)) -> 0 | E170: =SUMPRODUCT((E5:E154="Wk 12 (07 Jul)")*((G5:G154="MTN MoMo")+(G5:G154="Vodafone Cash")+(G5:G154="AirtelTigo Money"))*(F5:F154)) -> 900 | F170: =SUMPRODUCT((E5:E154="Wk 12 (07 Jul)")*(G5:G154="Bank Transfer")*(F5:F154)) -> 900 | G170: =SUMPRODUCT((E5:E154="Wk 12 (07 Jul)")*(G5:G154="Cheque")*(F5:F154)) -> 0 | H170: =SUM(D170:G170) -> 1800 | I170: =I169+H170 -> 25040 | J170: PAST DEADLINE
A171: Wk 13 (14 Jul) | B171: 46217 | C171: =COUNTIF(E5:E154,"Wk 13 (14 Jul)") -> 1 | D171: =SUMPRODUCT((E5:E154="Wk 13 (14 Jul)")*(G5:G154="Cash")*(F5:F154)) -> 0 | E171: =SUMPRODUCT((E5:E154="Wk 13 (14 Jul)")*((G5:G154="MTN MoMo")+(G5:G154="Vodafone Cash")+(G5:G154="AirtelTigo Money"))*(F5:F154)) -> 2400 | F171: =SUMPRODUCT((E5:E154="Wk 13 (14 Jul)")*(G5:G154="Bank Transfer")*(F5:F154)) -> 0 | G171: =SUMPRODUCT((E5:E154="Wk 13 (14 Jul)")*(G5:G154="Cheque")*(F5:F154)) -> 0 | H171: =SUM(D171:G171) -> 2400 | I171: =I170+H171 -> 27440 | J171: PAST DEADLINE
A172: Wk 14 (21 Jul) | B172: 46224 | C172: =COUNTIF(E5:E154,"Wk 14 (21 Jul)") -> 0 | D172: =SUMPRODUCT((E5:E154="Wk 14 (21 Jul)")*(G5:G154="Cash")*(F5:F154)) -> 0 | E172: =SUMPRODUCT((E5:E154="Wk 14 (21 Jul)")*((G5:G154="MTN MoMo")+(G5:G154="Vodafone Cash")+(G5:G154="AirtelTigo Money"))*(F5:F154)) -> 0 | F172: =SUMPRODUCT((E5:E154="Wk 14 (21 Jul)")*(G5:G154="Bank Transfer")*(F5:F154)) -> 0 | G172: =SUMPRODUCT((E5:E154="Wk 14 (21 Jul)")*(G5:G154="Cheque")*(F5:F154)) -> 0 | H172: =SUM(D172:G172) -> 0 | I172: =I171+H172 -> 27440 | J172: PAST DEADLINE
A173: TERM 3 TOTAL | C173: =SUM(C159:C172) -> 15 | D173: =SUM(D159:D172) -> 2400 | E173: =SUM(E159:E172) -> 15680 | F173: =SUM(F159:F172) -> 9360 | G173: =SUM(G159:G172) -> 0 | H173: =SUM(H159:H172) -> 27440
A176: MONTHLY COLLECTION SUMMARY
A177: Month | B177: No. of Payments | C177: Cash | D177: MoMo (All) | E177: Bank Transfer | F177: Cheque | G177: Month Total | H177: Cumulative | I177: Target % | J177: Actual % | K177: Notes
A178: Apr | B178: =SUMPRODUCT((MONTH(A5:A154)=4)*(A5:A154<>"")) -> 2 | C178: =SUMPRODUCT((MONTH(A5:A154)=4)*(G5:G154="Cash")*(F5:F154)) -> 0 | D178: =SUMPRODUCT((MONTH(A5:A154)=4)*((G5:G154="MTN MoMo")+(G5:G154="Vodafone Cash")+(G5:G154="AirtelTigo Money"))*(F5:F154)) -> 1000 | E178: =SUMPRODUCT((MONTH(A5:A154)=4)*(G5:G154="Bank Transfer")*(F5:F154)) -> 2400 | F178: =SUMPRODUCT((MONTH(A5:A154)=4)*(G5:G154="Cheque")*(F5:F154)) -> 0 | G178: =SUM(C178:F178) -> 3400 | H178: =G178 -> 3400 | I178: 0.3
A179: May | B179: =SUMPRODUCT((MONTH(A5:A154)=5)*(A5:A154<>"")) -> 8 | C179: =SUMPRODUCT((MONTH(A5:A154)=5)*(G5:G154="Cash")*(F5:F154)) -> 2400 | D179: =SUMPRODUCT((MONTH(A5:A154)=5)*((G5:G154="MTN MoMo")+(G5:G154="Vodafone Cash")+(G5:G154="AirtelTigo Money"))*(F5:F154)) -> 7480 | E179: =SUMPRODUCT((MONTH(A5:A154)=5)*(G5:G154="Bank Transfer")*(F5:F154)) -> 6060 | F179: =SUMPRODUCT((MONTH(A5:A154)=5)*(G5:G154="Cheque")*(F5:F154)) -> 0 | G179: =SUM(C179:F179) -> 15940 | H179: =H178+G179 -> 19340 | I179: 0.65
A180: Jun | B180: =SUMPRODUCT((MONTH(A5:A154)=6)*(A5:A154<>"")) -> 2 | C180: =SUMPRODUCT((MONTH(A5:A154)=6)*(G5:G154="Cash")*(F5:F154)) -> 0 | D180: =SUMPRODUCT((MONTH(A5:A154)=6)*((G5:G154="MTN MoMo")+(G5:G154="Vodafone Cash")+(G5:G154="AirtelTigo Money"))*(F5:F154)) -> 3900 | E180: =SUMPRODUCT((MONTH(A5:A154)=6)*(G5:G154="Bank Transfer")*(F5:F154)) -> 0 | F180: =SUMPRODUCT((MONTH(A5:A154)=6)*(G5:G154="Cheque")*(F5:F154)) -> 0 | G180: =SUM(C180:F180) -> 3900 | H180: =H179+G180 -> 23240 | I180: 1
A181: Jul | B181: =SUMPRODUCT((MONTH(A5:A154)=7)*(A5:A154<>"")) -> 1 | C181: =SUMPRODUCT((MONTH(A5:A154)=7)*(G5:G154="Cash")*(F5:F154)) -> 0 | D181: =SUMPRODUCT((MONTH(A5:A154)=7)*((G5:G154="MTN MoMo")+(G5:G154="Vodafone Cash")+(G5:G154="AirtelTigo Money"))*(F5:F154)) -> 2400 | E181: =SUMPRODUCT((MONTH(A5:A154)=7)*(G5:G154="Bank Transfer")*(F5:F154)) -> 0 | F181: =SUMPRODUCT((MONTH(A5:A154)=7)*(G5:G154="Cheque")*(F5:F154)) -> 0 | G181: =SUM(C181:F181) -> 2400 | H181: =H180+G181 -> 25640 | I181: 1
A182: TOTAL | B182: =SUM(B178:B181) -> 13 | C182: =SUM(C178:C181) -> 2400 | D182: =SUM(D178:D181) -> 14780 | E182: =SUM(E178:E181) -> 8460 | F182: =SUM(F178:F181) -> 0 | G182: =SUM(G178:G181) -> 25640

Sheet KG 1 - Kingfishers
A1: KG 1: Kingfishers — Precision | Focus | Annual: GHS 7,350 | Termly: GHS 2,550
A3: PUPIL DETAILS | D3: TERM 1 (COMPLETED) | H3: TERM 2 (COMPLETED) | M3: TERM 3 (ACTIVE — arrears from T1/T2 included) | Q3: NOTES
A4: No. | B4: Pupil Name | C4: Discount Type | D4: T1 Fee | E4: T1 Arrears BF | F4: T1 Paid | G4: T1 Balance | H4: T2 Fee | I4: T2 Arrears BF | J4: T2 Discount | K4: T2 Paid | L4: T2 Balance | M4: T3 Fee | N4: T3 Discount | O4: T3 Paid | P4: T3 Balance | Q4: Remarks / Waiver Notes
A6: 1 | B6: Agyapong A. Akyedie Emmalyn-Rosemond | D6: 2550 | F6: 1700 | G6: =IF(B6="","",IF(D6="",0,D6)+IF(E6="",0,E6)-IF(F6="",0,F6)) -> 850 | H6: 2550 | K6: 2550 | L6: =IF(B6="","",IF(H6="",0,H6)+IF(I6="",0,I6)-IF(J6="",0,J6)-IF(K6="",0,K6)) -> 0 | M6: 0 | O6: =SUMIF('KG 1 - Payments'!C5:C154,B6,'KG 1 - Payments'!F5:F154) -> 0 | P6: =IF(B6="","",IF(M6="",0,M6)-IF(N6="",0,N6)+IF(L6<0,0,IF(L6="",0,L6))-IF(O6="",0,O6)) -> 0
A7: 2 | B7: Asare Tony Papa Kwesi | D7: 2550 | F7: 1000 | G7: =IF(B7="","",IF(D7="",0,D7)+IF(E7="",0,E7)-IF(F7="",0,F7)) -> 1550 | H7: 2550 | K7: 2550 | L7: =IF(B7="","",IF(H7="",0,H7)+IF(I7="",0,I7)-IF(J7="",0,J7)-IF(K7="",0,K7)) -> 0 | M7: 2550 | O7: =SUMIF('KG 1 - Payments'!C5:C154,B7,'KG 1 - Payments'!F5:F154) -> 2550 | P7: =IF(B7="","",IF(M7="",0,M7)-IF(N7="",0,N7)+IF(L7<0,0,IF(L7="",0,L7))-IF(O7="",0,O7)) -> 0 | Q7: T1 partial (GHS 1,550 short); T2 fully settled
A8: 3 | B8: Darko Asher Kukuwa | D8: 2550 | E8: 1450 | F8: 2550 | G8: =IF(B8="","",IF(D8="",0,D8)+IF(E8="",0,E8)-IF(F8="",0,F8)) -> 1450 | H8: 2550 | I8: 1550 | K8: 3600 | L8: =IF(B8="","",IF(H8="",0,H8)+IF(I8="",0,I8)-IF(J8="",0,J8)-IF(K8="",0,K8)) -> 500 | M8: 2550 | O8: =SUMIF('KG 1 - Payments'!C5:C154,B8,'KG 1 - Payments'!F5:F154) -> 2550 | P8: =IF(B8="","",IF(M8="",0,M8)-IF(N8="",0,N8)+IF(L8<0,0,IF(L8="",0,L8))-IF(O8="",0,O8)) -> 500 | Q8: Prior year BF GHS 1,450; reduced to GHS 500 by T2 end
A9: 4 | B9: Monney Obrempong Nyamedo | C9: Sibling | D9: 2422.5 | F9: 2422.5 | G9: =IF(B9="","",IF(D9="",0,D9)+IF(E9="",0,E9)-IF(F9="",0,F9)) -> 0 | H9: 2550 | J9: 127.5 | K9: 2422.5 | L9: =IF(B9="","",IF(H9="",0,H9)+IF(I9="",0,I9)-IF(J9="",0,J9)-IF(K9="",0,K9)) -> 0 | M9: 2550 | N9: 127.5 | O9: =SUMIF('KG 1 - Payments'!C5:C154,B9,'KG 1 - Payments'!F5:F154) -> 2422.5 | P9: =IF(B9="","",IF(M9="",0,M9)-IF(N9="",0,N9)+IF(L9<0,0,IF(L9="",0,L9))-IF(O9="",0,O9)) -> 0
A10: 5 | B10: Rufai Kiara Nhyira | D10: 2550 | F10: 2550 | G10: =IF(B10="","",IF(D10="",0,D10)+IF(E10="",0,E10)-IF(F10="",0,F10)) -> 0 | H10: 2550 | K10: 2550 | L10: =IF(B10="","",IF(H10="",0,H10)+IF(I10="",0,I10)-IF(J10="",0,J10)-IF(K10="",0,K10)) -> 0 | M10: 2550 | O10: =SUMIF('KG 1 - Payments'!C5:C154,B10,'KG 1 - Payments'!F5:F154) -> 2550 | P10: =IF(B10="","",IF(M10="",0,M10)-IF(N10="",0,N10)+IF(L10<0,0,IF(L10="",0,L10))-IF(O10="",0,O10)) -> 0
A11: 6 | B11: Precious Dogbatsey | G11: =IF(B11="","",0) -> 0 | L11: =IF(B11="","",0) -> 0 | M11: 2550 | P11: =IF(B11="","",0) -> 0
A12: 7 | G12: =IF(B12="","",0) | L12: =IF(B12="","",0) | P12: =IF(B12="","",0)
A13: 8 | G13: =IF(B13="","",0) | L13: =IF(B13="","",0) | P13: =IF(B13="","",0)
A14: 9 | G14: =IF(B14="","",0) | L14: =IF(B14="","",0) | P14: =IF(B14="","",0)
A15: 10 | G15: =IF(B15="","",0) | L15: =IF(B15="","",0) | P15: =IF(B15="","",0)
A16: 11 | G16: =IF(B16="","",0) | L16: =IF(B16="","",0) | P16: =IF(B16="","",0)
A17: 12 | G17: =IF(B17="","",0) | L17: =IF(B17="","",0) | P17: =IF(B17="","",0)
A18: 13 | G18: =IF(B18="","",0) | L18: =IF(B18="","",0) | P18: =IF(B18="","",0)
A19: 14 | G19: =IF(B19="","",0) | L19: =IF(B19="","",0) | P19: =IF(B19="","",0)
A20: 15 | G20: =IF(B20="","",0) | L20: =IF(B20="","",0) | P20: =IF(B20="","",0)
B21: TOTALS | D21: =SUM(D6:D20) -> 12622.5 | E21: =SUM(E6:E20) -> 1450 | F21: =SUM(F6:F20) -> 10222.5 | G21: =SUM(G6:G20) -> 3850 | H21: =SUM(H6:H20) -> 12750 | I21: =SUM(I6:I20) -> 1550 | J21: =SUM(J6:J20) -> 127.5 | K21: =SUM(K6:K20) -> 13672.5 | ... P21: =SUM(P6:P20) -> 500
B22: Collection Rate: | F22: T1: | G22: =IF(D21+E21=0,1,F21/(D21+E21)) -> 0.72641677 | K22: T2: | L22: =IF(H21+I21-J21=0,1,K21/(H21+I21-J21)) -> 0.96472041 | O22: =SUMIF('KG 1 - Payments'!C5:C154,B22,'KG 1 - Payments'!F5:F154) -> 0

Sheet KG 1 - Payments
A1: KG 1: Kingfishers — PAYMENT RECEIPTS LOG (Term 3, 2025/26: 21 Apr – 24 Jul 2026) | P1: Adjei-Djeton Jahmiel
A2: Payment deadline: 30 June 2026 | Enter one row per payment | T3 Paid on class register auto-updates via SUMIFS | P2: Agyapong A.A.E. Rosemond
A3: TRANSACTION DETAILS | G3: PAYMENT | J3: VERIFICATION | P3: Ansah-Darko Carissa Elyon
A4: Date | B4: Receipt No. | C4: Pupil Name | D4: Term | E4: Week | F4: Amount (GHS) | G4: Payment Method | H4: Received By | I4: Running Total | J4: Verified | K4: Notes | P4: Appiah Serwaa Senam
A5: 46134 | B5: 1046 | C5: Precious Dogbatsey | D5: Term 3 | E5: Wk 1 (21 Apr) | F5: 2550 | G5: MTN MoMo / Cash | H5: Other | I5: =IF(F5="","",F5) -> 2550 | P5: Asare Nana Ama Sakyibea
A6: 46141 | B6: 1059 | C6: Asare Tony Papa Kwesi | D6: Term 3 | E6: Wk 2 (28 Apr) | F6: 1000 | G6: Cash | H6: Dorcas Matilda Akosua Kusi | I6: =IF(F6="","",IF(I5="",F6,I5+F6)) -> 3550 | P6: Asare Tony Papa Kwesi
A7: 46162 | B7: 1078 | C7: Rufai Kiara Nhyira | D7: Term 3 | E7: Wk 5 (19 May) | F7: 2550 | G7: Bank Transfer | H7: Dorcas Matilda Akosua Kusi | I7: =IF(F7="","",IF(I6="",F7,I6+F7)) -> 6100 | P7: Ayeh-Kumi Jomari Paakow
A8: 46168 | B8: 1091 | C8: Darko Asher Kukuwa | D8: Term 3 | E8: Wk 6 (26 May) | F8: 1050 | G8: MTN MoMo | H8: Dorcas Matilda Akosua Kusi | I8: =IF(F8="","",IF(I7="",F8,I7+F8)) -> 7150 | P8: Bakari Lilian Jamima
A9: 46136 | B9: 1099 | C9: Monney Obrempong Nyamedo | D9: Term 3 | E9: Wk 1 (21 Apr) | F9: 1000 | G9: Bank Transfer | H9: Dorcas Matilda Akosua Kusi | I9: =IF(F9="","",IF(I8="",F9,I8+F9)) -> 8150 | P9: Boafo Ivanna Asabea
A10: 46167 | B10: 1102 | C10: Monney Obrempong Nyamedo | D10: Term 3 | E10: Wk 6 (26 May) | F10: 1422.5 | G10: Bank Transfer | H10: Dorcas Matilda Akosua Kusi | I10: =IF(F10="","",IF(I9="",F10,I9+F10)) -> 9572.5 | P10: Darko Asher Kukuwa
A11: 46183 | B11: 1111 | C11: Asare Tony Papa Kwesi | D11: Term 3 | E11: Wk 8 (09 Jun) | F11: 1550 | G11: Cash | H11: Other | I11: =IF(F11="","",IF(I10="",F11,I10+F11)) -> 11122.5 | P11: Kanati Jed Elikem
A12: 46191 | B12: 1117 | C12: Darko Asher Kukuwa | D12: Term 3 | E12: Wk 9 (16 Jun) | F12: 1000 | G12: MTN MoMo | H12: Dorcas Matilda Akosua Kusi | I12: =IF(F12="","",IF(I11="",F12,I11+F12)) -> 12122.5 | P12: Monney Obrempong Nyamedo
A13: 13/07/2026 | B13: 1136 | C13: Darko Asher Kukuwa | D13: Term 3 | E13: Wk 13 (14 Jul) | F13: 500 | G13: MTN MoMo | H13: Dorcas Matilda Akosua Kusi | I13: =IF(F13="","",IF(I12="",F13,I12+F13)) -> 12622.5 | P13: Rufai Kiara Nhyira
I14: =IF(F14="","",IF(I13="",F14,I13+F14))
I15: =IF(F15="","",IF(I14="",F15,I14+F15))
I16: =IF(F16="","",IF(I15="",F16,I15+F16))
I17: =IF(F17="","",IF(I16="",F17,I16+F17))
I18: =IF(F18="","",IF(I17="",F18,I17+F18))
I19: =IF(F19="","",IF(I18="",F19,I18+F19))
I20: =IF(F20="","",IF(I19="",F20,I19+F20))
I21: =IF(F21="","",IF(I20="",F21,I20+F21))
I22: =IF(F22="","",IF(I21="",F22,I21+F22))
I23: =IF(F23="","",IF(I22="",F23,I22+F23))
I24: =IF(F24="","",IF(I23="",F24,I23+F24))
I25: =IF(F25="","",IF(I24="",F25,I24+F25))
... I154: =IF(F154="","",IF(I153="",F154,I153+F154))
A157: WEEKLY COLLECTION SUMMARY (auto-calculated from payment log)
A158: Week | B158: Week Starting | C158: Entries | D158: Cash | E158: MoMo (All) | F158: Bank Transfer | G158: Cheque | H158: Week Total | I158: Cumulative | J158: vs Deadline | K158: Notes
A159: Wk 1 (21 Apr) | B159: 46133 | C159: =COUNTIF(E5:E154,"Wk 1 (21 Apr)") -> 2 | D159: =SUMPRODUCT((E5:E154="Wk 1 (21 Apr)")*(G5:G154="Cash")*(F5:F154)) -> 0 | E159: =SUMPRODUCT((E5:E154="Wk 1 (21 Apr)")*((G5:G154="MTN MoMo")+(G5:G154="Vodafone Cash")+(G5:G154="AirtelTigo Money"))*(F5:F154)) -> 0 | F159: =SUMPRODUCT((E5:E154="Wk 1 (21 Apr)")*(G5:G154="Bank Transfer")*(F5:F154)) -> 1000 | G159: =SUMPRODUCT((E5:E154="Wk 1 (21 Apr)")*(G5:G154="Cheque")*(F5:F154)) -> 0 | H159: =SUM(D159:G159) -> 1000 | I159: =H159 -> 1000
A160: Wk 2 (28 Apr) | B160: 46140 | C160: =COUNTIF(E5:E154,"Wk 2 (28 Apr)") -> 1 | D160: =SUMPRODUCT((E5:E154="Wk 2 (28 Apr)")*(G5:G154="Cash")*(F5:F154)) -> 1000 | E160: =SUMPRODUCT((E5:E154="Wk 2 (28 Apr)")*((G5:G154="MTN MoMo")+(G5:G154="Vodafone Cash")+(G5:G154="AirtelTigo Money"))*(F5:F154)) -> 0 | F160: =SUMPRODUCT((E5:E154="Wk 2 (28 Apr)")*(G5:G154="Bank Transfer")*(F5:F154)) -> 0 | G160: =SUMPRODUCT((E5:E154="Wk 2 (28 Apr)")*(G5:G154="Cheque")*(F5:F154)) -> 0 | H160: =SUM(D160:G160) -> 1000 | I160: =I159+H160 -> 2000
A161: Wk 3 (05 May) | B161: 46147 | C161: =COUNTIF(E5:E154,"Wk 3 (05 May)") -> 0 | D161: =SUMPRODUCT((E5:E154="Wk 3 (05 May)")*(G5:G154="Cash")*(F5:F154)) -> 0 | E161: =SUMPRODUCT((E5:E154="Wk 3 (05 May)")*((G5:G154="MTN MoMo")+(G5:G154="Vodafone Cash")+(G5:G154="AirtelTigo Money"))*(F5:F154)) -> 0 | F161: =SUMPRODUCT((E5:E154="Wk 3 (05 May)")*(G5:G154="Bank Transfer")*(F5:F154)) -> 0 | G161: =SUMPRODUCT((E5:E154="Wk 3 (05 May)")*(G5:G154="Cheque")*(F5:F154)) -> 0 | H161: =SUM(D161:G161) -> 0 | I161: =I160+H161 -> 2000
A162: Wk 4 (12 May) | B162: 46154 | C162: =COUNTIF(E5:E154,"Wk 4 (12 May)") -> 0 | D162: =SUMPRODUCT((E5:E154="Wk 4 (12 May)")*(G5:G154="Cash")*(F5:F154)) -> 0 | E162: =SUMPRODUCT((E5:E154="Wk 4 (12 May)")*((G5:G154="MTN MoMo")+(G5:G154="Vodafone Cash")+(G5:G154="AirtelTigo Money"))*(F5:F154)) -> 0 | F162: =SUMPRODUCT((E5:E154="Wk 4 (12 May)")*(G5:G154="Bank Transfer")*(F5:F154)) -> 0 | G162: =SUMPRODUCT((E5:E154="Wk 4 (12 May)")*(G5:G154="Cheque")*(F5:F154)) -> 0 | H162: =SUM(D162:G162) -> 0 | I162: =I161+H162 -> 2000
A163: Wk 5 (19 May) | B163: 46161 | C163: =COUNTIF(E5:E154,"Wk 5 (19 May)") -> 1 | D163: =SUMPRODUCT((E5:E154="Wk 5 (19 May)")*(G5:G154="Cash")*(F5:F154)) -> 0 | E163: =SUMPRODUCT((E5:E154="Wk 5 (19 May)")*((G5:G154="MTN MoMo")+(G5:G154="Vodafone Cash")+(G5:G154="AirtelTigo Money"))*(F5:F154)) -> 0 | F163: =SUMPRODUCT((E5:E154="Wk 5 (19 May)")*(G5:G154="Bank Transfer")*(F5:F154)) -> 2550 | G163: =SUMPRODUCT((E5:E154="Wk 5 (19 May)")*(G5:G154="Cheque")*(F5:F154)) -> 0 | H163: =SUM(D163:G163) -> 2550 | I163: =I162+H163 -> 4550
A164: Wk 6 (26 May) | B164: 46168 | C164: =COUNTIF(E5:E154,"Wk 6 (26 May)") -> 2 | D164: =SUMPRODUCT((E5:E154="Wk 6 (26 May)")*(G5:G154="Cash")*(F5:F154)) -> 0 | E164: =SUMPRODUCT((E5:E154="Wk 6 (26 May)")*((G5:G154="MTN MoMo")+(G5:G154="Vodafone Cash")+(G5:G154="AirtelTigo Money"))*(F5:F154)) -> 1050 | F164: =SUMPRODUCT((E5:E154="Wk 6 (26 May)")*(G5:G154="Bank Transfer")*(F5:F154)) -> 1422.5 | G164: =SUMPRODUCT((E5:E154="Wk 6 (26 May)")*(G5:G154="Cheque")*(F5:F154)) -> 0 | H164: =SUM(D164:G164) -> 2472.5 | I164: =I163+H164 -> 7022.5
A165: Wk 7 (02 Jun) | B165: 46175 | C165: =COUNTIF(E5:E154,"Wk 7 (02 Jun)") -> 0 | D165: =SUMPRODUCT((E5:E154="Wk 7 (02 Jun)")*(G5:G154="Cash")*(F5:F154)) -> 0 | E165: =SUMPRODUCT((E5:E154="Wk 7 (02 Jun)")*((G5:G154="MTN MoMo")+(G5:G154="Vodafone Cash")+(G5:G154="AirtelTigo Money"))*(F5:F154)) -> 0 | F165: =SUMPRODUCT((E5:E154="Wk 7 (02 Jun)")*(G5:G154="Bank Transfer")*(F5:F154)) -> 0 | G165: =SUMPRODUCT((E5:E154="Wk 7 (02 Jun)")*(G5:G154="Cheque")*(F5:F154)) -> 0 | H165: =SUM(D165:G165) -> 0 | I165: =I164+H165 -> 7022.5
A166: Wk 8 (09 Jun) | B166: 46182 | C166: =COUNTIF(E5:E154,"Wk 8 (09 Jun)") -> 1 | D166: =SUMPRODUCT((E5:E154="Wk 8 (09 Jun)")*(G5:G154="Cash")*(F5:F154)) -> 1550 | E166: =SUMPRODUCT((E5:E154="Wk 8 (09 Jun)")*((G5:G154="MTN MoMo")+(G5:G154="Vodafone Cash")+(G5:G154="AirtelTigo Money"))*(F5:F154)) -> 0 | F166: =SUMPRODUCT((E5:E154="Wk 8 (09 Jun)")*(G5:G154="Bank Transfer")*(F5:F154)) -> 0 | G166: =SUMPRODUCT((E5:E154="Wk 8 (09 Jun)")*(G5:G154="Cheque")*(F5:F154)) -> 0 | H166: =SUM(D166:G166) -> 1550 | I166: =I165+H166 -> 8572.5
A167: Wk 9 (16 Jun) | B167: 46189 | C167: =COUNTIF(E5:E154,"Wk 9 (16 Jun)") -> 1 | D167: =SUMPRODUCT((E5:E154="Wk 9 (16 Jun)")*(G5:G154="Cash")*(F5:F154)) -> 0 | E167: =SUMPRODUCT((E5:E154="Wk 9 (16 Jun)")*((G5:G154="MTN MoMo")+(G5:G154="Vodafone Cash")+(G5:G154="AirtelTigo Money"))*(F5:F154)) -> 1000 | F167: =SUMPRODUCT((E5:E154="Wk 9 (16 Jun)")*(G5:G154="Bank Transfer")*(F5:F154)) -> 0 | G167: =SUMPRODUCT((E5:E154="Wk 9 (16 Jun)")*(G5:G154="Cheque")*(F5:F154)) -> 0 | H167: =SUM(D167:G167) -> 1000 | I167: =I166+H167 -> 9572.5
A168: Wk 10 (23 Jun) | B168: 46196 | C168: =COUNTIF(E5:E154,"Wk 10 (23 Jun)") -> 0 | D168: =SUMPRODUCT((E5:E154="Wk 10 (23 Jun)")*(G5:G154="Cash")*(F5:F154)) -> 0 | E168: =SUMPRODUCT((E5:E154="Wk 10 (23 Jun)")*((G5:G154="MTN MoMo")+(G5:G154="Vodafone Cash")+(G5:G154="AirtelTigo Money"))*(F5:F154)) -> 0 | F168: =SUMPRODUCT((E5:E154="Wk 10 (23 Jun)")*(G5:G154="Bank Transfer")*(F5:F154)) -> 0 | G168: =SUMPRODUCT((E5:E154="Wk 10 (23 Jun)")*(G5:G154="Cheque")*(F5:F154)) -> 0 | H168: =SUM(D168:G168) -> 0 | I168: =I167+H168 -> 9572.5
A169: Wk 11 (30 Jun) | B169: 46203 | C169: =COUNTIF(E5:E154,"Wk 11 (30 Jun)") -> 0 | D169: =SUMPRODUCT((E5:E154="Wk 11 (30 Jun)")*(G5:G154="Cash")*(F5:F154)) -> 0 | E169: =SUMPRODUCT((E5:E154="Wk 11 (30 Jun)")*((G5:G154="MTN MoMo")+(G5:G154="Vodafone Cash")+(G5:G154="AirtelTigo Money"))*(F5:F154)) -> 0 | F169: =SUMPRODUCT((E5:E154="Wk 11 (30 Jun)")*(G5:G154="Bank Transfer")*(F5:F154)) -> 0 | G169: =SUMPRODUCT((E5:E154="Wk 11 (30 Jun)")*(G5:G154="Cheque")*(F5:F154)) -> 0 | H169: =SUM(D169:G169) -> 0 | I169: =I168+H169 -> 9572.5
A170: Wk 12 (07 Jul) | B170: 46210 | C170: =COUNTIF(E5:E154,"Wk 12 (07 Jul)") -> 0 | D170: =SUMPRODUCT((E5:E154="Wk 12 (07 Jul)")*(G5:G154="Cash")*(F5:F154)) -> 0 | E170: =SUMPRODUCT((E5:E154="Wk 12 (07 Jul)")*((G5:G154="MTN MoMo")+(G5:G154="Vodafone Cash")+(G5:G154="AirtelTigo Money"))*(F5:F154)) -> 0 | F170: =SUMPRODUCT((E5:E154="Wk 12 (07 Jul)")*(G5:G154="Bank Transfer")*(F5:F154)) -> 0 | G170: =SUMPRODUCT((E5:E154="Wk 12 (07 Jul)")*(G5:G154="Cheque")*(F5:F154)) -> 0 | H170: =SUM(D170:G170) -> 0 | I170: =I169+H170 -> 9572.5 | J170: PAST DEADLINE
A171: Wk 13 (14 Jul) | B171: 46217 | C171: =COUNTIF(E5:E154,"Wk 13 (14 Jul)") -> 1 | D171: =SUMPRODUCT((E5:E154="Wk 13 (14 Jul)")*(G5:G154="Cash")*(F5:F154)) -> 0 | E171: =SUMPRODUCT((E5:E154="Wk 13 (14 Jul)")*((G5:G154="MTN MoMo")+(G5:G154="Vodafone Cash")+(G5:G154="AirtelTigo Money"))*(F5:F154)) -> 500 | F171: =SUMPRODUCT((E5:E154="Wk 13 (14 Jul)")*(G5:G154="Bank Transfer")*(F5:F154)) -> 0 | G171: =SUMPRODUCT((E5:E154="Wk 13 (14 Jul)")*(G5:G154="Cheque")*(F5:F154)) -> 0 | H171: =SUM(D171:G171) -> 500 | I171: =I170+H171 -> 10072.5 | J171: PAST DEADLINE
A172: Wk 14 (21 Jul) | B172: 46224 | C172: =COUNTIF(E5:E154,"Wk 14 (21 Jul)") -> 0 | D172: =SUMPRODUCT((E5:E154="Wk 14 (21 Jul)")*(G5:G154="Cash")*(F5:F154)) -> 0 | E172: =SUMPRODUCT((E5:E154="Wk 14 (21 Jul)")*((G5:G154="MTN MoMo")+(G5:G154="Vodafone Cash")+(G5:G154="AirtelTigo Money"))*(F5:F154)) -> 0 | F172: =SUMPRODUCT((E5:E154="Wk 14 (21 Jul)")*(G5:G154="Bank Transfer")*(F5:F154)) -> 0 | G172: =SUMPRODUCT((E5:E154="Wk 14 (21 Jul)")*(G5:G154="Cheque")*(F5:F154)) -> 0 | H172: =SUM(D172:G172) -> 0 | I172: =I171+H172 -> 10072.5 | J172: PAST DEADLINE
A173: TERM 3 TOTAL | C173: =SUM(C159:C172) -> 9 | D173: =SUM(D159:D172) -> 2550 | E173: =SUM(E159:E172) -> 2550 | F173: =SUM(F159:F172) -> 4972.5 | G173: =SUM(G159:G172) -> 0 | H173: =SUM(H159:H172) -> 10072.5
A176: MONTHLY COLLECTION SUMMARY
A177: Month | B177: No. of Payments | C177: Cash | D177: MoMo (All) | E177: Bank Transfer | F177: Cheque | G177: Month Total | H177: Cumulative | I177: Target % | J177: Actual % | K177: Notes
A178: Apr | B178: =SUMPRODUCT((MONTH(A5:A154)=4)*(A5:A154<>"")) -> 3 | C178: =SUMPRODUCT((MONTH(A5:A154)=4)*(G5:G154="Cash")*(F5:F154)) -> 1000 | D178: =SUMPRODUCT((MONTH(A5:A154)=4)*((G5:G154="MTN MoMo")+(G5:G154="Vodafone Cash")+(G5:G154="AirtelTigo Money"))*(F5:F154)) -> 0 | E178: =SUMPRODUCT((MONTH(A5:A154)=4)*(G5:G154="Bank Transfer")*(F5:F154)) -> 1000 | F178: =SUMPRODUCT((MONTH(A5:A154)=4)*(G5:G154="Cheque")*(F5:F154)) -> 0 | G178: =SUM(C178:F178) -> 2000 | H178: =G178 -> 2000 | I178: 0.3
A179: May | B179: =SUMPRODUCT((MONTH(A5:A154)=5)*(A5:A154<>"")) -> 3 | C179: =SUMPRODUCT((MONTH(A5:A154)=5)*(G5:G154="Cash")*(F5:F154)) -> 0 | D179: =SUMPRODUCT((MONTH(A5:A154)=5)*((G5:G154="MTN MoMo")+(G5:G154="Vodafone Cash")+(G5:G154="AirtelTigo Money"))*(F5:F154)) -> 1050 | E179: =SUMPRODUCT((MONTH(A5:A154)=5)*(G5:G154="Bank Transfer")*(F5:F154)) -> 3972.5 | F179: =SUMPRODUCT((MONTH(A5:A154)=5)*(G5:G154="Cheque")*(F5:F154)) -> 0 | G179: =SUM(C179:F179) -> 5022.5 | H179: =H178+G179 -> 7022.5 | I179: 0.65
A180: Jun | B180: =SUMPRODUCT((MONTH(A5:A154)=6)*(A5:A154<>"")) -> 2 | C180: =SUMPRODUCT((MONTH(A5:A154)=6)*(G5:G154="Cash")*(F5:F154)) -> 1550 | D180: =SUMPRODUCT((MONTH(A5:A154)=6)*((G5:G154="MTN MoMo")+(G5:G154="Vodafone Cash")+(G5:G154="AirtelTigo Money"))*(F5:F154)) -> 1000 | E180: =SUMPRODUCT((MONTH(A5:A154)=6)*(G5:G154="Bank Transfer")*(F5:F154)) -> 0 | F180: =SUMPRODUCT((MONTH(A5:A154)=6)*(G5:G154="Cheque")*(F5:F154)) -> 0 | G180: =SUM(C180:F180) -> 2550 | H180: =H179+G180 -> 9572.5 | I180: 1
A181: Jul | B181: =SUMPRODUCT((MONTH(A5:A154)=7)*(A5:A154<>"")) -> 1 | C181: =SUMPRODUCT((MONTH(A5:A154)=7)*(G5:G154="Cash")*(F5:F154)) -> 0 | D181: =SUMPRODUCT((MONTH(A5:A154)=7)*((G5:G154="MTN MoMo")+(G5:G154="Vodafone Cash")+(G5:G154="AirtelTigo Money"))*(F5:F154)) -> 500 | E181: =SUMPRODUCT((MONTH(A5:A154)=7)*(G5:G154="Bank Transfer")*(F5:F154)) -> 0 | F181: =SUMPRODUCT((MONTH(A5:A154)=7)*(G5:G154="Cheque")*(F5:F154)) -> 0 | G181: =SUM(C181:F181) -> 500 | H181: =H180+G181 -> 10072.5 | I181: 1
A182: TOTAL | B182: =SUM(B178:B181) -> 9 | C182: =SUM(C178:C181) -> 2550 | D182: =SUM(D178:D181) -> 2550 | E182: =SUM(E178:E181) -> 4972.5 | F182: =SUM(F178:F181) -> 0 | G182: =SUM(G178:G181) -> 10072.5

Sheet KG 2 - Hawks
A1: KG 2: Hawks — Vision | Focus | Annual: GHS 7,350 | Termly: GHS 2,550
A3: PUPIL DETAILS | D3: TERM 1 (COMPLETED) | H3: TERM 2 (COMPLETED) | M3: TERM 3 (ACTIVE — arrears from T1/T2 included) | Q3: NOTES
A4: No. | B4: Pupil Name | C4: Discount Type | D4: T1 Fee | E4: T1 Arrears BF | F4: T1 Paid | G4: T1 Balance | H4: T2 Fee | I4: T2 Arrears BF | J4: T2 Discount | K4: T2 Paid | L4: T2 Balance | M4: T3 Fee | N4: T3 Discount | O4: T3 Paid | P4: T3 Balance | Q4: Remarks / Waiver Notes
A5: 1 | B5: Morkeh Bradley | C5: Sibling | D5: 2422.5 | G5: =IF(B5="","",IF(D5="",0,D5)+IF(E5="",0,E5)-IF(F5="",0,F5)) -> 2422.5 | H5: 2550 | I5: 922.5 | J5: 127.5 | K5: 2422.5 | L5: =IF(B5="","",IF(H5="",0,H5)+IF(I5="",0,I5)-IF(J5="",0,J5)-IF(K5="",0,K5)) -> 922.5 | M5: 2550 | N5: 127.5 | O5: =SUMIF('KG 2 - Payments'!C5:C154,B5,'KG 2 - Payments'!F5:F154) -> 3022.5 | P5: =IF(B5="","",IF(M5="",0,M5)-IF(N5="",0,N5)+IF(L5<0,0,IF(L5="",0,L5))-IF(O5="",0,O5)) -> 322.5 | Q5: Sibling — never paid T1; T2 balance GHS 922.50; chronic defaulter
A6: 2 | B6: Nartey Zayne Nene Kwadjo | D6: 3080 | F6: 3000 | G6: =IF(B6="","",IF(D6="",0,D6)+IF(E6="",0,E6)-IF(F6="",0,F6)) -> 80 | H6: 3050 | I6: 80 | K6: 3000 | L6: =IF(B6="","",IF(H6="",0,H6)+IF(I6="",0,I6)-IF(J6="",0,J6)-IF(K6="",0,K6)) -> 130 | M6: 3050 | O6: =SUMIF('KG 2 - Payments'!C5:C154,B6,'KG 2 - Payments'!F5:F154) -> 3180 | P6: =IF(B6="","",IF(M6="",0,M6)-IF(N6="",0,N6)+IF(L6<0,0,IF(L6="",0,L6))-IF(O6="",0,O6)) -> 0 | Q6: Higher fee level; T2 balance GHS 130
A7: 3 | B7: Oppong Ama Aseda | D7: 2750 | F7: 2750 | G7: =IF(B7="","",IF(D7="",0,D7)+IF(E7="",0,E7)-IF(F7="",0,F7)) -> 0 | H7: 2550 | K7: 2550 | L7: =IF(B7="","",IF(H7="",0,H7)+IF(I7="",0,I7)-IF(J7="",0,J7)-IF(K7="",0,K7)) -> 0 | M7: 2550 | O7: =SUMIF('KG 2 - Payments'!C5:C154,B7,'KG 2 - Payments'!F5:F154) -> 2550 | P7: =IF(B7="","",IF(M7="",0,M7)-IF(N7="",0,N7)+IF(L7<0,0,IF(L7="",0,L7))-IF(O7="",0,O7)) -> 0
A8: 4 | B8: Adjei-Djeton Jahmiel | C8: Staff Child | D8: 850 | F8: 850 | G8: =IF(B8="","",IF(D8="",0,D8)+IF(E8="",0,E8)-IF(F8="",0,F8)) -> 0 | H8: 2550 | J8: 2550 | L8: =IF(B8="","",IF(H8="",0,H8)+IF(I8="",0,I8)-IF(J8="",0,J8)-IF(K8="",0,K8)) -> 0 | M8: 2550 | N8: 2550 | O8: =SUMIF('KG 1 - Payments'!C5:C154,B8,'KG 1 - Payments'!F5:F154) -> 0 | P8: =IF(B8="","",IF(M8="",0,M8)-IF(N8="",0,N8)+IF(L8<0,0,IF(L8="",0,L8))-IF(O8="",0,O8)) -> 0 | Q8: Staff child — fees fully covered
A9: 5 | B9: Appiah Serwaa Senam | C9: Sibling | D9: 2422.5 | F9: 1800 | G9: =IF(B9="","",IF(D9="",0,D9)+IF(E9="",0,E9)-IF(F9="",0,F9)) -> 622.5 | H9: 2550 | J9: 127.5 | K9: 1550 | L9: 0 | M9: 2550 | N9: 127.5 | O9: =1500+922.5 -> 2422.5 | P9: =IF(B9="","",IF(M9="",0,M9)-IF(N9="",0,N9)+IF(L9<0,0,IF(L9="",0,L9))-IF(O9="",0,O9)) -> 0 | Q9: Sibling — T2 balance GHS 872.50
A10: 6 | B10: Ansah-Darko Carissa Elyon | D10: 2550 | F10: 2550 | G10: =IF(B10="","",IF(D10="",0,D10)+IF(E10="",0,E10)-IF(F10="",0,F10)) -> 0 | H10: 2550 | K10: 2550 | L10: =IF(B10="","",IF(H10="",0,H10)+IF(I10="",0,I10)-IF(J10="",0,J10)-IF(K10="",0,K10)) -> 0 | M10: 2550 | O10: 2550 | P10: =IF(B10="","",IF(M10="",0,M10)-IF(N10="",0,N10)+IF(L10<0,0,IF(L10="",0,L10))-IF(O10="",0,O10)) -> 0
A11: 7 | B11: Asare Nana Ama Sakyibea | D11: 2550 | F11: 1500 | G11: =IF(B11="","",IF(D11="",0,D11)+IF(E11="",0,E11)-IF(F11="",0,F11)) -> 1050 | H11: 2550 | K11: 2200 | L11: =IF(B11="","",IF(H11="",0,H11)+IF(I11="",0,I11)-IF(J11="",0,J11)-IF(K11="",0,K11)) -> 350 | M11: 2550 | O11: 2282.5 | P11: =IF(B11="","",IF(M11="",0,M11)-IF(N11="",0,N11)+IF(L11<0,0,IF(L11="",0,L11))-IF(O11="",0,O11)) -> 617.5 | Q11: T1 partial; T2 balance GHS 350
A12: 8 | B12: Ayeh-Kumi Jomari Paakow | D12: 2550 | E12: 3110 | F12: 2500 | G12: =IF(B12="","",IF(D12="",0,D12)+IF(E12="",0,E12)-IF(F12="",0,F12)) -> 3160 | H12: 2550 | I12: 3660 | K12: 2000 | L12: =IF(B12="","",IF(H12="",0,H12)+IF(I12="",0,I12)-IF(J12="",0,J12)-IF(K12="",0,K12)) -> 4210 | M12: 2550 | O12: 1500 | P12: =IF(B12="","",IF(M12="",0,M12)-IF(N12="",0,N12)+IF(L12<0,0,IF(L12="",0,L12))-IF(O12="",0,O12)) -> 5260 | Q12: Prior year BF GHS 3,110; growing arrears — GHS 4,210 T2 balance
A13: 9 | B13: Bakari Lilian Jamima | D13: 2550 | F13: 2550 | G13: =IF(B13="","",IF(D13="",0,D13)+IF(E13="",0,E13)-IF(F13="",0,F13)) -> 0 | H13: 2550 | K13: 2550 | L13: =IF(B13="","",IF(H13="",0,H13)+IF(I13="",0,I13)-IF(J13="",0,J13)-IF(K13="",0,K13)) -> 0 | M13: 2550 | O13: 2550 | P13: =IF(B13="","",IF(M13="",0,M13)-IF(N13="",0,N13)+IF(L13<0,0,IF(L13="",0,L13))-IF(O13="",0,O13)) -> 0
A14: 10 | B14: Kanati Jed Elikem | C14: Sibling | D14: 2422.5 | F14: 2550 | G14: =IF(B14="","",IF(D14="",0,D14)+IF(E14="",0,E14)-IF(F14="",0,F14)) -> -127.5 | H14: 2550 | J14: 127.5 | K14: 2422.5 | L14: =IF(B14="","",IF(H14="",0,H14)+IF(I14="",0,I14)-IF(J14="",0,J14)-IF(K14="",0,K14)) -> 0 | M14: 2550 | N14: 127.5 | O14: 2422.5 | P14: =IF(B14="","",IF(M14="",0,M14)-IF(N14="",0,N14)+IF(L14<0,0,IF(L14="",0,L14))-IF(O14="",0,O14)) -> 0
A15: 11 | G15: =IF(B15="","",0) | L15: =IF(B15="","",0) | P15: =IF(B15="","",0)
A16: 12 | G16: =IF(B16="","",0) | L16: =IF(B16="","",0) | P16: =IF(B16="","",0)
A17: 13 | G17: =IF(B17="","",0) | L17: =IF(B17="","",0) | P17: =IF(B17="","",0)
B18: TOTALS | D18: =SUM(D5:D17) -> 24147.5 | E18: =SUM(E5:E17) -> 3110 | F18: =SUM(F5:F17) -> 20050 | G18: =SUM(G5:G17) -> 7207.5 | H18: =SUM(H5:H17) -> 26000 | I18: =SUM(I5:I17) -> 4662.5 | J18: =SUM(J5:J17) -> 2932.5 | K18: =SUM(K5:K17) -> 21245 | ... P18: =SUM(P5:P17) -> 6200
B19: Collection Rate: | F19: T1: | G19: =IF(D18+E18=0,1,F18/(D18+E18)) -> 0.73557736 | K19: T2: | L19: =IF(H18+I18-J18=0,1,K18/(H18+I18-J18)) -> 0.76613776 | O19: =SUMIF('KG 2 - Payments'!C5:C154,B19,'KG 2 - Payments'!F5:F154) -> 0

Sheet KG 2 - Payments
A1: KG 2: Hawks — PAYMENT RECEIPTS LOG (Term 3, 2025/26: 21 Apr – 24 Jul 2026) | P1: Morkeh Bradley
A2: Payment deadline: 30 June 2026 | Enter one row per payment | T3 Paid on class register auto-updates via SUMIFS | P2: Nartey Zayne Nene Kwadjo
A3: TRANSACTION DETAILS | G3: PAYMENT | J3: VERIFICATION | P3: Oppong Ama Aseda
A4: Date | B4: Receipt No. | C4: Pupil Name | D4: Term | E4: Week | F4: Amount (GHS) | G4: Payment Method | H4: Received By | I4: Running Total | J4: Verified | K4: Notes
A5: 46111 | B5: 1024 | C5: Morkeh Bradley | D5: Term 2 Arrears | F5: 500 | G5: MTN MoMo | H5: Dorcas Matilda Akosua Kusi | I5: =IF(F5="","",F5) -> 500
A6: 46114 | B6: 1030 | C6: Serwaa Senam Appiah | D6: Term 2 Arrears | F6: 1072.5 | G6: Cash | H6: Dorcas Matilda Akosua Kusi | I6: =IF(F6="","",IF(I5="",F6,I5+F6)) -> 1572.5
A7: 46122 | B7: 1035 | C7: Jed Elikem Kanati | D7: Term 3 | E7: Vacation | F7: 1000 | G7: Bank Transfer | H7: Dorcas Matilda Akosua Kusi | I7: =IF(F7="","",IF(I6="",F7,I6+F7)) -> 2572.5
A8: 46127 | B8: 1038 | C8: Jed Elikem Kanati | D8: Term 3 | E8: Vacation | F8: 1622.5 | G8: Bank Transfer | H8: Dorcas Matilda Akosua Kusi | I8: =IF(F8="","",IF(I7="",F8,I7+F8)) -> 4195
A9: 46132 | B9: 1044 | C9: Lilian Jamima Bakari | D9: Term 3 | E9: Wk 1 (21 Apr) | F9: 2550 | G9: Bank Transfer | H9: Dorcas Matilda Akosua Kusi | I9: =IF(F9="","",IF(I8="",F9,I8+F9)) -> 6745
A10: 46135 | B10: 1047 | C10: Morkeh Bradley | D10: Term 2 Arrears | E10: Wk 1 (21 Apr) | F10: 622.5 | G10: MTN MoMo / Cash | H10: Other | I10: =IF(F10="","",IF(I9="",F10,I9+F10)) -> 7367.5
A11: 46139 | B11: 1048 | C11: Oppong Ama Aseda | D11: Term 3 | E11: Wk 2 (28 Apr) | F11: 2550 | G11: Cash | H11: Other | I11: =IF(F11="","",IF(I10="",F11,I10+F11)) -> 9917.5
A12: 46140 | B12: 1058 | C12: Carissa Ansah-Darko | D12: Term 3 | E12: Wk 2 (28 Apr) | F12: 2550 | G12: Bank Transfer | H12: Dorcas Matilda Akosua Kusi | I12: =IF(F12="","",IF(I11="",F12,I11+F12)) -> 12467.5
A13: 46118 | B13: 1064 | C13: Nartey Zayne Nene Kwadjo | D13: Term 3 | E13: Wk 3 (05 May) | F13: 1500 | G13: MTN MoMo | H13: Other | I13: =IF(F13="","",IF(I12="",F13,I12+F13)) -> 13967.5
A14: 46171 | B14: 1092 | C14: Asare Nana Ama Sakyibea | D14: Term 3 | E14: Wk 6 (26 May) | F14: 1000 | G14: MTN MoMo | H14: Other | I14: =IF(F14="","",IF(I13="",F14,I13+F14)) -> 14967.5
A15: 46174 | B15: 1097 | C15: Morkeh Bradley | D15: Term 3 | E15: Wk 6 (26 May) | F15: 1000 | G15: MTN MoMo | H15: Dorcas Matilda Akosua Kusi | I15: =IF(F15="","",IF(I14="",F15,I14+F15)) -> 15967.5
A16: 46195 | B16: 1119 | C16: Asare Nana Ama Sakyibea | D16: Term 3 | E16: Wk 10 (23 Jun) | F16: 1500 | G16: Cash | H16: Other | I16: =IF(F16="","",IF(I15="",F16,I15+F16)) -> 17467.5
A17: 46197 | B17: 1121 | C17: Nartey Zayne Nene Kwadjo | D17: Term 3 | E17: Wk 10 (23 Jun) | F17: 1000 | G17: MTN MoMo | H17: Other | I17: =IF(F17="","",IF(I16="",F17,I16+F17)) -> 18467.5
A18: 46205 | B18: 1122 | C18: Nartey Zayne Nene Kwadjo | D18: Term 3 | E18: Wk 11 (30 Jun) | F18: 680 | G18: MTN MoMo | H18: Other | I18: =IF(F18="","",IF(I17="",F18,I17+F18)) -> 19147.5
... A20: 46302 | B20: 1134 | C20: Jomari Paakolw Ayeh-Kumi | D20: Term 2 Arrears | E20: Wk 12 (07 Jul) | F20: 1500 | G20: MTN MoMo | H20: Dorcas Matilda Akosua Kusi | I20: =IF(F20="","",IF(I19="",F20,I19+F20)) -> 22147.5
A21: 15/07/2026 | B21: 1142 | C21: Serwaa Senam Appiah | D21: Term 3 | E21: Wk 13 (14 Jul) | F21: 400 | G21: Cash | H21: Dorcas Matilda Akosua Kusi | I21: =IF(F21="","",IF(I20="",F21,I20+F21)) -> 22547.5
A22: 46223 | B22: 1146 | C22: Morkeh Bradley | D22: Term 3 | E22: Wk 13 (14 Jul) | F22: 900 | G22: Cash | H22: Other | I22: =IF(F22="","",IF(I21="",F22,I21+F22)) -> 23447.5
A23: 46225 | B23: 1147 | C23: Appiah Senam Serwaa | D23: Term 3 | E23: Wk 14 (21 Jul) | F23: 722.5 | G23: MTN MoMo | H23: Other | I23: =IF(F23="","",IF(I22="",F23,I22+F23)) -> 24170
A24: 46226 | B24: 1150 | C24: Jomari Paakow Ayeh-Kumi | D24: Term 2 Arrears | E24: Wk 14 (21 Jul) | F24: 1000 | G24: Cash | H24: Other | I24: =IF(F24="","",IF(I23="",F24,I23+F24)) -> 25170
I25: =IF(F25="","",IF(I24="",F25,I24+F25))
I26: =IF(F26="","",IF(I25="",F26,I25+F26))
I27: =IF(F27="","",IF(I26="",F27,I26+F27))
I28: =IF(F28="","",IF(I27="",F28,I27+F28))
I29: =IF(F29="","",IF(I28="",F29,I28+F29))
I30: =IF(F30="","",IF(I29="",F30,I29+F30))
I31: =IF(F31="","",IF(I30="",F31,I30+F31))
I32: =IF(F32="","",IF(I31="",F32,I31+F32))
I33: =IF(F33="","",IF(I32="",F33,I32+F33))
I34: =IF(F34="","",IF(I33="",F34,I33+F34))
I35: =IF(F35="","",IF(I34="",F35,I34+F35))
I36: =IF(F36="","",IF(I35="",F36,I35+F36))
... I154: =IF(F154="","",IF(I153="",F154,I153+F154))
A157: WEEKLY COLLECTION SUMMARY (auto-calculated from payment log)
A158: Week | B158: Week Starting | C158: Entries | D158: Cash | E158: MoMo (All) | F158: Bank Transfer | G158: Cheque | H158: Week Total | I158: Cumulative | J158: vs Deadline | K158: Notes
A159: Wk 1 (21 Apr) | B159: 46133 | C159: =COUNTIF(E5:E154,"Wk 1 (21 Apr)") -> 2 | D159: =SUMPRODUCT((E5:E154="Wk 1 (21 Apr)")*(G5:G154="Cash")*(F5:F154)) -> 0 | E159: =SUMPRODUCT((E5:E154="Wk 1 (21 Apr)")*((G5:G154="MTN MoMo")+(G5:G154="Vodafone Cash")+(G5:G154="AirtelTigo Money"))*(F5:F154)) -> 0 | F159: =SUMPRODUCT((E5:E154="Wk 1 (21 Apr)")*(G5:G154="Bank Transfer")*(F5:F154)) -> 2550 | G159: =SUMPRODUCT((E5:E154="Wk 1 (21 Apr)")*(G5:G154="Cheque")*(F5:F154)) -> 0 | H159: =SUM(D159:G159) -> 2550 | I159: =H159 -> 2550
A160: Wk 2 (28 Apr) | B160: 46140 | C160: =COUNTIF(E5:E154,"Wk 2 (28 Apr)") -> 2 | D160: =SUMPRODUCT((E5:E154="Wk 2 (28 Apr)")*(G5:G154="Cash")*(F5:F154)) -> 2550 | E160: =SUMPRODUCT((E5:E154="Wk 2 (28 Apr)")*((G5:G154="MTN MoMo")+(G5:G154="Vodafone Cash")+(G5:G154="AirtelTigo Money"))*(F5:F154)) -> 0 | F160: =SUMPRODUCT((E5:E154="Wk 2 (28 Apr)")*(G5:G154="Bank Transfer")*(F5:F154)) -> 2550 | G160: =SUMPRODUCT((E5:E154="Wk 2 (28 Apr)")*(G5:G154="Cheque")*(F5:F154)) -> 0 | H160: =SUM(D160:G160) -> 5100 | I160: =I159+H160 -> 7650
A161: Wk 3 (05 May) | B161: 46147 | C161: =COUNTIF(E5:E154,"Wk 3 (05 May)") -> 1 | D161: =SUMPRODUCT((E5:E154="Wk 3 (05 May)")*(G5:G154="Cash")*(F5:F154)) -> 0 | E161: =SUMPRODUCT((E5:E154="Wk 3 (05 May)")*((G5:G154="MTN MoMo")+(G5:G154="Vodafone Cash")+(G5:G154="AirtelTigo Money"))*(F5:F154)) -> 1500 | F161: =SUMPRODUCT((E5:E154="Wk 3 (05 May)")*(G5:G154="Bank Transfer")*(F5:F154)) -> 0 | G161: =SUMPRODUCT((E5:E154="Wk 3 (05 May)")*(G5:G154="Cheque")*(F5:F154)) -> 0 | H161: =SUM(D161:G161) -> 1500 | I161: =I160+H161 -> 9150
A162: Wk 4 (12 May) | B162: 46154 | C162: =COUNTIF(E5:E154,"Wk 4 (12 May)") -> 0 | D162: =SUMPRODUCT((E5:E154="Wk 4 (12 May)")*(G5:G154="Cash")*(F5:F154)) -> 0 | E162: =SUMPRODUCT((E5:E154="Wk 4 (12 May)")*((G5:G154="MTN MoMo")+(G5:G154="Vodafone Cash")+(G5:G154="AirtelTigo Money"))*(F5:F154)) -> 0 | F162: =SUMPRODUCT((E5:E154="Wk 4 (12 May)")*(G5:G154="Bank Transfer")*(F5:F154)) -> 0 | G162: =SUMPRODUCT((E5:E154="Wk 4 (12 May)")*(G5:G154="Cheque")*(F5:F154)) -> 0 | H162: =SUM(D162:G162) -> 0 | I162: =I161+H162 -> 9150
A163: Wk 5 (19 May) | B163: 46161 | C163: =COUNTIF(E5:E154,"Wk 5 (19 May)") -> 0 | D163: =SUMPRODUCT((E5:E154="Wk 5 (19 May)")*(G5:G154="Cash")*(F5:F154)) -> 0 | E163: =SUMPRODUCT((E5:E154="Wk 5 (19 May)")*((G5:G154="MTN MoMo")+(G5:G154="Vodafone Cash")+(G5:G154="AirtelTigo Money"))*(F5:F154)) -> 0 | F163: =SUMPRODUCT((E5:E154="Wk 5 (19 May)")*(G5:G154="Bank Transfer")*(F5:F154)) -> 0 | G163: =SUMPRODUCT((E5:E154="Wk 5 (19 May)")*(G5:G154="Cheque")*(F5:F154)) -> 0 | H163: =SUM(D163:G163) -> 0 | I163: =I162+H163 -> 9150
A164: Wk 6 (26 May) | B164: 46168 | C164: =COUNTIF(E5:E154,"Wk 6 (26 May)") -> 2 | D164: =SUMPRODUCT((E5:E154="Wk 6 (26 May)")*(G5:G154="Cash")*(F5:F154)) -> 0 | E164: =SUMPRODUCT((E5:E154="Wk 6 (26 May)")*((G5:G154="MTN MoMo")+(G5:G154="Vodafone Cash")+(G5:G154="AirtelTigo Money"))*(F5:F154)) -> 2000 | F164: =SUMPRODUCT((E5:E154="Wk 6 (26 May)")*(G5:G154="Bank Transfer")*(F5:F154)) -> 0 | G164: =SUMPRODUCT((E5:E154="Wk 6 (26 May)")*(G5:G154="Cheque")*(F5:F154)) -> 0 | H164: =SUM(D164:G164) -> 2000 | I164: =I163+H164 -> 11150
A165: Wk 7 (02 Jun) | B165: 46175 | C165: =COUNTIF(E5:E154,"Wk 7 (02 Jun)") -> 0 | D165: =SUMPRODUCT((E5:E154="Wk 7 (02 Jun)")*(G5:G154="Cash")*(F5:F154)) -> 0 | E165: =SUMPRODUCT((E5:E154="Wk 7 (02 Jun)")*((G5:G154="MTN MoMo")+(G5:G154="Vodafone Cash")+(G5:G154="AirtelTigo Money"))*(F5:F154)) -> 0 | F165: =SUMPRODUCT((E5:E154="Wk 7 (02 Jun)")*(G5:G154="Bank Transfer")*(F5:F154)) -> 0 | G165: =SUMPRODUCT((E5:E154="Wk 7 (02 Jun)")*(G5:G154="Cheque")*(F5:F154)) -> 0 | H165: =SUM(D165:G165) -> 0 | I165: =I164+H165 -> 11150
A166: Wk 8 (09 Jun) | B166: 46182 | C166: =COUNTIF(E5:E154,"Wk 8 (09 Jun)") -> 0 | D166: =SUMPRODUCT((E5:E154="Wk 8 (09 Jun)")*(G5:G154="Cash")*(F5:F154)) -> 0 | E166: =SUMPRODUCT((E5:E154="Wk 8 (09 Jun)")*((G5:G154="MTN MoMo")+(G5:G154="Vodafone Cash")+(G5:G154="AirtelTigo Money"))*(F5:F154)) -> 0 | F166: =SUMPRODUCT((E5:E154="Wk 8 (09 Jun)")*(G5:G154="Bank Transfer")*(F5:F154)) -> 0 | G166: =SUMPRODUCT((E5:E154="Wk 8 (09 Jun)")*(G5:G154="Cheque")*(F5:F154)) -> 0 | H166: =SUM(D166:G166) -> 0 | I166: =I165+H166 -> 11150
A167: Wk 9 (16 Jun) | B167: 46189 | C167: =COUNTIF(E5:E154,"Wk 9 (16 Jun)") -> 0 | D167: =SUMPRODUCT((E5:E154="Wk 9 (16 Jun)")*(G5:G154="Cash")*(F5:F154)) -> 0 | E167: =SUMPRODUCT((E5:E154="Wk 9 (16 Jun)")*((G5:G154="MTN MoMo")+(G5:G154="Vodafone Cash")+(G5:G154="AirtelTigo Money"))*(F5:F154)) -> 0 | F167: =SUMPRODUCT((E5:E154="Wk 9 (16 Jun)")*(G5:G154="Bank Transfer")*(F5:F154)) -> 0 | G167: =SUMPRODUCT((E5:E154="Wk 9 (16 Jun)")*(G5:G154="Cheque")*(F5:F154)) -> 0 | H167: =SUM(D167:G167) -> 0 | I167: =I166+H167 -> 11150
A168: Wk 10 (23 Jun) | B168: 46196 | C168: =COUNTIF(E5:E154,"Wk 10 (23 Jun)") -> 2 | D168: =SUMPRODUCT((E5:E154="Wk 10 (23 Jun)")*(G5:G154="Cash")*(F5:F154)) -> 1500 | E168: =SUMPRODUCT((E5:E154="Wk 10 (23 Jun)")*((G5:G154="MTN MoMo")+(G5:G154="Vodafone Cash")+(G5:G154="AirtelTigo Money"))*(F5:F154)) -> 1000 | F168: =SUMPRODUCT((E5:E154="Wk 10 (23 Jun)")*(G5:G154="Bank Transfer")*(F5:F154)) -> 0 | G168: =SUMPRODUCT((E5:E154="Wk 10 (23 Jun)")*(G5:G154="Cheque")*(F5:F154)) -> 0 | H168: =SUM(D168:G168) -> 2500 | I168: =I167+H168 -> 13650
A169: Wk 11 (30 Jun) | B169: 46203 | C169: =COUNTIF(E5:E154,"Wk 11 (30 Jun)") -> 1 | D169: =SUMPRODUCT((E5:E154="Wk 11 (30 Jun)")*(G5:G154="Cash")*(F5:F154)) -> 0 | E169: =SUMPRODUCT((E5:E154="Wk 11 (30 Jun)")*((G5:G154="MTN MoMo")+(G5:G154="Vodafone Cash")+(G5:G154="AirtelTigo Money"))*(F5:F154)) -> 680 | F169: =SUMPRODUCT((E5:E154="Wk 11 (30 Jun)")*(G5:G154="Bank Transfer")*(F5:F154)) -> 0 | G169: =SUMPRODUCT((E5:E154="Wk 11 (30 Jun)")*(G5:G154="Cheque")*(F5:F154)) -> 0 | H169: =SUM(D169:G169) -> 680 | I169: =I168+H169 -> 14330
A170: Wk 12 (07 Jul) | B170: 46210 | C170: =COUNTIF(E5:E154,"Wk 12 (07 Jul)") -> 2 | D170: =SUMPRODUCT((E5:E154="Wk 12 (07 Jul)")*(G5:G154="Cash")*(F5:F154)) -> 1500 | E170: =SUMPRODUCT((E5:E154="Wk 12 (07 Jul)")*((G5:G154="MTN MoMo")+(G5:G154="Vodafone Cash")+(G5:G154="AirtelTigo Money"))*(F5:F154)) -> 1500 | F170: =SUMPRODUCT((E5:E154="Wk 12 (07 Jul)")*(G5:G154="Bank Transfer")*(F5:F154)) -> 0 | G170: =SUMPRODUCT((E5:E154="Wk 12 (07 Jul)")*(G5:G154="Cheque")*(F5:F154)) -> 0 | H170: =SUM(D170:G170) -> 3000 | I170: =I169+H170 -> 17330 | J170: PAST DEADLINE
A171: Wk 13 (14 Jul) | B171: 46217 | C171: =COUNTIF(E5:E154,"Wk 13 (14 Jul)") -> 2 | D171: =SUMPRODUCT((E5:E154="Wk 13 (14 Jul)")*(G5:G154="Cash")*(F5:F154)) -> 1300 | E171: =SUMPRODUCT((E5:E154="Wk 13 (14 Jul)")*((G5:G154="MTN MoMo")+(G5:G154="Vodafone Cash")+(G5:G154="AirtelTigo Money"))*(F5:F154)) -> 0 | F171: =SUMPRODUCT((E5:E154="Wk 13 (14 Jul)")*(G5:G154="Bank Transfer")*(F5:F154)) -> 0 | G171: =SUMPRODUCT((E5:E154="Wk 13 (14 Jul)")*(G5:G154="Cheque")*(F5:F154)) -> 0 | H171: =SUM(D171:G171) -> 1300 | I171: =I170+H171 -> 18630 | J171: PAST DEADLINE
A172: Wk 14 (21 Jul) | B172: 46224 | C172: =COUNTIF(E5:E154,"Wk 14 (21 Jul)") -> 2 | D172: =SUMPRODUCT((E5:E154="Wk 14 (21 Jul)")*(G5:G154="Cash")*(F5:F154)) -> 1000 | E172: =SUMPRODUCT((E5:E154="Wk 14 (21 Jul)")*((G5:G154="MTN MoMo")+(G5:G154="Vodafone Cash")+(G5:G154="AirtelTigo Money"))*(F5:F154)) -> 722.5 | F172: =SUMPRODUCT((E5:E154="Wk 14 (21 Jul)")*(G5:G154="Bank Transfer")*(F5:F154)) -> 0 | G172: =SUMPRODUCT((E5:E154="Wk 14 (21 Jul)")*(G5:G154="Cheque")*(F5:F154)) -> 0 | H172: =SUM(D172:G172) -> 1722.5 | I172: =I171+H172 -> 20352.5 | J172: PAST DEADLINE
A173: TERM 3 TOTAL | C173: =SUM(C159:C172) -> 16 | D173: =SUM(D159:D172) -> 7850 | E173: =SUM(E159:E172) -> 7402.5 | F173: =SUM(F159:F172) -> 5100 | G173: =SUM(G159:G172) -> 0 | H173: =SUM(H159:H172) -> 20352.5
A176: MONTHLY COLLECTION SUMMARY
A177: Month | B177: No. of Payments | C177: Cash | D177: MoMo (All) | E177: Bank Transfer | F177: Cheque | G177: Month Total | H177: Cumulative | I177: Target % | J177: Actual % | K177: Notes
A178: Apr | B178: =SUMPRODUCT((MONTH(A5:A154)=4)*(A5:A154<>"")) -> 8 | C178: =SUMPRODUCT((MONTH(A5:A154)=4)*(G5:G154="Cash")*(F5:F154)) -> 3622.5 | D178: =SUMPRODUCT((MONTH(A5:A154)=4)*((G5:G154="MTN MoMo")+(G5:G154="Vodafone Cash")+(G5:G154="AirtelTigo Money"))*(F5:F154)) -> 1500 | E178: =SUMPRODUCT((MONTH(A5:A154)=4)*(G5:G154="Bank Transfer")*(F5:F154)) -> 7722.5 | F178: =SUMPRODUCT((MONTH(A5:A154)=4)*(G5:G154="Cheque")*(F5:F154)) -> 0 | G178: =SUM(C178:F178) -> 12845 | H178: =G178 -> 12845 | I178: 0.3
A179: May | B179: =SUMPRODUCT((MONTH(A5:A154)=5)*(A5:A154<>"")) -> 1 | C179: =SUMPRODUCT((MONTH(A5:A154)=5)*(G5:G154="Cash")*(F5:F154)) -> 0 | D179: =SUMPRODUCT((MONTH(A5:A154)=5)*((G5:G154="MTN MoMo")+(G5:G154="Vodafone Cash")+(G5:G154="AirtelTigo Money"))*(F5:F154)) -> 1000 | E179: =SUMPRODUCT((MONTH(A5:A154)=5)*(G5:G154="Bank Transfer")*(F5:F154)) -> 0 | F179: =SUMPRODUCT((MONTH(A5:A154)=5)*(G5:G154="Cheque")*(F5:F154)) -> 0 | G179: =SUM(C179:F179) -> 1000 | H179: =H178+G179 -> 13845 | I179: 0.65
A180: Jun | B180: =SUMPRODUCT((MONTH(A5:A154)=6)*(A5:A154<>"")) -> 3 | C180: =SUMPRODUCT((MONTH(A5:A154)=6)*(G5:G154="Cash")*(F5:F154)) -> 1500 | D180: =SUMPRODUCT((MONTH(A5:A154)=6)*((G5:G154="MTN MoMo")+(G5:G154="Vodafone Cash")+(G5:G154="AirtelTigo Money"))*(F5:F154)) -> 2000 | E180: =SUMPRODUCT((MONTH(A5:A154)=6)*(G5:G154="Bank Transfer")*(F5:F154)) -> 0 | F180: =SUMPRODUCT((MONTH(A5:A154)=6)*(G5:G154="Cheque")*(F5:F154)) -> 0 | G180: =SUM(C180:F180) -> 3500 | H180: =H179+G180 -> 17345 | I180: 1
A181: Jul | B181: =SUMPRODUCT((MONTH(A5:A154)=7)*(A5:A154<>"")) -> 6 | C181: =SUMPRODUCT((MONTH(A5:A154)=7)*(G5:G154="Cash")*(F5:F154)) -> 3800 | D181: =SUMPRODUCT((MONTH(A5:A154)=7)*((G5:G154="MTN MoMo")+(G5:G154="Vodafone Cash")+(G5:G154="AirtelTigo Money"))*(F5:F154)) -> 1402.5 | E181: =SUMPRODUCT((MONTH(A5:A154)=7)*(G5:G154="Bank Transfer")*(F5:F154)) -> 0 | F181: =SUMPRODUCT((MONTH(A5:A154)=7)*(G5:G154="Cheque")*(F5:F154)) -> 0 | G181: =SUM(C181:F181) -> 5202.5 | H181: =H180+G181 -> 22547.5 | I181: 1
A182: TOTAL | B182: =SUM(B178:B181) -> 18 | C182: =SUM(C178:C181) -> 8922.5 | D182: =SUM(D178:D181) -> 5902.5 | E182: =SUM(E178:E181) -> 7722.5 | F182: =SUM(F178:F181) -> 0 | G182: =SUM(G178:G181) -> 22547.5

Sheet Grade 1 - Skylarks
A1: Grade 1: Skylarks — Joy | Freedom | Annual: GHS 8,500 | Termly: GHS 3,000
A3: PUPIL DETAILS | D3: TERM 1 (COMPLETED) | H3: TERM 2 (COMPLETED) | M3: TERM 3 (ACTIVE — arrears from T1/T2 included) | Q3: NOTES
A4: No. | B4: Pupil Name | C4: Discount Type | D4: T1 Fee | E4: T1 Arrears BF | F4: T1 Paid | G4: T1 Balance | H4: T2 Fee | I4: T2 Arrears BF | J4: T2 Discount | K4: T2 Paid | L4: T2 Balance | M4: T3 Fee | N4: T3 Discount | O4: T3 Paid | P4: T3 Balance | Q4: Remarks / Waiver Notes
A5: 1 | B5: Abomabiik Janelle Adepa | D5: 3200 | F5: 3000 | G5: =IF(B5="","",IF(D5="",0,D5)+IF(E5="",0,E5)-IF(F5="",0,F5)) -> 200 | H5: 3000 | K5: 3000 | L5: =IF(B5="","",IF(H5="",0,H5)+IF(I5="",0,I5)-IF(J5="",0,J5)-IF(K5="",0,K5)) -> 0 | M5: 3000 | O5: =SUMIF('Grade 1 - Payments'!C5:C154,B5,'Grade 1 - Payments'!F5:F154) -> 3200 | P5: =IF(B5="","",IF(M5="",0,M5)-IF(N5="",0,N5)+IF(L5<0,0,IF(L5="",0,L5))-IF(O5="",0,O5)) -> -200
A6: 2 | B6: Anaman Sam Darkoh | D6: 3200 | F6: 3200 | G6: =IF(B6="","",IF(D6="",0,D6)+IF(E6="",0,E6)-IF(F6="",0,F6)) -> 0 | H6: 3000 | K6: 3000 | L6: =IF(B6="","",IF(H6="",0,H6)+IF(I6="",0,I6)-IF(J6="",0,J6)-IF(K6="",0,K6)) -> 0 | M6: 3000 | O6: =SUMIF('Grade 1 - Payments'!C5:C154,B6,'Grade 1 - Payments'!F5:F154) -> 3200 | P6: =IF(B6="","",IF(M6="",0,M6)-IF(N6="",0,N6)+IF(L6<0,0,IF(L6="",0,L6))-IF(O6="",0,O6)) -> -200
A7: 3 | B7: Asare Okaine Bismark | D7: 3200 | F7: 2000 | G7: =IF(B7="","",IF(D7="",0,D7)+IF(E7="",0,E7)-IF(F7="",0,F7)) -> 1200 | I7: 1200 | L7: =IF(B7="","",IF(H7="",0,H7)+IF(I7="",0,I7)-IF(J7="",0,J7)-IF(K7="",0,K7)) -> 1200 | M7: 0 | O7: =SUMIF('Grade 1 - Payments'!C5:C154,B7,'Grade 1 - Payments'!F5:F154) -> 0 | P7: =IF(B7="","",IF(M7="",0,M7)-IF(N7="",0,N7)+IF(L7<0,0,IF(L7="",0,L7))-IF(O7="",0,O7)) -> 1200 | Q7: T1 partial; no T2 fee charged — GHS 1,200 arrears persisting
A8: 4 | B8: Campbell Jaheem Coffie | C8: Waiver | D8: 3200 | F8: 3200 | G8: =IF(B8="","",IF(D8="",0,D8)+IF(E8="",0,E8)-IF(F8="",0,F8)) -> 0 | H8: 3000 | J8: 2000 | K8: 1000 | L8: =IF(B8="","",IF(H8="",0,H8)+IF(I8="",0,I8)-IF(J8="",0,J8)-IF(K8="",0,K8)) -> 0 | M8: 3000 | O8: =SUMIF('Grade 1 - Payments'!C5:C154,B8,'Grade 1 - Payments'!F5:F154) -> 3200 | P8: =IF(B8="","",IF(M8="",0,M8)-IF(N8="",0,N8)+IF(L8<0,0,IF(L8="",0,L8))-IF(O8="",0,O8)) -> -200 | Q8: Waiver — parent's condition; GHS 2,000 waived T2
A9: 5 | B9: Djaba Emily | C9: Sibling | D9: 2900 | F9: 2466.67 | G9: =IF(B9="","",IF(D9="",0,D9)+IF(E9="",0,E9)-IF(F9="",0,F9)) -> 433.33 | H9: 3000 | J9: 300 | K9: 2700 | L9: =IF(B9="","",IF(H9="",0,H9)+IF(I9="",0,I9)-IF(J9="",0,J9)-IF(K9="",0,K9)) -> 0 | M9: 3000 | N9: 300 | O9: =SUMIF('Grade 1 - Payments'!C5:C154,B9,'Grade 1 - Payments'!F5:F154) -> 0 | P9: =IF(B9="","",IF(M9="",0,M9)-IF(N9="",0,N9)+IF(L9<0,0,IF(L9="",0,L9))-IF(O9="",0,O9)) -> 2700 | Q9: Sibling discount
A10: 6 | B10: Gyesi-Dodd Nkunim Kwesi | D10: 3200 | F10: 3200 | G10: =IF(B10="","",IF(D10="",0,D10)+IF(E10="",0,E10)-IF(F10="",0,F10)) -> 0 | H10: 3000 | K10: 3000 | L10: =IF(B10="","",IF(H10="",0,H10)+IF(I10="",0,I10)-IF(J10="",0,J10)-IF(K10="",0,K10)) -> 0 | M10: 3000 | O10: =SUMIF('Grade 1 - Payments'!C5:C154,B10,'Grade 1 - Payments'!F5:F154) -> 3200 | P10: =IF(B10="","",IF(M10="",0,M10)-IF(N10="",0,N10)+IF(L10<0,0,IF(L10="",0,L10))-IF(O10="",0,O10)) -> -200
A11: 7 | B11: Kassim Umar | C11: Sibling | G11: =IF(B11="","",IF(D11="",0,D11)+IF(E11="",0,E11)-IF(F11="",0,F11)) -> 0 | H11: 3000 | J11: 150 | K11: 2622.5 | L11: =IF(B11="","",IF(H11="",0,H11)+IF(I11="",0,I11)-IF(J11="",0,J11)-IF(K11="",0,K11)) -> 227.5 | M11: 3000 | N11: 150 | O11: =SUMIF('Grade 1 - Payments'!C5:C154,B11,'Grade 1 - Payments'!F5:F154) -> 3627.5 | P11: =IF(B11="","",IF(M11="",0,M11)-IF(N11="",0,N11)+IF(L11<0,0,IF(L11="",0,L11))-IF(O11="",0,O11)) -> -550 | Q11: Sibling — joined mid-year; T2 balance GHS 377.50
A12: 8 | B12: Mensah-Aborampah Asa Essilfie Owuraku | C12: Sibling | D12: 3050 | F12: 1600 | G12: =IF(B12="","",IF(D12="",0,D12)+IF(E12="",0,E12)-IF(F12="",0,F12)) -> 1450 | H12: 3000 | I12: 450 | J12: 150 | K12: 2450 | L12: =IF(B12="","",IF(H12="",0,H12)+IF(I12="",0,I12)-IF(J12="",0,J12)-IF(K12="",0,K12)) -> 850 | M12: 3000 | N12: 150 | O12: 2800 | P12: 1152.5 | Q12: Sibling — consistent partial payer; T2 balance GHS 850
A13: 9 | B13: Tsikata Sejanam Kokui | C13: Waiver | D13: 3050 | F13: 3050 | G13: =IF(B13="","",IF(D13="",0,D13)+IF(E13="",0,E13)-IF(F13="",0,F13)) -> 0 | H13: 3000 | J13: 2000 | K13: 1000 | L13: =IF(B13="","",IF(H13="",0,H13)+IF(I13="",0,I13)-IF(J13="",0,J13)-IF(K13="",0,K13)) -> 0 | M13: 3000 | N13: 150 | O13: =SUMIF('Grade 1 - Payments'!C5:C154,B13,'Grade 1 - Payments'!F5:F154) -> 3050 | P13: =IF(B13="","",IF(M13="",0,M13)-IF(N13="",0,N13)+IF(L13<0,0,IF(L13="",0,L13))-IF(O13="",0,O13)) -> -200 | Q13: Waiver — parent's condition; GHS 2,000 waived T2
A14: 10 | B14: Bekoe Calvin Darko | G14: =IF(B14="","",IF(D14="",0,D14)+IF(E14="",0,E14)-IF(F14="",0,F14)) -> 0 | H14: 5000 | K14: 5000 | L14: =IF(B14="","",IF(H14="",0,H14)+IF(I14="",0,I14)-IF(J14="",0,J14)-IF(K14="",0,K14)) -> 0 | M14: 3000 | O14: 3200 | P14: =IF(B14="","",IF(M14="",0,M14)-IF(N14="",0,N14)+IF(L14<0,0,IF(L14="",0,L14))-IF(O14="",0,O14)) -> -200 | Q14: Joined mid-year; higher fee includes catch-up
A15: 11 | B15: Benneh Gregoria | G15: =IF(B15="","",0) -> 0 | L15: =IF(B15="","",0) -> 0 | P15: =IF(B15="","",0) -> 0
A16: 12 | G16: =IF(B16="","",0) | L16: =IF(B16="","",0) | P16: =IF(B16="","",0)
A17: 13 | G17: =IF(B17="","",0) | L17: =IF(B17="","",0) | P17: =IF(B17="","",0)
A18: 14 | G18: =IF(B18="","",0) | L18: =IF(B18="","",0) | P18: =IF(B18="","",0)
A19: 15 | G19: =IF(B19="","",0) | L19: =IF(B19="","",0) | P19: =IF(B19="","",0)
A20: 16 | G20: =IF(B20="","",0) | L20: =IF(B20="","",0) | P20: =IF(B20="","",0)
A21: 17 | G21: =IF(B21="","",0) | L21: =IF(B21="","",0) | P21: =IF(B21="","",0)
A22: 18 | G22: =IF(B22="","",0) | L22: =IF(B22="","",0) | P22: =IF(B22="","",0)
A23: 19 | G23: =IF(B23="","",0) | L23: =IF(B23="","",0) | P23: =IF(B23="","",0)
A24: 20 | G24: =IF(B24="","",0) | L24: =IF(B24="","",0) | P24: =IF(B24="","",0)
B25: TOTALS | D25: =SUM(D5:D24) -> 25000 | E25: =SUM(E5:E24) -> 0 | F25: =SUM(F5:F24) -> 21716.67 | G25: =SUM(G5:G24) -> 3283.33 | H25: =SUM(H5:H24) -> 29000 | I25: =SUM(I5:I24) -> 1650 | J25: =SUM(J5:J24) -> 4600 | K25: =SUM(K5:K24) -> 23772.5 | ... P25: =SUM(P5:P24) -> 3302.5
B26: Collection Rate: | F26: T1: | G26: =IF(D25+E25=0,1,F25/(D25+E25)) -> 0.8686668 | K26: T2: | L26: =IF(H25+I25-J25=0,1,K25/(H25+I25-J25)) -> 0.91257198 | O26: =SUMIF('Grade 1 - Payments'!C5:C154,B26,'Grade 1 - Payments'!F5:F154) -> 0

Sheet Grade 1 - Payments
A1: Grade 1: Skylarks — PAYMENT RECEIPTS LOG (Term 3, 2025/26: 21 Apr – 24 Jul 2026) | P1: Abomabiik Janelle Adepa
A2: Payment deadline: 30 June 2026 | Enter one row per payment | T3 Paid on class register auto-updates via SUMIFS | P2: Anaman Sam Darkoh
A3: TRANSACTION DETAILS | G3: PAYMENT | J3: VERIFICATION | P3: Asare Okaine Bismark
A4: Date | B4: Receipt No. | C4: Pupil Name | D4: Term | E4: Week | F4: Amount (GHS) | G4: Payment Method | H4: Received By | I4: Running Total | J4: Verified | K4: Notes | P4: Campbell Jaheem Coffie
A5: 46139 | B5: 1053 | C5: Campbell Jaheem Coffie | D5: Term 3 | E5: Wk 2 (28 Apr) | F5: 1000 | G5: MTN MoMo | H5: Dorcas Matilda Akosua Kusi | I5: =IF(F5="","",F5) -> 1000 | P5: Djaba Emily
A6: 46139 | B6: 1050 | C6: Tsikata Sejanam Kokui | D6: Term 3 | E6: Wk 2 (28 Apr) | F6: 2000 | G6: Cash | H6: Other | I6: =IF(F6="","",IF(I5="",F6,I5+F6)) -> 3000 | P6: Gyesi-Dodd Nkunim Kwesi
A7: 46146 | B7: 1061 | C7: Campbell Jaheem Coffie | D7: Term 3 | E7: Wk 3 (05 May) | F7: 749.5 | G7: MTN MoMo | H7: Other | I7: =IF(F7="","",IF(I6="",F7,I6+F7)) -> 3749.5 | P7: Kassim Umar
A8: 46148 | B8: 1063 | C8: Anaman Sam Darkoh | D8: Term 3 | E8: Wk 3 (05 May) | F8: 3200 | G8: MTN MoMo | H8: Other | I8: =IF(F8="","",IF(I7="",F8,I7+F8)) -> 6949.5 | P8: Mensah-Aborampah A.E. Owuraku
A9: 46149 | B9: 1065 | C9: Kassim Umar | D9: Term 3 | E9: Wk 3 (05 May) | F9: 3627.5 | G9: Cash | H9: Dorcas Matilda Akosua Kusi | I9: =IF(F9="","",IF(I8="",F9,I8+F9)) -> 10577 | P9: Tsikata Sejanam Kokui
A10: 46149 | B10: 1067 | C10: Gregoria Benneh | D10: Term 3 | E10: Wk 3 (05 May) | F10: 950 | G10: Cash | H10: Dorcas Matilda Akosua Kusi | I10: =IF(F10="","",IF(I9="",F10,I9+F10)) -> 11527 | P10: Bekoe Calvin Darko
A11: 46155 | B11: 1071 | C11: Mensah-Aborampah A.E. Owuraku | D11: Term 2 Arrears | E11: Wk 4 (12 May) | F11: 900 | G11: MTN MoMo | H11: Dorcas Matilda Akosua Kusi | I11: =IF(F11="","",IF(I10="",F11,I10+F11)) -> 12427
A12: 46167 | B12: 1084 | C12: Abomabiik Janelle Adepa | D12: Term 3 | E12: Wk 6 (26 May) | F12: 2000 | G12: MTN MoMo | H12: Dorcas Matilda Akosua Kusi | I12: =IF(F12="","",IF(I11="",F12,I11+F12)) -> 14427
A13: 46167 | B13: 1085 | C13: Gyesi-Dodd Nkunim Kwesi | D13: Term 3 | E13: Wk 6 (26 May) | F13: 3200 | G13: Bank Transfer | H13: Dorcas Matilda Akosua Kusi | I13: =IF(F13="","",IF(I12="",F13,I12+F13)) -> 17627
A14: 46199 | B14: 1088 | C14: Campbell Jaheem Coffie | D14: Term 3 | E14: Wk 6 (26 May) | F14: 669.5 | G14: MTN MoMo | H14: Dorcas Matilda Akosua Kusi | I14: =IF(F14="","",IF(I13="",F14,I13+F14)) -> 18296.5
A15: 46176 | B15: 1106 | C15: Tsikata Sejanam Kokui | D15: Term 3 | E15: Wk 7 (02 Jun) | F15: 1050 | G15: MTN MoMo | H15: Dorcas Matilda Akosua Kusi | I15: =IF(F15="","",IF(I14="",F15,I14+F15)) -> 19346.5
A16: 46185 | B16: 1114 | C16: Mensah-Aborampah A.E. Owuraku | D16: Term 3 | E16: Wk 8 (09 Jun) | F16: 900 | G16: MTN MoMo | H16: Other | I16: =IF(F16="","",IF(I15="",F16,I15+F16)) -> 20246.5
A17: 46195 | B17: 1120 | C17: Campbell Jaheem Coffie | D17: Term 3 | E17: Wk 10 (23 Jun) | F17: 781 | G17: MTN MoMo | H17: Other | I17: =IF(F17="","",IF(I16="",F17,I16+F17)) -> 21027.5
A18: 46209 | B18: 1125 | C18: Abomabiik Janelle Adepa | D18: Term 3 | E18: Wk 12 (07 Jul) | F18: 1200 | G18: Cash | H18: Other | I18: =IF(F18="","",IF(I17="",F18,I17+F18)) -> 22227.5
A19: 14/07/2026 | B19: 1138 | C19: Mensah-Aborampah A.E. Owuraku | D19: Term 3 | E19: Wk 13 (14 Jul) | F19: 1000 | G19: MTN MoMo | H19: Dorcas Matilda Akosua Kusi | I19: =IF(F19="","",IF(I18="",F19,I18+F19)) -> 23227.5
A20: 27/04/2026 | B20: 1055 | C20: Calvin Bekoe | D20: Term 3 | E20: Wk 2 (28 Apr) | F20: 3200 | G20: Bank Transfer | H20: Dorcas Matilda Akosua Kusi | I20: =IF(F20="","",IF(I19="",F20,I19+F20)) -> 26427.5
I21: =IF(F21="","",IF(I20="",F21,I20+F21))
I22: =IF(F22="","",IF(I21="",F22,I21+F22))
I23: =IF(F23="","",IF(I22="",F23,I22+F23))
I24: =IF(F24="","",IF(I23="",F24,I23+F24))
I25: =IF(F25="","",IF(I24="",F25,I24+F25))
I26: =IF(F26="","",IF(I25="",F26,I25+F26))
I27: =IF(F27="","",IF(I26="",F27,I26+F27))
I28: =IF(F28="","",IF(I27="",F28,I27+F28))
I29: =IF(F29="","",IF(I28="",F29,I28+F29))
I30: =IF(F30="","",IF(I29="",F30,I29+F30))
I31: =IF(F31="","",IF(I30="",F31,I30+F31))
I32: =IF(F32="","",IF(I31="",F32,I31+F32))
... I154: =IF(F154="","",IF(I153="",F154,I153+F154))
A157: WEEKLY COLLECTION SUMMARY (auto-calculated from payment log)
A158: Week | B158: Week Starting | C158: Entries | D158: Cash | E158: MoMo (All) | F158: Bank Transfer | G158: Cheque | H158: Week Total | I158: Cumulative | J158: vs Deadline | K158: Notes
A159: Wk 1 (21 Apr) | B159: 46133 | C159: =COUNTIF(E5:E154,"Wk 1 (21 Apr)") -> 0 | D159: =SUMPRODUCT((E5:E154="Wk 1 (21 Apr)")*(G5:G154="Cash")*(F5:F154)) -> 0 | E159: =SUMPRODUCT((E5:E154="Wk 1 (21 Apr)")*((G5:G154="MTN MoMo")+(G5:G154="Vodafone Cash")+(G5:G154="AirtelTigo Money"))*(F5:F154)) -> 0 | F159: =SUMPRODUCT((E5:E154="Wk 1 (21 Apr)")*(G5:G154="Bank Transfer")*(F5:F154)) -> 0 | G159: =SUMPRODUCT((E5:E154="Wk 1 (21 Apr)")*(G5:G154="Cheque")*(F5:F154)) -> 0 | H159: =SUM(D159:G159) -> 0 | I159: =H159 -> 0
A160: Wk 2 (28 Apr) | B160: 46140 | C160: =COUNTIF(E5:E154,"Wk 2 (28 Apr)") -> 3 | D160: =SUMPRODUCT((E5:E154="Wk 2 (28 Apr)")*(G5:G154="Cash")*(F5:F154)) -> 2000 | E160: =SUMPRODUCT((E5:E154="Wk 2 (28 Apr)")*((G5:G154="MTN MoMo")+(G5:G154="Vodafone Cash")+(G5:G154="AirtelTigo Money"))*(F5:F154)) -> 1000 | F160: =SUMPRODUCT((E5:E154="Wk 2 (28 Apr)")*(G5:G154="Bank Transfer")*(F5:F154)) -> 3200 | G160: =SUMPRODUCT((E5:E154="Wk 2 (28 Apr)")*(G5:G154="Cheque")*(F5:F154)) -> 0 | H160: =SUM(D160:G160) -> 6200 | I160: =I159+H160 -> 6200
A161: Wk 3 (05 May) | B161: 46147 | C161: =COUNTIF(E5:E154,"Wk 3 (05 May)") -> 4 | D161: =SUMPRODUCT((E5:E154="Wk 3 (05 May)")*(G5:G154="Cash")*(F5:F154)) -> 4577.5 | E161: =SUMPRODUCT((E5:E154="Wk 3 (05 May)")*((G5:G154="MTN MoMo")+(G5:G154="Vodafone Cash")+(G5:G154="AirtelTigo Money"))*(F5:F154)) -> 3949.5 | F161: =SUMPRODUCT((E5:E154="Wk 3 (05 May)")*(G5:G154="Bank Transfer")*(F5:F154)) -> 0 | G161: =SUMPRODUCT((E5:E154="Wk 3 (05 May)")*(G5:G154="Cheque")*(F5:F154)) -> 0 | H161: =SUM(D161:G161) -> 8527 | I161: =I160+H161 -> 14727
A162: Wk 4 (12 May) | B162: 46154 | C162: =COUNTIF(E5:E154,"Wk 4 (12 May)") -> 1 | D162: =SUMPRODUCT((E5:E154="Wk 4 (12 May)")*(G5:G154="Cash")*(F5:F154)) -> 0 | E162: =SUMPRODUCT((E5:E154="Wk 4 (12 May)")*((G5:G154="MTN MoMo")+(G5:G154="Vodafone Cash")+(G5:G154="AirtelTigo Money"))*(F5:F154)) -> 900 | F162: =SUMPRODUCT((E5:E154="Wk 4 (12 May)")*(G5:G154="Bank Transfer")*(F5:F154)) -> 0 | G162: =SUMPRODUCT((E5:E154="Wk 4 (12 May)")*(G5:G154="Cheque")*(F5:F154)) -> 0 | H162: =SUM(D162:G162) -> 900 | I162: =I161+H162 -> 15627
A163: Wk 5 (19 May) | B163: 46161 | C163: =COUNTIF(E5:E154,"Wk 5 (19 May)") -> 0 | D163: =SUMPRODUCT((E5:E154="Wk 5 (19 May)")*(G5:G154="Cash")*(F5:F154)) -> 0 | E163: =SUMPRODUCT((E5:E154="Wk 5 (19 May)")*((G5:G154="MTN MoMo")+(G5:G154="Vodafone Cash")+(G5:G154="AirtelTigo Money"))*(F5:F154)) -> 0 | F163: =SUMPRODUCT((E5:E154="Wk 5 (19 May)")*(G5:G154="Bank Transfer")*(F5:F154)) -> 0 | G163: =SUMPRODUCT((E5:E154="Wk 5 (19 May)")*(G5:G154="Cheque")*(F5:F154)) -> 0 | H163: =SUM(D163:G163) -> 0 | I163: =I162+H163 -> 15627
A164: Wk 6 (26 May) | B164: 46168 | C164: =COUNTIF(E5:E154,"Wk 6 (26 May)") -> 3 | D164: =SUMPRODUCT((E5:E154="Wk 6 (26 May)")*(G5:G154="Cash")*(F5:F154)) -> 0 | E164: =SUMPRODUCT((E5:E154="Wk 6 (26 May)")*((G5:G154="MTN MoMo")+(G5:G154="Vodafone Cash")+(G5:G154="AirtelTigo Money"))*(F5:F154)) -> 2669.5 | F164: =SUMPRODUCT((E5:E154="Wk 6 (26 May)")*(G5:G154="Bank Transfer")*(F5:F154)) -> 3200 | G164: =SUMPRODUCT((E5:E154="Wk 6 (26 May)")*(G5:G154="Cheque")*(F5:F154)) -> 0 | H164: =SUM(D164:G164) -> 5869.5 | I164: =I163+H164 -> 21496.5
A165: Wk 7 (02 Jun) | B165: 46175 | C165: =COUNTIF(E5:E154,"Wk 7 (02 Jun)") -> 1 | D165: =SUMPRODUCT((E5:E154="Wk 7 (02 Jun)")*(G5:G154="Cash")*(F5:F154)) -> 0 | E165: =SUMPRODUCT((E5:E154="Wk 7 (02 Jun)")*((G5:G154="MTN MoMo")+(G5:G154="Vodafone Cash")+(G5:G154="AirtelTigo Money"))*(F5:F154)) -> 1050 | F165: =SUMPRODUCT((E5:E154="Wk 7 (02 Jun)")*(G5:G154="Bank Transfer")*(F5:F154)) -> 0 | G165: =SUMPRODUCT((E5:E154="Wk 7 (02 Jun)")*(G5:G154="Cheque")*(F5:F154)) -> 0 | H165: =SUM(D165:G165) -> 1050 | I165: =I164+H165 -> 22546.5
A166: Wk 8 (09 Jun) | B166: 46182 | C166: =COUNTIF(E5:E154,"Wk 8 (09 Jun)") -> 1 | D166: =SUMPRODUCT((E5:E154="Wk 8 (09 Jun)")*(G5:G154="Cash")*(F5:F154)) -> 0 | E166: =SUMPRODUCT((E5:E154="Wk 8 (09 Jun)")*((G5:G154="MTN MoMo")+(G5:G154="Vodafone Cash")+(G5:G154="AirtelTigo Money"))*(F5:F154)) -> 900 | F166: =SUMPRODUCT((E5:E154="Wk 8 (09 Jun)")*(G5:G154="Bank Transfer")*(F5:F154)) -> 0 | G166: =SUMPRODUCT((E5:E154="Wk 8 (09 Jun)")*(G5:G154="Cheque")*(F5:F154)) -> 0 | H166: =SUM(D166:G166) -> 900 | I166: =I165+H166 -> 23446.5
A167: Wk 9 (16 Jun) | B167: 46189 | C167: =COUNTIF(E5:E154,"Wk 9 (16 Jun)") -> 0 | D167: =SUMPRODUCT((E5:E154="Wk 9 (16 Jun)")*(G5:G154="Cash")*(F5:F154)) -> 0 | E167: =SUMPRODUCT((E5:E154="Wk 9 (16 Jun)")*((G5:G154="MTN MoMo")+(G5:G154="Vodafone Cash")+(G5:G154="AirtelTigo Money"))*(F5:F154)) -> 0 | F167: =SUMPRODUCT((E5:E154="Wk 9 (16 Jun)")*(G5:G154="Bank Transfer")*(F5:F154)) -> 0 | G167: =SUMPRODUCT((E5:E154="Wk 9 (16 Jun)")*(G5:G154="Cheque")*(F5:F154)) -> 0 | H167: =SUM(D167:G167) -> 0 | I167: =I166+H167 -> 23446.5
A168: Wk 10 (23 Jun) | B168: 46196 | C168: =COUNTIF(E5:E154,"Wk 10 (23 Jun)") -> 1 | D168: =SUMPRODUCT((E5:E154="Wk 10 (23 Jun)")*(G5:G154="Cash")*(F5:F154)) -> 0 | E168: =SUMPRODUCT((E5:E154="Wk 10 (23 Jun)")*((G5:G154="MTN MoMo")+(G5:G154="Vodafone Cash")+(G5:G154="AirtelTigo Money"))*(F5:F154)) -> 781 | F168: =SUMPRODUCT((E5:E154="Wk 10 (23 Jun)")*(G5:G154="Bank Transfer")*(F5:F154)) -> 0 | G168: =SUMPRODUCT((E5:E154="Wk 10 (23 Jun)")*(G5:G154="Cheque")*(F5:F154)) -> 0 | H168: =SUM(D168:G168) -> 781 | I168: =I167+H168 -> 24227.5
A169: Wk 11 (30 Jun) | B169: 46203 | C169: =COUNTIF(E5:E154,"Wk 11 (30 Jun)") -> 0 | D169: =SUMPRODUCT((E5:E154="Wk 11 (30 Jun)")*(G5:G154="Cash")*(F5:F154)) -> 0 | E169: =SUMPRODUCT((E5:E154="Wk 11 (30 Jun)")*((G5:G154="MTN MoMo")+(G5:G154="Vodafone Cash")+(G5:G154="AirtelTigo Money"))*(F5:F154)) -> 0 | F169: =SUMPRODUCT((E5:E154="Wk 11 (30 Jun)")*(G5:G154="Bank Transfer")*(F5:F154)) -> 0 | G169: =SUMPRODUCT((E5:E154="Wk 11 (30 Jun)")*(G5:G154="Cheque")*(F5:F154)) -> 0 | H169: =SUM(D169:G169) -> 0 | I169: =I168+H169 -> 24227.5
A170: Wk 12 (07 Jul) | B170: 46210 | C170: =COUNTIF(E5:E154,"Wk 12 (07 Jul)") -> 1 | D170: =SUMPRODUCT((E5:E154="Wk 12 (07 Jul)")*(G5:G154="Cash")*(F5:F154)) -> 1200 | E170: =SUMPRODUCT((E5:E154="Wk 12 (07 Jul)")*((G5:G154="MTN MoMo")+(G5:G154="Vodafone Cash")+(G5:G154="AirtelTigo Money"))*(F5:F154)) -> 0 | F170: =SUMPRODUCT((E5:E154="Wk 12 (07 Jul)")*(G5:G154="Bank Transfer")*(F5:F154)) -> 0 | G170: =SUMPRODUCT((E5:E154="Wk 12 (07 Jul)")*(G5:G154="Cheque")*(F5:F154)) -> 0 | H170: =SUM(D170:G170) -> 1200 | I170: =I169+H170 -> 25427.5 | J170: PAST DEADLINE
A171: Wk 13 (14 Jul) | B171: 46217 | C171: =COUNTIF(E5:E154,"Wk 13 (14 Jul)") -> 1 | D171: =SUMPRODUCT((E5:E154="Wk 13 (14 Jul)")*(G5:G154="Cash")*(F5:F154)) -> 0 | E171: =SUMPRODUCT((E5:E154="Wk 13 (14 Jul)")*((G5:G154="MTN MoMo")+(G5:G154="Vodafone Cash")+(G5:G154="AirtelTigo Money"))*(F5:F154)) -> 1000 | F171: =SUMPRODUCT((E5:E154="Wk 13 (14 Jul)")*(G5:G154="Bank Transfer")*(F5:F154)) -> 0 | G171: =SUMPRODUCT((E5:E154="Wk 13 (14 Jul)")*(G5:G154="Cheque")*(F5:F154)) -> 0 | H171: =SUM(D171:G171) -> 1000 | I171: =I170+H171 -> 26427.5 | J171: PAST DEADLINE
A172: Wk 14 (21 Jul) | B172: 46224 | C172: =COUNTIF(E5:E154,"Wk 14 (21 Jul)") -> 0 | D172: =SUMPRODUCT((E5:E154="Wk 14 (21 Jul)")*(G5:G154="Cash")*(F5:F154)) -> 0 | E172: =SUMPRODUCT((E5:E154="Wk 14 (21 Jul)")*((G5:G154="MTN MoMo")+(G5:G154="Vodafone Cash")+(G5:G154="AirtelTigo Money"))*(F5:F154)) -> 0 | F172: =SUMPRODUCT((E5:E154="Wk 14 (21 Jul)")*(G5:G154="Bank Transfer")*(F5:F154)) -> 0 | G172: =SUMPRODUCT((E5:E154="Wk 14 (21 Jul)")*(G5:G154="Cheque")*(F5:F154)) -> 0 | H172: =SUM(D172:G172) -> 0 | I172: =I171+H172 -> 26427.5 | J172: PAST DEADLINE
A173: TERM 3 TOTAL | C173: =SUM(C159:C172) -> 16 | D173: =SUM(D159:D172) -> 7777.5 | E173: =SUM(E159:E172) -> 12250 | F173: =SUM(F159:F172) -> 6400 | G173: =SUM(G159:G172) -> 0 | H173: =SUM(H159:H172) -> 26427.5
A176: MONTHLY COLLECTION SUMMARY
A177: Month | B177: No. of Payments | C177: Cash | D177: MoMo (All) | E177: Bank Transfer | F177: Cheque | G177: Month Total | H177: Cumulative | I177: Target % | J177: Actual % | K177: Notes
A178: Apr | B178: =SUMPRODUCT((MONTH(A5:A154)=4)*(A5:A154<>"")) -> 3 | C178: =SUMPRODUCT((MONTH(A5:A154)=4)*(G5:G154="Cash")*(F5:F154)) -> 2000 | D178: =SUMPRODUCT((MONTH(A5:A154)=4)*((G5:G154="MTN MoMo")+(G5:G154="Vodafone Cash")+(G5:G154="AirtelTigo Money"))*(F5:F154)) -> 1000 | E178: =SUMPRODUCT((MONTH(A5:A154)=4)*(G5:G154="Bank Transfer")*(F5:F154)) -> 3200 | F178: =SUMPRODUCT((MONTH(A5:A154)=4)*(G5:G154="Cheque")*(F5:F154)) -> 0 | G178: =SUM(C178:F178) -> 6200 | H178: =G178 -> 6200 | I178: 0.3
A179: May | B179: =SUMPRODUCT((MONTH(A5:A154)=5)*(A5:A154<>"")) -> 7 | C179: =SUMPRODUCT((MONTH(A5:A154)=5)*(G5:G154="Cash")*(F5:F154)) -> 4577.5 | D179: =SUMPRODUCT((MONTH(A5:A154)=5)*((G5:G154="MTN MoMo")+(G5:G154="Vodafone Cash")+(G5:G154="AirtelTigo Money"))*(F5:F154)) -> 6849.5 | E179: =SUMPRODUCT((MONTH(A5:A154)=5)*(G5:G154="Bank Transfer")*(F5:F154)) -> 3200 | F179: =SUMPRODUCT((MONTH(A5:A154)=5)*(G5:G154="Cheque")*(F5:F154)) -> 0 | G179: =SUM(C179:F179) -> 14627 | H179: =H178+G179 -> 20827 | I179: 0.65
A180: Jun | B180: =SUMPRODUCT((MONTH(A5:A154)=6)*(A5:A154<>"")) -> 4 | C180: =SUMPRODUCT((MONTH(A5:A154)=6)*(G5:G154="Cash")*(F5:F154)) -> 0 | D180: =SUMPRODUCT((MONTH(A5:A154)=6)*((G5:G154="MTN MoMo")+(G5:G154="Vodafone Cash")+(G5:G154="AirtelTigo Money"))*(F5:F154)) -> 3400.5 | E180: =SUMPRODUCT((MONTH(A5:A154)=6)*(G5:G154="Bank Transfer")*(F5:F154)) -> 0 | F180: =SUMPRODUCT((MONTH(A5:A154)=6)*(G5:G154="Cheque")*(F5:F154)) -> 0 | G180: =SUM(C180:F180) -> 3400.5 | H180: =H179+G180 -> 24227.5 | I180: 1
A181: Jul | B181: =SUMPRODUCT((MONTH(A5:A154)=7)*(A5:A154<>"")) -> 2 | C181: =SUMPRODUCT((MONTH(A5:A154)=7)*(G5:G154="Cash")*(F5:F154)) -> 1200 | D181: =SUMPRODUCT((MONTH(A5:A154)=7)*((G5:G154="MTN MoMo")+(G5:G154="Vodafone Cash")+(G5:G154="AirtelTigo Money"))*(F5:F154)) -> 1000 | E181: =SUMPRODUCT((MONTH(A5:A154)=7)*(G5:G154="Bank Transfer")*(F5:F154)) -> 0 | F181: =SUMPRODUCT((MONTH(A5:A154)=7)*(G5:G154="Cheque")*(F5:F154)) -> 0 | G181: =SUM(C181:F181) -> 2200 | H181: =H180+G181 -> 26427.5 | I181: 1
A182: TOTAL | B182: =SUM(B178:B181) -> 16 | C182: =SUM(C178:C181) -> 7777.5 | D182: =SUM(D178:D181) -> 12250 | E182: =SUM(E178:E181) -> 6400 | F182: =SUM(F178:F181) -> 0 | G182: =SUM(G178:G181) -> 26427.5

Sheet Grade 2 - Kestrels
A1: Grade 2: Kestrels — Vigilance | Determine | Annual: GHS 8,500 | Termly: GHS 3,000
A3: PUPIL DETAILS | D3: TERM 1 (COMPLETED) | H3: TERM 2 (COMPLETED) | M3: TERM 3 (ACTIVE — arrears from T1/T2 included) | Q3: NOTES
A4: No. | B4: Pupil Name | C4: Discount Type | D4: T1 Fee | E4: T1 Arrears BF | F4: T1 Paid | G4: T1 Balance | H4: T2 Fee | I4: T2 Arrears BF | J4: T2 Discount | K4: T2 Paid | L4: T2 Balance | M4: T3 Fee | N4: T3 Discount | O4: T3 Paid | P4: T3 Balance | Q4: Remarks / Waiver Notes
A5: 1 | B5: Afful Ewura-Yaa Nkunim | D5: 3200 | F5: 3200 | G5: =IF(B5="","",IF(D5="",0,D5)+IF(E5="",0,E5)-IF(F5="",0,F5)) -> 0 | H5: 3000 | K5: 3000 | L5: =IF(B5="","",IF(H5="",0,H5)+IF(I5="",0,I5)-IF(J5="",0,J5)-IF(K5="",0,K5)) -> 0 | M5: 3000 | O5: =SUMIF('Grade 2 - Payments'!C5:C154,B5,'Grade 2 - Payments'!F5:F154) -> 3200 | P5: =IF(B5="","",IF(M5="",0,M5)-IF(N5="",0,N5)+IF(L5<0,0,IF(L5="",0,L5))-IF(O5="",0,O5)) -> -200
A6: 2 | B6: Antwi Brion | D6: 3200 | F6: 3000 | G6: =IF(B6="","",IF(D6="",0,D6)+IF(E6="",0,E6)-IF(F6="",0,F6)) -> 200 | H6: 3000 | K6: 3000 | L6: =IF(B6="","",IF(H6="",0,H6)+IF(I6="",0,I6)-IF(J6="",0,J6)-IF(K6="",0,K6)) -> 0 | M6: 3000 | O6: =SUMIF('Grade 2 - Payments'!C5:C154,B6,'Grade 2 - Payments'!F5:F154) -> 3200 | P6: =IF(B6="","",IF(M6="",0,M6)-IF(N6="",0,N6)+IF(L6<0,0,IF(L6="",0,L6))-IF(O6="",0,O6)) -> -200
A7: 3 | B7: Appiah Zakiel Nana Kwame | D7: 3200 | F7: 2900 | G7: =IF(B7="","",IF(D7="",0,D7)+IF(E7="",0,E7)-IF(F7="",0,F7)) -> 300 | H7: 3000 | K7: 1650 | L7: =IF(B7="","",IF(H7="",0,H7)+IF(I7="",0,I7)-IF(J7="",0,J7)-IF(K7="",0,K7)) -> 1350 | M7: 3000 | O7: =SUMIF('Grade 2 - Payments'!C5:C154,B7,'Grade 2 - Payments'!F5:F154) -> 4750 | P7: =IF(B7="","",IF(M7="",0,M7)-IF(N7="",0,N7)+IF(L7<0,0,IF(L7="",0,L7))-IF(O7="",0,O7)) -> -400 | Q7: Growing arrears — T2 balance GHS 1,350
A8: 4 | B8: Kanati Jesse Nuna | D8: 3200 | F8: 3200 | G8: =IF(B8="","",IF(D8="",0,D8)+IF(E8="",0,E8)-IF(F8="",0,F8)) -> 0 | H8: 3000 | K8: 3000 | L8: =IF(B8="","",IF(H8="",0,H8)+IF(I8="",0,I8)-IF(J8="",0,J8)-IF(K8="",0,K8)) -> 0 | M8: 3000 | O8: =SUMIF('Grade 2 - Payments'!C5:C154,B8,'Grade 2 - Payments'!F5:F154) -> 3200 | P8: =IF(B8="","",IF(M8="",0,M8)-IF(N8="",0,N8)+IF(L8<0,0,IF(L8="",0,L8))-IF(O8="",0,O8)) -> -200
A9: 5 | B9: Morkeh Michelle | D9: 3200 | G9: =IF(B9="","",IF(D9="",0,D9)+IF(E9="",0,E9)-IF(F9="",0,F9)) -> 3200 | H9: 3000 | I9: 1700 | K9: 2577.5 | L9: =IF(B9="","",IF(H9="",0,H9)+IF(I9="",0,I9)-IF(J9="",0,J9)-IF(K9="",0,K9)) -> 2122.5 | M9: 3000 | O9: =SUMIF('Grade 2 - Payments'!C5:C154,B9,'Grade 2 - Payments'!F5:F154) -> 4222.5 | P9: =IF(B9="","",IF(M9="",0,M9)-IF(N9="",0,N9)+IF(L9<0,0,IF(L9="",0,L9))-IF(O9="",0,O9)) -> 900 | Q9: Never paid T1 or T2 — chronic defaulter; T2 balance GHS 2,122.50
A10: 6 | B10: Mortty Gaius Eyiram | C10: Sibling | D10: 3050 | F10: 3050 | G10: =IF(B10="","",IF(D10="",0,D10)+IF(E10="",0,E10)-IF(F10="",0,F10)) -> 0 | H10: 3000 | J10: 150 | K10: 2850 | L10: =IF(B10="","",IF(H10="",0,H10)+IF(I10="",0,I10)-IF(J10="",0,J10)-IF(K10="",0,K10)) -> 0 | M10: 3000 | N10: 150 | O10: =SUMIF('Grade 2 - Payments'!C5:C154,B10,'Grade 2 - Payments'!F5:F154) -> 3050 | P10: =IF(B10="","",IF(M10="",0,M10)-IF(N10="",0,N10)+IF(L10<0,0,IF(L10="",0,L10))-IF(O10="",0,O10)) -> -200
A11: 7 | B11: Tagoe Henry | D11: 3200 | F11: 1800 | G11: =IF(B11="","",IF(D11="",0,D11)+IF(E11="",0,E11)-IF(F11="",0,F11)) -> 1400 | I11: 400 | L11: =IF(B11="","",IF(H11="",0,H11)+IF(I11="",0,I11)-IF(J11="",0,J11)-IF(K11="",0,K11)) -> 400 | M11: 0 | O11: =SUMIF('Grade 2 - Payments'!C5:C154,B11,'Grade 2 - Payments'!F5:F154) -> 0 | P11: =IF(B11="","",IF(M11="",0,M11)-IF(N11="",0,N11)+IF(L11<0,0,IF(L11="",0,L11))-IF(O11="",0,O11)) -> 400 | Q11: T1 partial; no T2 fee charged — GHS 400 arrears
A12: 8 | B12: Tsikata Eli-Vava Sebastian | C12: Waiver | D12: 3200 | F12: 3200 | G12: =IF(B12="","",IF(D12="",0,D12)+IF(E12="",0,E12)-IF(F12="",0,F12)) -> 0 | H12: 3000 | J12: 2000 | K12: 1000 | L12: =IF(B12="","",IF(H12="",0,H12)+IF(I12="",0,I12)-IF(J12="",0,J12)-IF(K12="",0,K12)) -> 0 | M12: 3000 | O12: =SUMIF('Grade 2 - Payments'!C5:C154,B12,'Grade 2 - Payments'!F5:F154) -> 3200 | P12: =IF(B12="","",IF(M12="",0,M12)-IF(N12="",0,N12)+IF(L12<0,0,IF(L12="",0,L12))-IF(O12="",0,O12)) -> -200 | Q12: Waiver — parent's condition; GHS 2,000 waived T2
A13: 9 | G13: =IF(B13="","",0) | L13: =IF(B13="","",0) | P13: =IF(B13="","",0)
A14: 10 | G14: =IF(B14="","",0) | L14: =IF(B14="","",0) | P14: =IF(B14="","",0)
A15: 11 | G15: =IF(B15="","",0) | L15: =IF(B15="","",0) | P15: =IF(B15="","",0)
A16: 12 | G16: =IF(B16="","",0) | L16: =IF(B16="","",0) | P16: =IF(B16="","",0)
A17: 13 | G17: =IF(B17="","",0) | L17: =IF(B17="","",0) | P17: =IF(B17="","",0)
A18: 14 | G18: =IF(B18="","",0) | L18: =IF(B18="","",0) | P18: =IF(B18="","",0)
A19: 15 | G19: =IF(B19="","",0) | L19: =IF(B19="","",0) | P19: =IF(B19="","",0)
A20: 16 | G20: =IF(B20="","",0) | L20: =IF(B20="","",0) | P20: =IF(B20="","",0)
A21: 17 | G21: =IF(B21="","",0) | L21: =IF(B21="","",0) | P21: =IF(B21="","",0)
A22: 18 | G22: =IF(B22="","",0) | L22: =IF(B22="","",0) | P22: =IF(B22="","",0)
B23: TOTALS | D23: =SUM(D5:D22) -> 25450 | E23: =SUM(E5:E22) -> 0 | F23: =SUM(F5:F22) -> 20350 | G23: =SUM(G5:G22) -> 5100 | H23: =SUM(H5:H22) -> 21000 | I23: =SUM(I5:I22) -> 2100 | J23: =SUM(J5:J22) -> 2150 | K23: =SUM(K5:K22) -> 17077.5 | ... P23: =SUM(P5:P22) -> -100
B24: Collection Rate: | F24: T1: | G24: =IF(D23+E23=0,1,F23/(D23+E23)) -> 0.79960707 | K24: T2: | L24: =IF(H23+I23-J23=0,1,K23/(H23+I23-J23)) -> 0.81515513 | O24: =SUMIF('Grade 2 - Payments'!C5:C154,B24,'Grade 2 - Payments'!F5:F154) -> 0

Sheet Grade 2 - Payments
A1: Grade 2: Kestrels — PAYMENT RECEIPTS LOG (Term 3, 2025/26: 21 Apr – 24 Jul 2026) | P1: Afful Ewura-Yaa Nkunim
A2: Payment deadline: 30 June 2026 | Enter one row per payment | T3 Paid on class register auto-updates via SUMIFS | P2: Antwi Brion
A3: TRANSACTION DETAILS | G3: PAYMENT | J3: VERIFICATION | P3: Appiah Zakiel Nana Kwame
A4: Date | B4: Receipt No. | C4: Pupil Name | D4: Term | E4: Week | F4: Amount (GHS) | G4: Payment Method | H4: Received By | I4: Running Total | J4: Verified | K4: Notes | P4: Kanati Jesse Nuna
A5: 46111 | B5: 1025 | C5: Morkeh Michelle | D5: Term 2 Arrears | F5: 600 | G5: MTN MoMo | H5: Dorcas Matilda Akosua Kusi | I5: =IF(F5="","",F5) -> 600 | P5: Morkeh Michelle
A6: 46114 | B6: 1029 | C6: Appiah Zakiel Nana Kwame | D6: Term 2 Arrears | F6: 1550 | G6: Cash | H6: Dorcas Matilda Akosua Kusi | I6: =IF(F6="","",IF(I5="",F6,I5+F6)) -> 2150 | P6: Mortty Gaius Eyiram
A7: 46122 | B7: 1034 | C7: Kanati Jesse Nuna | D7: Term 3 | E7: Vacation | F7: 1000 | G7: Bank Transfer | H7: Dorcas Matilda Akosua Kusi | I7: =IF(F7="","",IF(I6="",F7,I6+F7)) -> 3150 | P7: Tagoe Henry
A8: 46127 | B8: 1037 | C8: Kanati Jesse Nuna | D8: Term 3 | E8: Vacation | F8: 2200 | G8: Bank Transfer | H8: Dorcas Matilda Akosua Kusi | I8: =IF(F8="","",IF(I7="",F8,I7+F8)) -> 5350 | P8: Tsikata Eli-Vava Sebastian
A9: 46128 | B9: 1040 | C9: Antwi Brion | D9: Term 3 | E9: Vacation | F9: 3000 | G9: MTN MoMo | H9: Dorcas Matilda Akosua Kusi | I9: =IF(F9="","",IF(I8="",F9,I8+F9)) -> 8350
A10: 46135 | B10: 1047 | C10: Morkeh Michelle | D10: Term 2 Arrears | E10: Wk 1 (21 Apr) | F10: 1722.5 | G10: MTN MoMo / Cash | H10: Other | I10: =IF(F10="","",IF(I9="",F10,I9+F10)) -> 10072.5
A11: 46139 | B11: 1048 | C11: Tsikata Eli-Vava Sebastian | D11: Term 3 | E11: Wk 2 (28 Apr) | F11: 2000 | G11: Cash | H11: Other | I11: =IF(F11="","",IF(I10="",F11,I10+F11)) -> 12072.5
A12: 46156 | B12: 1073 | C12: Mortty Gaius Eyiram | D12: Term 3 | E12: Wk 4 (12 May) | F12: 3050 | G12: Cash | H12: Dorcas Matilda Akosua Kusi | I12: =IF(F12="","",IF(I11="",F12,I11+F12)) -> 15122.5
A13: 46174 | B13: 1096 | C13: Morkeh Michelle | D13: Term 3 | E13: Wk 7 (02 Jun) | F13: 1000 | G13: MTN MoMo | H13: Dorcas Matilda Akosua Kusi | I13: =IF(F13="","",IF(I12="",F13,I12+F13)) -> 16122.5
A14: 46176 | B14: 1105 | C14: Tsikata Eli-Vava Sebastian | D14: Term 3 | E14: Wk 7 (02 Jun) | F14: 1200 | G14: MTN MoMo | H14: Dorcas Matilda Akosua Kusi | I14: =IF(F14="","",IF(I13="",F14,I13+F14)) -> 17322.5
A15: 46183 | B15: 1112 | C15: Afful Ewura-Yaa Nkunim | D15: Term 3 | E15: Wk 8 (09 Jun) | F15: 2000 | G15: MTN MoMo | H15: Dorcas Matilda Akosua Kusi | I15: =IF(F15="","",IF(I14="",F15,I14+F15)) -> 19322.5
A16: 06/07/206 | B16: 1126 | C16: Appiah Zakiel Nana Kwame | D16: Term 3 | E16: Wk 12 (07 Jul) | F16: 2000 | G16: Cash | H16: Other | I16: =IF(F16="","",IF(I15="",F16,I15+F16)) -> 21322.5
A17: 46210 | B17: 1129 | C17: Antwi Brion | D17: Term 3 | E17: Wk 12 (07 Jul) | F17: 200 | G17: Cash | H17: Other | I17: =IF(F17="","",IF(I16="",F17,I16+F17)) -> 21522.5
A18: 15/07/2026 | B18: 1141 | C18: Appiah Zakiel Nana Kwame | D18: Term 3 | E18: Wk 13 (14 Jul) | F18: 1200 | G18: Cash | H18: Dorcas Matilda Akosua Kusi | I18: =IF(F18="","",IF(I17="",F18,I17+F18)) -> 22722.5
A19: 46220 | B19: 1144 | C19: Afful Ewura-Yaa Nkunim | D19: Term 3 | E19: Wk 13 (14 Jul) | F19: 1200 | G19: MTN MoMo | H19: Other | I19: =IF(F19="","",IF(I18="",F19,I18+F19)) -> 23922.5
A20: 46223 | B20: 1145 | C20: Morkeh Michelle | D20: Term 3 | E20: Wk 14 (21 Jul) | F20: 900 | G20: Cash | H20: Other | I20: =IF(F20="","",IF(I19="",F20,I19+F20)) -> 24822.5
I21: =IF(F21="","",IF(I20="",F21,I20+F21))
I22: =IF(F22="","",IF(I21="",F22,I21+F22))
I23: =IF(F23="","",IF(I22="",F23,I22+F23))
I24: =IF(F24="","",IF(I23="",F24,I23+F24))
I25: =IF(F25="","",IF(I24="",F25,I24+F25))
I26: =IF(F26="","",IF(I25="",F26,I25+F26))
I27: =IF(F27="","",IF(I26="",F27,I26+F27))
I28: =IF(F28="","",IF(I27="",F28,I27+F28))
I29: =IF(F29="","",IF(I28="",F29,I28+F29))
I30: =IF(F30="","",IF(I29="",F30,I29+F30))
I31: =IF(F31="","",IF(I30="",F31,I30+F31))
I32: =IF(F32="","",IF(I31="",F32,I31+F32))
... I154: =IF(F154="","",IF(I153="",F154,I153+F154))
A157: WEEKLY COLLECTION SUMMARY (auto-calculated from payment log)
A158: Week | B158: Week Starting | C158: Entries | D158: Cash | E158: MoMo (All) | F158: Bank Transfer | G158: Cheque | H158: Week Total | I158: Cumulative | J158: vs Deadline | K158: Notes
A159: Wk 1 (21 Apr) | B159: 46133 | C159: =COUNTIF(E5:E154,"Wk 1 (21 Apr)") -> 1 | D159: =SUMPRODUCT((E5:E154="Wk 1 (21 Apr)")*(G5:G154="Cash")*(F5:F154)) -> 0 | E159: =SUMPRODUCT((E5:E154="Wk 1 (21 Apr)")*((G5:G154="MTN MoMo")+(G5:G154="Vodafone Cash")+(G5:G154="AirtelTigo Money"))*(F5:F154)) -> 0 | F159: =SUMPRODUCT((E5:E154="Wk 1 (21 Apr)")*(G5:G154="Bank Transfer")*(F5:F154)) -> 0 | G159: =SUMPRODUCT((E5:E154="Wk 1 (21 Apr)")*(G5:G154="Cheque")*(F5:F154)) -> 0 | H159: =SUM(D159:G159) -> 0 | I159: =H159 -> 0
A160: Wk 2 (28 Apr) | B160: 46140 | C160: =COUNTIF(E5:E154,"Wk 2 (28 Apr)") -> 1 | D160: =SUMPRODUCT((E5:E154="Wk 2 (28 Apr)")*(G5:G154="Cash")*(F5:F154)) -> 2000 | E160: =SUMPRODUCT((E5:E154="Wk 2 (28 Apr)")*((G5:G154="MTN MoMo")+(G5:G154="Vodafone Cash")+(G5:G154="AirtelTigo Money"))*(F5:F154)) -> 0 | F160: =SUMPRODUCT((E5:E154="Wk 2 (28 Apr)")*(G5:G154="Bank Transfer")*(F5:F154)) -> 0 | G160: =SUMPRODUCT((E5:E154="Wk 2 (28 Apr)")*(G5:G154="Cheque")*(F5:F154)) -> 0 | H160: =SUM(D160:G160) -> 2000 | I160: =I159+H160 -> 2000
A161: Wk 3 (05 May) | B161: 46147 | C161: =COUNTIF(E5:E154,"Wk 3 (05 May)") -> 0 | D161: =SUMPRODUCT((E5:E154="Wk 3 (05 May)")*(G5:G154="Cash")*(F5:F154)) -> 0 | E161: =SUMPRODUCT((E5:E154="Wk 3 (05 May)")*((G5:G154="MTN MoMo")+(G5:G154="Vodafone Cash")+(G5:G154="AirtelTigo Money"))*(F5:F154)) -> 0 | F161: =SUMPRODUCT((E5:E154="Wk 3 (05 May)")*(G5:G154="Bank Transfer")*(F5:F154)) -> 0 | G161: =SUMPRODUCT((E5:E154="Wk 3 (05 May)")*(G5:G154="Cheque")*(F5:F154)) -> 0 | H161: =SUM(D161:G161) -> 0 | I161: =I160+H161 -> 2000
A162: Wk 4 (12 May) | B162: 46154 | C162: =COUNTIF(E5:E154,"Wk 4 (12 May)") -> 1 | D162: =SUMPRODUCT((E5:E154="Wk 4 (12 May)")*(G5:G154="Cash")*(F5:F154)) -> 3050 | E162: =SUMPRODUCT((E5:E154="Wk 4 (12 May)")*((G5:G154="MTN MoMo")+(G5:G154="Vodafone Cash")+(G5:G154="AirtelTigo Money"))*(F5:F154)) -> 0 | F162: =SUMPRODUCT((E5:E154="Wk 4 (12 May)")*(G5:G154="Bank Transfer")*(F5:F154)) -> 0 | G162: =SUMPRODUCT((E5:E154="Wk 4 (12 May)")*(G5:G154="Cheque")*(F5:F154)) -> 0 | H162: =SUM(D162:G162) -> 3050 | I162: =I161+H162 -> 5050
A163: Wk 5 (19 May) | B163: 46161 | C163: =COUNTIF(E5:E154,"Wk 5 (19 May)") -> 0 | D163: =SUMPRODUCT((E5:E154="Wk 5 (19 May)")*(G5:G154="Cash")*(F5:F154)) -> 0 | E163: =SUMPRODUCT((E5:E154="Wk 5 (19 May)")*((G5:G154="MTN MoMo")+(G5:G154="Vodafone Cash")+(G5:G154="AirtelTigo Money"))*(F5:F154)) -> 0 | F163: =SUMPRODUCT((E5:E154="Wk 5 (19 May)")*(G5:G154="Bank Transfer")*(F5:F154)) -> 0 | G163: =SUMPRODUCT((E5:E154="Wk 5 (19 May)")*(G5:G154="Cheque")*(F5:F154)) -> 0 | H163: =SUM(D163:G163) -> 0 | I163: =I162+H163 -> 5050
A164: Wk 6 (26 May) | B164: 46168 | C164: =COUNTIF(E5:E154,"Wk 6 (26 May)") -> 0 | D164: =SUMPRODUCT((E5:E154="Wk 6 (26 May)")*(G5:G154="Cash")*(F5:F154)) -> 0 | E164: =SUMPRODUCT((E5:E154="Wk 6 (26 May)")*((G5:G154="MTN MoMo")+(G5:G154="Vodafone Cash")+(G5:G154="AirtelTigo Money"))*(F5:F154)) -> 0 | F164: =SUMPRODUCT((E5:E154="Wk 6 (26 May)")*(G5:G154="Bank Transfer")*(F5:F154)) -> 0 | G164: =SUMPRODUCT((E5:E154="Wk 6 (26 May)")*(G5:G154="Cheque")*(F5:F154)) -> 0 | H164: =SUM(D164:G164) -> 0 | I164: =I163+H164 -> 5050
A165: Wk 7 (02 Jun) | B165: 46175 | C165: =COUNTIF(E5:E154,"Wk 7 (02 Jun)") -> 2 | D165: =SUMPRODUCT((E5:E154="Wk 7 (02 Jun)")*(G5:G154="Cash")*(F5:F154)) -> 0 | E165: =SUMPRODUCT((E5:E154="Wk 7 (02 Jun)")*((G5:G154="MTN MoMo")+(G5:G154="Vodafone Cash")+(G5:G154="AirtelTigo Money"))*(F5:F154)) -> 2200 | F165: =SUMPRODUCT((E5:E154="Wk 7 (02 Jun)")*(G5:G154="Bank Transfer")*(F5:F154)) -> 0 | G165: =SUMPRODUCT((E5:E154="Wk 7 (02 Jun)")*(G5:G154="Cheque")*(F5:F154)) -> 0 | H165: =SUM(D165:G165) -> 2200 | I165: =I164+H165 -> 7250
A166: Wk 8 (09 Jun) | B166: 46182 | C166: =COUNTIF(E5:E154,"Wk 8 (09 Jun)") -> 1 | D166: =SUMPRODUCT((E5:E154="Wk 8 (09 Jun)")*(G5:G154="Cash")*(F5:F154)) -> 0 | E166: =SUMPRODUCT((E5:E154="Wk 8 (09 Jun)")*((G5:G154="MTN MoMo")+(G5:G154="Vodafone Cash")+(G5:G154="AirtelTigo Money"))*(F5:F154)) -> 2000 | F166: =SUMPRODUCT((E5:E154="Wk 8 (09 Jun)")*(G5:G154="Bank Transfer")*(F5:F154)) -> 0 | G166: =SUMPRODUCT((E5:E154="Wk 8 (09 Jun)")*(G5:G154="Cheque")*(F5:F154)) -> 0 | H166: =SUM(D166:G166) -> 2000 | I166: =I165+H166 -> 9250
A167: Wk 9 (16 Jun) | B167: 46189 | C167: =COUNTIF(E5:E154,"Wk 9 (16 Jun)") -> 0 | D167: =SUMPRODUCT((E5:E154="Wk 9 (16 Jun)")*(G5:G154="Cash")*(F5:F154)) -> 0 | E167: =SUMPRODUCT((E5:E154="Wk 9 (16 Jun)")*((G5:G154="MTN MoMo")+(G5:G154="Vodafone Cash")+(G5:G154="AirtelTigo Money"))*(F5:F154)) -> 0 | F167: =SUMPRODUCT((E5:E154="Wk 9 (16 Jun)")*(G5:G154="Bank Transfer")*(F5:F154)) -> 0 | G167: =SUMPRODUCT((E5:E154="Wk 9 (16 Jun)")*(G5:G154="Cheque")*(F5:F154)) -> 0 | H167: =SUM(D167:G167) -> 0 | I167: =I166+H167 -> 9250
A168: Wk 10 (23 Jun) | B168: 46196 | C168: =COUNTIF(E5:E154,"Wk 10 (23 Jun)") -> 0 | D168: =SUMPRODUCT((E5:E154="Wk 10 (23 Jun)")*(G5:G154="Cash")*(F5:F154)) -> 0 | E168: =SUMPRODUCT((E5:E154="Wk 10 (23 Jun)")*((G5:G154="MTN MoMo")+(G5:G154="Vodafone Cash")+(G5:G154="AirtelTigo Money"))*(F5:F154)) -> 0 | F168: =SUMPRODUCT((E5:E154="Wk 10 (23 Jun)")*(G5:G154="Bank Transfer")*(F5:F154)) -> 0 | G168: =SUMPRODUCT((E5:E154="Wk 10 (23 Jun)")*(G5:G154="Cheque")*(F5:F154)) -> 0 | H168: =SUM(D168:G168) -> 0 | I168: =I167+H168 -> 9250
A169: Wk 11 (30 Jun) | B169: 46203 | C169: =COUNTIF(E5:E154,"Wk 11 (30 Jun)") -> 0 | D169: =SUMPRODUCT((E5:E154="Wk 11 (30 Jun)")*(G5:G154="Cash")*(F5:F154)) -> 0 | E169: =SUMPRODUCT((E5:E154="Wk 11 (30 Jun)")*((G5:G154="MTN MoMo")+(G5:G154="Vodafone Cash")+(G5:G154="AirtelTigo Money"))*(F5:F154)) -> 0 | F169: =SUMPRODUCT((E5:E154="Wk 11 (30 Jun)")*(G5:G154="Bank Transfer")*(F5:F154)) -> 0 | G169: =SUMPRODUCT((E5:E154="Wk 11 (30 Jun)")*(G5:G154="Cheque")*(F5:F154)) -> 0 | H169: =SUM(D169:G169) -> 0 | I169: =I168+H169 -> 9250
A170: Wk 12 (07 Jul) | B170: 46210 | C170: =COUNTIF(E5:E154,"Wk 12 (07 Jul)") -> 2 | D170: =SUMPRODUCT((E5:E154="Wk 12 (07 Jul)")*(G5:G154="Cash")*(F5:F154)) -> 2200 | E170: =SUMPRODUCT((E5:E154="Wk 12 (07 Jul)")*((G5:G154="MTN MoMo")+(G5:G154="Vodafone Cash")+(G5:G154="AirtelTigo Money"))*(F5:F154)) -> 0 | F170: =SUMPRODUCT((E5:E154="Wk 12 (07 Jul)")*(G5:G154="Bank Transfer")*(F5:F154)) -> 0 | G170: =SUMPRODUCT((E5:E154="Wk 12 (07 Jul)")*(G5:G154="Cheque")*(F5:F154)) -> 0 | H170: =SUM(D170:G170) -> 2200 | I170: =I169+H170 -> 11450 | J170: PAST DEADLINE
A171: Wk 13 (14 Jul) | B171: 46217 | C171: =COUNTIF(E5:E154,"Wk 13 (14 Jul)") -> 2 | D171: =SUMPRODUCT((E5:E154="Wk 13 (14 Jul)")*(G5:G154="Cash")*(F5:F154)) -> 1200 | E171: =SUMPRODUCT((E5:E154="Wk 13 (14 Jul)")*((G5:G154="MTN MoMo")+(G5:G154="Vodafone Cash")+(G5:G154="AirtelTigo Money"))*(F5:F154)) -> 1200 | F171: =SUMPRODUCT((E5:E154="Wk 13 (14 Jul)")*(G5:G154="Bank Transfer")*(F5:F154)) -> 0 | G171: =SUMPRODUCT((E5:E154="Wk 13 (14 Jul)")*(G5:G154="Cheque")*(F5:F154)) -> 0 | H171: =SUM(D171:G171) -> 2400 | I171: =I170+H171 -> 13850 | J171: PAST DEADLINE
A172: Wk 14 (21 Jul) | B172: 46224 | C172: =COUNTIF(E5:E154,"Wk 14 (21 Jul)") -> 1 | D172: =SUMPRODUCT((E5:E154="Wk 14 (21 Jul)")*(G5:G154="Cash")*(F5:F154)) -> 900 | E172: =SUMPRODUCT((E5:E154="Wk 14 (21 Jul)")*((G5:G154="MTN MoMo")+(G5:G154="Vodafone Cash")+(G5:G154="AirtelTigo Money"))*(F5:F154)) -> 0 | F172: =SUMPRODUCT((E5:E154="Wk 14 (21 Jul)")*(G5:G154="Bank Transfer")*(F5:F154)) -> 0 | G172: =SUMPRODUCT((E5:E154="Wk 14 (21 Jul)")*(G5:G154="Cheque")*(F5:F154)) -> 0 | H172: =SUM(D172:G172) -> 900 | I172: =I171+H172 -> 14750 | J172: PAST DEADLINE
A173: TERM 3 TOTAL | C173: =SUM(C159:C172) -> 11 | D173: =SUM(D159:D172) -> 9350 | E173: =SUM(E159:E172) -> 5400 | F173: =SUM(F159:F172) -> 0 | G173: =SUM(G159:G172) -> 0 | H173: =SUM(H159:H172) -> 14750
A176: MONTHLY COLLECTION SUMMARY
A177: Month | B177: No. of Payments | C177: Cash | D177: MoMo (All) | E177: Bank Transfer | F177: Cheque | G177: Month Total | H177: Cumulative | I177: Target % | J177: Actual % | K177: Notes
A178: Apr | B178: =SUMPRODUCT((MONTH(A5:A154)=4)*(A5:A154<>"")) -> #VALUE! | C178: =SUMPRODUCT((MONTH(A5:A154)=4)*(G5:G154="Cash")*(F5:F154)) -> #VALUE! | D178: =SUMPRODUCT((MONTH(A5:A154)=4)*((G5:G154="MTN MoMo")+(G5:G154="Vodafone Cash")+(G5:G154="AirtelTigo Money"))*(F5:F154)) -> #VALUE! | E178: =SUMPRODUCT((MONTH(A5:A154)=4)*(G5:G154="Bank Transfer")*(F5:F154)) -> #VALUE! | F178: =SUMPRODUCT((MONTH(A5:A154)=4)*(G5:G154="Cheque")*(F5:F154)) -> #VALUE! | G178: =SUM(C178:F178) -> #VALUE! | H178: =G178 -> #VALUE! | I178: 0.3
A179: May | B179: =SUMPRODUCT((MONTH(A5:A154)=5)*(A5:A154<>"")) -> #VALUE! | C179: =SUMPRODUCT((MONTH(A5:A154)=5)*(G5:G154="Cash")*(F5:F154)) -> #VALUE! | D179: =SUMPRODUCT((MONTH(A5:A154)=5)*((G5:G154="MTN MoMo")+(G5:G154="Vodafone Cash")+(G5:G154="AirtelTigo Money"))*(F5:F154)) -> #VALUE! | E179: =SUMPRODUCT((MONTH(A5:A154)=5)*(G5:G154="Bank Transfer")*(F5:F154)) -> #VALUE! | F179: =SUMPRODUCT((MONTH(A5:A154)=5)*(G5:G154="Cheque")*(F5:F154)) -> #VALUE! | G179: =SUM(C179:F179) -> #VALUE! | H179: =H178+G179 -> #VALUE! | I179: 0.65
A180: Jun | B180: =SUMPRODUCT((MONTH(A5:A154)=6)*(A5:A154<>"")) -> #VALUE! | C180: =SUMPRODUCT((MONTH(A5:A154)=6)*(G5:G154="Cash")*(F5:F154)) -> #VALUE! | D180: =SUMPRODUCT((MONTH(A5:A154)=6)*((G5:G154="MTN MoMo")+(G5:G154="Vodafone Cash")+(G5:G154="AirtelTigo Money"))*(F5:F154)) -> #VALUE! | E180: =SUMPRODUCT((MONTH(A5:A154)=6)*(G5:G154="Bank Transfer")*(F5:F154)) -> #VALUE! | F180: =SUMPRODUCT((MONTH(A5:A154)=6)*(G5:G154="Cheque")*(F5:F154)) -> #VALUE! | G180: =SUM(C180:F180) -> #VALUE! | H180: =H179+G180 -> #VALUE! | I180: 1
A181: Jul | B181: =SUMPRODUCT((MONTH(A5:A154)=7)*(A5:A154<>"")) -> #VALUE! | C181: =SUMPRODUCT((MONTH(A5:A154)=7)*(G5:G154="Cash")*(F5:F154)) -> #VALUE! | D181: =SUMPRODUCT((MONTH(A5:A154)=7)*((G5:G154="MTN MoMo")+(G5:G154="Vodafone Cash")+(G5:G154="AirtelTigo Money"))*(F5:F154)) -> #VALUE! | E181: =SUMPRODUCT((MONTH(A5:A154)=7)*(G5:G154="Bank Transfer")*(F5:F154)) -> #VALUE! | F181: =SUMPRODUCT((MONTH(A5:A154)=7)*(G5:G154="Cheque")*(F5:F154)) -> #VALUE! | G181: =SUM(C181:F181) -> #VALUE! | H181: =H180+G181 -> #VALUE! | I181: 1
A182: TOTAL | B182: =SUM(B178:B181) -> #VALUE! | C182: =SUM(C178:C181) -> #VALUE! | D182: =SUM(D178:D181) -> #VALUE! | E182: =SUM(E178:E181) -> #VALUE! | F182: =SUM(F178:F181) -> #VALUE! | G182: =SUM(G178:G181) -> #VALUE!

Sheet Grade 3 - Woodpeckers
A1: Grade 3: Woodpeckers — Skilful | Adaptability | Annual: GHS 8,500 | Termly: GHS 3,000
A3: PUPIL DETAILS | D3: TERM 1 (COMPLETED) | H3: TERM 2 (COMPLETED) | M3: TERM 3 (ACTIVE — arrears from T1/T2 included) | Q3: NOTES
A4: No. | B4: Pupil Name | C4: Discount Type | D4: T1 Fee | E4: T1 Arrears BF | F4: T1 Paid | G4: T1 Balance | H4: T2 Fee | I4: T2 Arrears BF | J4: T2 Discount | K4: T2 Paid | L4: T2 Balance | M4: T3 Fee | N4: T3 Discount | O4: T3 Paid | P4: T3 Balance | Q4: Remarks / Waiver Notes
A5: 1 | B5: Adjei-Djeton Jayden | C5: Staff Child | D5: 1300 | F5: 1300 | G5: =IF(B5="","",IF(D5="",0,D5)+IF(E5="",0,E5)-IF(F5="",0,F5)) -> 0 | H5: 3000 | J5: 3000 | L5: =IF(B5="","",IF(H5="",0,H5)+IF(I5="",0,I5)-IF(J5="",0,J5)-IF(K5="",0,K5)) -> 0 | M5: 3000 | N5: 3000 | O5: =SUMIF('Grade 3 - Payments'!C5:C154,B5,'Grade 3 - Payments'!F5:F154) -> 0 | P5: =IF(B5="","",IF(M5="",0,M5)-IF(N5="",0,N5)+IF(L5<0,0,IF(L5="",0,L5))-IF(O5="",0,O5)) -> 0 | Q5: Staff child — fees fully covered
A6: 2 | B6: Akrofi-Quarcoo Jesse Papa Kwesi | C6: Sibling | D6: 3050 | F6: 3050 | G6: =IF(B6="","",IF(D6="",0,D6)+IF(E6="",0,E6)-IF(F6="",0,F6)) -> 0 | H6: 3000 | J6: 150 | K6: 2850 | L6: =IF(B6="","",IF(H6="",0,H6)+IF(I6="",0,I6)-IF(J6="",0,J6)-IF(K6="",0,K6)) -> 0 | M6: 3000 | N6: 150 | O6: 1500 | P6: =IF(B6="","",IF(M6="",0,M6)-IF(N6="",0,N6)+IF(L6<0,0,IF(L6="",0,L6))-IF(O6="",0,O6)) -> 1350
A7: 3 | B7: Ampofo Yirenkyi Papa Kofi | E7: 1650 | G7: =IF(B7="","",IF(D7="",0,D7)+IF(E7="",0,E7)-IF(F7="",0,F7)) -> 1650 | I7: 1650 | L7: =IF(B7="","",IF(H7="",0,H7)+IF(I7="",0,I7)-IF(J7="",0,J7)-IF(K7="",0,K7)) -> 1650 | O7: =SUMIF('Grade 3 - Payments'!C5:C154,B7,'Grade 3 - Payments'!F5:F154) -> 0 | P7: =IF(B7="","",IF(M7="",0,M7)-IF(N7="",0,N7)+IF(L7<0,0,IF(L7="",0,L7))-IF(O7="",0,O7)) -> 1650 | Q7: Prior year BF GHS 1,650; no fees charged T1/T2 — arrears only
A8: 4 | B8: Azasoo Jayden-Elyon Elikem | D8: 3500 | F8: 700 | G8: =IF(B8="","",IF(D8="",0,D8)+IF(E8="",0,E8)-IF(F8="",0,F8)) -> 2800 | H8: 3500 | I8: 800 | L8: =IF(B8="","",IF(H8="",0,H8)+IF(I8="",0,I8)-IF(J8="",0,J8)-IF(K8="",0,K8)) -> 4300 | M8: 3000 | O8: =SUMIF('Grade 3 - Payments'!C5:C154,B8,'Grade 3 - Payments'!F5:F154) -> 2000 | P8: =IF(B8="","",IF(M8="",0,M8)-IF(N8="",0,N8)+IF(L8<0,0,IF(L8="",0,L8))-IF(O8="",0,O8)) -> 5300 | Q8: T1 paid GHS 700 of 3,500; zero T2 payment — GHS 4,300 arrears
A9: 5 | B9: Mensah-Aborampah Ayeyi Yeboah | D9: 3200 | F9: 1600 | G9: =IF(B9="","",IF(D9="",0,D9)+IF(E9="",0,E9)-IF(F9="",0,F9)) -> 1600 | H9: 3000 | I9: 600 | K9: 2500 | L9: 1352.5 | M9: 3000 | O9: 2800 | P9: =IF(B9="","",IF(M9="",0,M9)-IF(N9="",0,N9)+IF(L9<0,0,IF(L9="",0,L9))-IF(O9="",0,O9)) -> 1552.5 | Q9: Consistent partial payer; T2 balance GHS 1,100
A10: 6 | B10: Owusu Katakyie Nana Kwame | C10: Sibling | D10: 3050 | E10: 3140 | F10: 3600 | G10: =IF(B10="","",IF(D10="",0,D10)+IF(E10="",0,E10)-IF(F10="",0,F10)) -> 2590 | I10: 2420 | J10: 150 | L10: =IF(B10="","",IF(H10="",0,H10)+IF(I10="",0,I10)-IF(J10="",0,J10)-IF(K10="",0,K10)) -> 2270 | O10: =SUMIF('Grade 3 - Payments'!C5:C154,B10,'Grade 3 - Payments'!F5:F154) -> 750 | P10: =IF(B10="","",IF(M10="",0,M10)-IF(N10="",0,N10)+IF(L10<0,0,IF(L10="",0,L10))-IF(O10="",0,O10)) -> 1520 | Q10: Sibling — prior year BF GHS 3,140; T2 balance GHS 2,270
A11: 7 | G11: =IF(B11="","",0) | L11: =IF(B11="","",0) | P11: =IF(B11="","",0)
A12: 8 | G12: =IF(B12="","",0) | L12: =IF(B12="","",0) | P12: =IF(B12="","",0)
A13: 9 | G13: =IF(B13="","",0) | L13: =IF(B13="","",0) | P13: =IF(B13="","",0)
A14: 10 | G14: =IF(B14="","",0) | L14: =IF(B14="","",0) | P14: =IF(B14="","",0)
A15: 11 | G15: =IF(B15="","",0) | L15: =IF(B15="","",0) | P15: =IF(B15="","",0)
A16: 12 | G16: =IF(B16="","",0) | L16: =IF(B16="","",0) | P16: =IF(B16="","",0)
A17: 13 | G17: =IF(B17="","",0) | L17: =IF(B17="","",0) | P17: =IF(B17="","",0)
A18: 14 | G18: =IF(B18="","",0) | L18: =IF(B18="","",0) | P18: =IF(B18="","",0)
A19: 15 | G19: =IF(B19="","",0) | L19: =IF(B19="","",0) | P19: =IF(B19="","",0)
A20: 16 | G20: =IF(B20="","",0) | L20: =IF(B20="","",0) | P20: =IF(B20="","",0)
B21: TOTALS | D21: =SUM(D5:D20) -> 14100 | E21: =SUM(E5:E20) -> 4790 | F21: =SUM(F5:F20) -> 10250 | G21: =SUM(G5:G20) -> 8640 | H21: =SUM(H5:H20) -> 12500 | I21: =SUM(I5:I20) -> 5470 | J21: =SUM(J5:J20) -> 3300 | K21: =SUM(K5:K20) -> 5350 | ... P21: =SUM(P5:P20) -> 11372.5
B22: Collection Rate: | F22: T1: | G22: =IF(D21+E21=0,1,F21/(D21+E21)) -> 0.54261514 | K22: T2: | L22: =IF(H21+I21-J21=0,1,K21/(H21+I21-J21)) -> 0.36468984 | O22: =SUMIF('Grade 3 - Payments'!C5:C154,B22,'Grade 3 - Payments'!F5:F154) -> 0

Sheet Grade 3 - Payments
A1: Grade 3: Woodpeckers — PAYMENT RECEIPTS LOG (Term 3, 2025/26: 21 Apr – 24 Jul 2026) | P1: Adjei-Djeton Jayden
A2: Payment deadline: 30 June 2026 | Enter one row per payment | T3 Paid on class register auto-updates via SUMIFS | P2: Akrofi-Quarcoo Jesse P.K.
A3: TRANSACTION DETAILS | G3: PAYMENT | J3: VERIFICATION | P3: Ampofo Yirenkyi Papa Kofi
A4: Date | B4: Receipt No. | C4: Pupil Name | D4: Term | E4: Week | F4: Amount (GHS) | G4: Payment Method | H4: Received By | I4: Running Total | J4: Verified | K4: Notes | P4: Azasoo Jayden-Elyon Elikem
A5: 46132 | B5: 1042 | C5: Akrofi-Quarcoo Jesse P.K. | D5: Term 3 | E5: Wk 1 (21 Apr) | F5: 1500 | G5: Bank Transfer | H5: Dorcas Matilda Akosua Kusi | I5: =IF(F5="","",F5) -> 1500 | P5: Mensah-Aborampah Ayeyi Y.
A6: 46154 | B6: 1069 | C6: Azasoo Jayden-Elyon Elikem | D6: Term 3 | E6: Wk 4 (12 May) | F6: 2000 | G6: MTN MoMo | H6: Dorcas Matilda Akosua Kusi | I6: =IF(F6="","",IF(I5="",F6,I5+F6)) -> 3500 | P6: Owusu Katakyie Nana Kwame
A7: 46155 | B7: 1070 | C7: Mensah-Aborampah Ayeyi Y. | D7: Term 2 Arrears | E7: Wk 4 (12 May) | F7: 900 | G7: MTN MoMo | H7: Dorcas Matilda Akosua Kusi | I7: =IF(F7="","",IF(I6="",F7,I6+F7)) -> 4400
A8: 46108 | B8: 1021 | C8: Owusu Katakyie Nana Kwame | D8: Term 1 Arrears | E8: March | F8: 500 | G8: Cash | H8: Dorcas Matilda Akosua Kusi | I8: =IF(F8="","",IF(I7="",F8,I7+F8)) -> 4900
A9: 46163 | B9: 1082 | C9: Akrofi-Quarcoo Jesse P.K. | D9: Term 3 | E9: Wk 5 (19 May) | F9: 1550 | G9: Bank Transfer | H9: Dorcas Matilda Akosua Kusi | I9: =IF(F9="","",IF(I8="",F9,I8+F9)) -> 6450
A10: 46177 | B10: 1108 | C10: Owusu Katakyie Nana Kwame | D10: Term 1 Arrears | E10: Wk 7 (02 Jun) | F10: 250 | G10: MTN MoMo | H10: Dorcas Matilda Akosua Kusi | I10: =IF(F10="","",IF(I9="",F10,I9+F10)) -> 6700
A11: 46185 | B11: 1113 | C11: Mensah-Aborampah Ayeyi Y. | D11: Term 3 | E11: Wk 8 (09 Jun) | F11: 900 | G11: MTN MoMo | H11: Other | I11: =IF(F11="","",IF(I10="",F11,I10+F11)) -> 7600
A12: 14/07/2026 | B12: 1137 | C12: Mensah-Aborampah Ayeyi Y. | D12: Term 3 | E12: Wk 13 (14 Jul) | F12: 1000 | G12: MTN MoMo | H12: Dorcas Matilda Akosua Kusi | I12: =IF(F12="","",IF(I11="",F12,I11+F12)) -> 8600
I13: =IF(F13="","",IF(I12="",F13,I12+F13))
I14: =IF(F14="","",IF(I13="",F14,I13+F14))
I15: =IF(F15="","",IF(I14="",F15,I14+F15))
I16: =IF(F16="","",IF(I15="",F16,I15+F16))
I17: =IF(F17="","",IF(I16="",F17,I16+F17))
I18: =IF(F18="","",IF(I17="",F18,I17+F18))
I19: =IF(F19="","",IF(I18="",F19,I18+F19))
I20: =IF(F20="","",IF(I19="",F20,I19+F20))
I21: =IF(F21="","",IF(I20="",F21,I20+F21))
I22: =IF(F22="","",IF(I21="",F22,I21+F22))
I23: =IF(F23="","",IF(I22="",F23,I22+F23))
I24: =IF(F24="","",IF(I23="",F24,I23+F24))
... I154: =IF(F154="","",IF(I153="",F154,I153+F154))
A157: WEEKLY COLLECTION SUMMARY (auto-calculated from payment log)
A158: Week | B158: Week Starting | C158: Entries | D158: Cash | E158: MoMo (All) | F158: Bank Transfer | G158: Cheque | H158: Week Total | I158: Cumulative | J158: vs Deadline | K158: Notes
A159: Wk 1 (21 Apr) | B159: 46133 | C159: =COUNTIF(E5:E154,"Wk 1 (21 Apr)") -> 1 | D159: =SUMPRODUCT((E5:E154="Wk 1 (21 Apr)")*(G5:G154="Cash")*(F5:F154)) -> 0 | E159: =SUMPRODUCT((E5:E154="Wk 1 (21 Apr)")*((G5:G154="MTN MoMo")+(G5:G154="Vodafone Cash")+(G5:G154="AirtelTigo Money"))*(F5:F154)) -> 0 | F159: =SUMPRODUCT((E5:E154="Wk 1 (21 Apr)")*(G5:G154="Bank Transfer")*(F5:F154)) -> 1500 | G159: =SUMPRODUCT((E5:E154="Wk 1 (21 Apr)")*(G5:G154="Cheque")*(F5:F154)) -> 0 | H159: =SUM(D159:G159) -> 1500 | I159: =H159 -> 1500
A160: Wk 2 (28 Apr) | B160: 46140 | C160: =COUNTIF(E5:E154,"Wk 2 (28 Apr)") -> 0 | D160: =SUMPRODUCT((E5:E154="Wk 2 (28 Apr)")*(G5:G154="Cash")*(F5:F154)) -> 0 | E160: =SUMPRODUCT((E5:E154="Wk 2 (28 Apr)")*((G5:G154="MTN MoMo")+(G5:G154="Vodafone Cash")+(G5:G154="AirtelTigo Money"))*(F5:F154)) -> 0 | F160: =SUMPRODUCT((E5:E154="Wk 2 (28 Apr)")*(G5:G154="Bank Transfer")*(F5:F154)) -> 0 | G160: =SUMPRODUCT((E5:E154="Wk 2 (28 Apr)")*(G5:G154="Cheque")*(F5:F154)) -> 0 | H160: =SUM(D160:G160) -> 0 | I160: =I159+H160 -> 1500
A161: Wk 3 (05 May) | B161: 46147 | C161: =COUNTIF(E5:E154,"Wk 3 (05 May)") -> 0 | D161: =SUMPRODUCT((E5:E154="Wk 3 (05 May)")*(G5:G154="Cash")*(F5:F154)) -> 0 | E161: =SUMPRODUCT((E5:E154="Wk 3 (05 May)")*((G5:G154="MTN MoMo")+(G5:G154="Vodafone Cash")+(G5:G154="AirtelTigo Money"))*(F5:F154)) -> 0 | F161: =SUMPRODUCT((E5:E154="Wk 3 (05 May)")*(G5:G154="Bank Transfer")*(F5:F154)) -> 0 | G161: =SUMPRODUCT((E5:E154="Wk 3 (05 May)")*(G5:G154="Cheque")*(F5:F154)) -> 0 | H161: =SUM(D161:G161) -> 0 | I161: =I160+H161 -> 1500
A162: Wk 4 (12 May) | B162: 46154 | C162: =COUNTIF(E5:E154,"Wk 4 (12 May)") -> 2 | D162: =SUMPRODUCT((E5:E154="Wk 4 (12 May)")*(G5:G154="Cash")*(F5:F154)) -> 0 | E162: =SUMPRODUCT((E5:E154="Wk 4 (12 May)")*((G5:G154="MTN MoMo")+(G5:G154="Vodafone Cash")+(G5:G154="AirtelTigo Money"))*(F5:F154)) -> 2900 | F162: =SUMPRODUCT((E5:E154="Wk 4 (12 May)")*(G5:G154="Bank Transfer")*(F5:F154)) -> 0 | G162: =SUMPRODUCT((E5:E154="Wk 4 (12 May)")*(G5:G154="Cheque")*(F5:F154)) -> 0 | H162: =SUM(D162:G162) -> 2900 | I162: =I161+H162 -> 4400
A163: Wk 5 (19 May) | B163: 46161 | C163: =COUNTIF(E5:E154,"Wk 5 (19 May)") -> 1 | D163: =SUMPRODUCT((E5:E154="Wk 5 (19 May)")*(G5:G154="Cash")*(F5:F154)) -> 0 | E163: =SUMPRODUCT((E5:E154="Wk 5 (19 May)")*((G5:G154="MTN MoMo")+(G5:G154="Vodafone Cash")+(G5:G154="AirtelTigo Money"))*(F5:F154)) -> 0 | F163: =SUMPRODUCT((E5:E154="Wk 5 (19 May)")*(G5:G154="Bank Transfer")*(F5:F154)) -> 1550 | G163: =SUMPRODUCT((E5:E154="Wk 5 (19 May)")*(G5:G154="Cheque")*(F5:F154)) -> 0 | H163: =SUM(D163:G163) -> 1550 | I163: =I162+H163 -> 5950
A164: Wk 6 (26 May) | B164: 46168 | C164: =COUNTIF(E5:E154,"Wk 6 (26 May)") -> 0 | D164: =SUMPRODUCT((E5:E154="Wk 6 (26 May)")*(G5:G154="Cash")*(F5:F154)) -> 0 | E164: =SUMPRODUCT((E5:E154="Wk 6 (26 May)")*((G5:G154="MTN MoMo")+(G5:G154="Vodafone Cash")+(G5:G154="AirtelTigo Money"))*(F5:F154)) -> 0 | F164: =SUMPRODUCT((E5:E154="Wk 6 (26 May)")*(G5:G154="Bank Transfer")*(F5:F154)) -> 0 | G164: =SUMPRODUCT((E5:E154="Wk 6 (26 May)")*(G5:G154="Cheque")*(F5:F154)) -> 0 | H164: =SUM(D164:G164) -> 0 | I164: =I163+H164 -> 5950
A165: Wk 7 (02 Jun) | B165: 46175 | C165: =COUNTIF(E5:E154,"Wk 7 (02 Jun)") -> 1 | D165: =SUMPRODUCT((E5:E154="Wk 7 (02 Jun)")*(G5:G154="Cash")*(F5:F154)) -> 0 | E165: =SUMPRODUCT((E5:E154="Wk 7 (02 Jun)")*((G5:G154="MTN MoMo")+(G5:G154="Vodafone Cash")+(G5:G154="AirtelTigo Money"))*(F5:F154)) -> 250 | F165: =SUMPRODUCT((E5:E154="Wk 7 (02 Jun)")*(G5:G154="Bank Transfer")*(F5:F154)) -> 0 | G165: =SUMPRODUCT((E5:E154="Wk 7 (02 Jun)")*(G5:G154="Cheque")*(F5:F154)) -> 0 | H165: =SUM(D165:G165) -> 250 | I165: =I164+H165 -> 6200
A166: Wk 8 (09 Jun) | B166: 46182 | C166: =COUNTIF(E5:E154,"Wk 8 (09 Jun)") -> 1 | D166: =SUMPRODUCT((E5:E154="Wk 8 (09 Jun)")*(G5:G154="Cash")*(F5:F154)) -> 0 | E166: =SUMPRODUCT((E5:E154="Wk 8 (09 Jun)")*((G5:G154="MTN MoMo")+(G5:G154="Vodafone Cash")+(G5:G154="AirtelTigo Money"))*(F5:F154)) -> 900 | F166: =SUMPRODUCT((E5:E154="Wk 8 (09 Jun)")*(G5:G154="Bank Transfer")*(F5:F154)) -> 0 | G166: =SUMPRODUCT((E5:E154="Wk 8 (09 Jun)")*(G5:G154="Cheque")*(F5:F154)) -> 0 | H166: =SUM(D166:G166) -> 900 | I166: =I165+H166 -> 7100
A167: Wk 9 (16 Jun) | B167: 46189 | C167: =COUNTIF(E5:E154,"Wk 9 (16 Jun)") -> 0 | D167: =SUMPRODUCT((E5:E154="Wk 9 (16 Jun)")*(G5:G154="Cash")*(F5:F154)) -> 0 | E167: =SUMPRODUCT((E5:E154="Wk 9 (16 Jun)")*((G5:G154="MTN MoMo")+(G5:G154="Vodafone Cash")+(G5:G154="AirtelTigo Money"))*(F5:F154)) -> 0 | F167: =SUMPRODUCT((E5:E154="Wk 9 (16 Jun)")*(G5:G154="Bank Transfer")*(F5:F154)) -> 0 | G167: =SUMPRODUCT((E5:E154="Wk 9 (16 Jun)")*(G5:G154="Cheque")*(F5:F154)) -> 0 | H167: =SUM(D167:G167) -> 0 | I167: =I166+H167 -> 7100
A168: Wk 10 (23 Jun) | B168: 46196 | C168: =COUNTIF(E5:E154,"Wk 10 (23 Jun)") -> 0 | D168: =SUMPRODUCT((E5:E154="Wk 10 (23 Jun)")*(G5:G154="Cash")*(F5:F154)) -> 0 | E168: =SUMPRODUCT((E5:E154="Wk 10 (23 Jun)")*((G5:G154="MTN MoMo")+(G5:G154="Vodafone Cash")+(G5:G154="AirtelTigo Money"))*(F5:F154)) -> 0 | F168: =SUMPRODUCT((E5:E154="Wk 10 (23 Jun)")*(G5:G154="Bank Transfer")*(F5:F154)) -> 0 | G168: =SUMPRODUCT((E5:E154="Wk 10 (23 Jun)")*(G5:G154="Cheque")*(F5:F154)) -> 0 | H168: =SUM(D168:G168) -> 0 | I168: =I167+H168 -> 7100
A169: Wk 11 (30 Jun) | B169: 46203 | C169: =COUNTIF(E5:E154,"Wk 11 (30 Jun)") -> 0 | D169: =SUMPRODUCT((E5:E154="Wk 11 (30 Jun)")*(G5:G154="Cash")*(F5:F154)) -> 0 | E169: =SUMPRODUCT((E5:E154="Wk 11 (30 Jun)")*((G5:G154="MTN MoMo")+(G5:G154="Vodafone Cash")+(G5:G154="AirtelTigo Money"))*(F5:F154)) -> 0 | F169: =SUMPRODUCT((E5:E154="Wk 11 (30 Jun)")*(G5:G154="Bank Transfer")*(F5:F154)) -> 0 | G169: =SUMPRODUCT((E5:E154="Wk 11 (30 Jun)")*(G5:G154="Cheque")*(F5:F154)) -> 0 | H169: =SUM(D169:G169) -> 0 | I169: =I168+H169 -> 7100
A170: Wk 12 (07 Jul) | B170: 46210 | C170: =COUNTIF(E5:E154,"Wk 12 (07 Jul)") -> 0 | D170: =SUMPRODUCT((E5:E154="Wk 12 (07 Jul)")*(G5:G154="Cash")*(F5:F154)) -> 0 | E170: =SUMPRODUCT((E5:E154="Wk 12 (07 Jul)")*((G5:G154="MTN MoMo")+(G5:G154="Vodafone Cash")+(G5:G154="AirtelTigo Money"))*(F5:F154)) -> 0 | F170: =SUMPRODUCT((E5:E154="Wk 12 (07 Jul)")*(G5:G154="Bank Transfer")*(F5:F154)) -> 0 | G170: =SUMPRODUCT((E5:E154="Wk 12 (07 Jul)")*(G5:G154="Cheque")*(F5:F154)) -> 0 | H170: =SUM(D170:G170) -> 0 | I170: =I169+H170 -> 7100 | J170: PAST DEADLINE
A171: Wk 13 (14 Jul) | B171: 46217 | C171: =COUNTIF(E5:E154,"Wk 13 (14 Jul)") -> 1 | D171: =SUMPRODUCT((E5:E154="Wk 13 (14 Jul)")*(G5:G154="Cash")*(F5:F154)) -> 0 | E171: =SUMPRODUCT((E5:E154="Wk 13 (14 Jul)")*((G5:G154="MTN MoMo")+(G5:G154="Vodafone Cash")+(G5:G154="AirtelTigo Money"))*(F5:F154)) -> 1000 | F171: =SUMPRODUCT((E5:E154="Wk 13 (14 Jul)")*(G5:G154="Bank Transfer")*(F5:F154)) -> 0 | G171: =SUMPRODUCT((E5:E154="Wk 13 (14 Jul)")*(G5:G154="Cheque")*(F5:F154)) -> 0 | H171: =SUM(D171:G171) -> 1000 | I171: =I170+H171 -> 8100 | J171: PAST DEADLINE
A172: Wk 14 (21 Jul) | B172: 46224 | C172: =COUNTIF(E5:E154,"Wk 14 (21 Jul)") -> 0 | D172: =SUMPRODUCT((E5:E154="Wk 14 (21 Jul)")*(G5:G154="Cash")*(F5:F154)) -> 0 | E172: =SUMPRODUCT((E5:E154="Wk 14 (21 Jul)")*((G5:G154="MTN MoMo")+(G5:G154="Vodafone Cash")+(G5:G154="AirtelTigo Money"))*(F5:F154)) -> 0 | F172: =SUMPRODUCT((E5:E154="Wk 14 (21 Jul)")*(G5:G154="Bank Transfer")*(F5:F154)) -> 0 | G172: =SUMPRODUCT((E5:E154="Wk 14 (21 Jul)")*(G5:G154="Cheque")*(F5:F154)) -> 0 | H172: =SUM(D172:G172) -> 0 | I172: =I171+H172 -> 8100 | J172: PAST DEADLINE
A173: TERM 3 TOTAL | C173: =SUM(C159:C172) -> 7 | D173: =SUM(D159:D172) -> 0 | E173: =SUM(E159:E172) -> 5050 | F173: =SUM(F159:F172) -> 3050 | G173: =SUM(G159:G172) -> 0 | H173: =SUM(H159:H172) -> 8100
A176: MONTHLY COLLECTION SUMMARY
A177: Month | B177: No. of Payments | C177: Cash | D177: MoMo (All) | E177: Bank Transfer | F177: Cheque | G177: Month Total | H177: Cumulative | I177: Target % | J177: Actual % | K177: Notes
A178: Apr | B178: =SUMPRODUCT((MONTH(A5:A154)=4)*(A5:A154<>"")) -> 1 | C178: =SUMPRODUCT((MONTH(A5:A154)=4)*(G5:G154="Cash")*(F5:F154)) -> 0 | D178: =SUMPRODUCT((MONTH(A5:A154)=4)*((G5:G154="MTN MoMo")+(G5:G154="Vodafone Cash")+(G5:G154="AirtelTigo Money"))*(F5:F154)) -> 0 | E178: =SUMPRODUCT((MONTH(A5:A154)=4)*(G5:G154="Bank Transfer")*(F5:F154)) -> 1500 | F178: =SUMPRODUCT((MONTH(A5:A154)=4)*(G5:G154="Cheque")*(F5:F154)) -> 0 | G178: =SUM(C178:F178) -> 1500 | H178: =G178 -> 1500 | I178: 0.3
A179: May | B179: =SUMPRODUCT((MONTH(A5:A154)=5)*(A5:A154<>"")) -> 3 | C179: =SUMPRODUCT((MONTH(A5:A154)=5)*(G5:G154="Cash")*(F5:F154)) -> 0 | D179: =SUMPRODUCT((MONTH(A5:A154)=5)*((G5:G154="MTN MoMo")+(G5:G154="Vodafone Cash")+(G5:G154="AirtelTigo Money"))*(F5:F154)) -> 2900 | E179: =SUMPRODUCT((MONTH(A5:A154)=5)*(G5:G154="Bank Transfer")*(F5:F154)) -> 1550 | F179: =SUMPRODUCT((MONTH(A5:A154)=5)*(G5:G154="Cheque")*(F5:F154)) -> 0 | G179: =SUM(C179:F179) -> 4450 | H179: =H178+G179 -> 5950 | I179: 0.65
A180: Jun | B180: =SUMPRODUCT((MONTH(A5:A154)=6)*(A5:A154<>"")) -> 2 | C180: =SUMPRODUCT((MONTH(A5:A154)=6)*(G5:G154="Cash")*(F5:F154)) -> 0 | D180: =SUMPRODUCT((MONTH(A5:A154)=6)*((G5:G154="MTN MoMo")+(G5:G154="Vodafone Cash")+(G5:G154="AirtelTigo Money"))*(F5:F154)) -> 1150 | E180: =SUMPRODUCT((MONTH(A5:A154)=6)*(G5:G154="Bank Transfer")*(F5:F154)) -> 0 | F180: =SUMPRODUCT((MONTH(A5:A154)=6)*(G5:G154="Cheque")*(F5:F154)) -> 0 | G180: =SUM(C180:F180) -> 1150 | H180: =H179+G180 -> 7100 | I180: 1
A181: Jul | B181: =SUMPRODUCT((MONTH(A5:A154)=7)*(A5:A154<>"")) -> 1 | C181: =SUMPRODUCT((MONTH(A5:A154)=7)*(G5:G154="Cash")*(F5:F154)) -> 0 | D181: =SUMPRODUCT((MONTH(A5:A154)=7)*((G5:G154="MTN MoMo")+(G5:G154="Vodafone Cash")+(G5:G154="AirtelTigo Money"))*(F5:F154)) -> 1000 | E181: =SUMPRODUCT((MONTH(A5:A154)=7)*(G5:G154="Bank Transfer")*(F5:F154)) -> 0 | F181: =SUMPRODUCT((MONTH(A5:A154)=7)*(G5:G154="Cheque")*(F5:F154)) -> 0 | G181: =SUM(C181:F181) -> 1000 | H181: =H180+G181 -> 8100 | I181: 1
A182: TOTAL | B182: =SUM(B178:B181) -> 7 | C182: =SUM(C178:C181) -> 0 | D182: =SUM(D178:D181) -> 5050 | E182: =SUM(E178:E181) -> 3050 | F182: =SUM(F178:F181) -> 0 | G182: =SUM(G178:G181) -> 8100

Sheet Grade 4 - Nightingales
A1: Grade 4: Nightingales — Talented | Exceptional | Annual: GHS 8,500 | Termly: GHS 3,000
A3: PUPIL DETAILS | D3: TERM 1 (COMPLETED) | H3: TERM 2 (COMPLETED) | M3: TERM 3 (ACTIVE — arrears from T1/T2 included) | Q3: NOTES
A4: No. | B4: Pupil Name | C4: Discount Type | D4: T1 Fee | E4: T1 Arrears BF | F4: T1 Paid | G4: T1 Balance | H4: T2 Fee | I4: T2 Arrears BF | J4: T2 Discount | K4: T2 Paid | L4: T2 Balance | M4: T3 Fee | N4: T3 Discount | O4: T3 Paid | P4: T3 Balance | Q4: Remarks / Waiver Notes
A5: 1 | B5: Djaba Larko Rhema | C5: Sibling | D5: 3050 | F5: 2516.67 | G5: =IF(B5="","",IF(D5="",0,D5)+IF(E5="",0,E5)-IF(F5="",0,F5)) -> 533.33 | H5: 3000 | J5: 150 | K5: 2850 | L5: =IF(B5="","",IF(H5="",0,H5)+IF(I5="",0,I5)-IF(J5="",0,J5)-IF(K5="",0,K5)) -> 0 | M5: 3000 | N5: 150 | O5: =SUMIF('Grade 4 - Payments'!C5:C154,B5,'Grade 4 - Payments'!F5:F154) -> 0 | P5: =IF(B5="","",IF(M5="",0,M5)-IF(N5="",0,N5)+IF(L5<0,0,IF(L5="",0,L5))-IF(O5="",0,O5)) -> 2850 | Q5: Sibling discount — T1 partial; T2 settled
A6: 2 | B6: Mortty Elikem Galen | D6: 3200 | F6: 3200 | G6: =IF(B6="","",IF(D6="",0,D6)+IF(E6="",0,E6)-IF(F6="",0,F6)) -> 0 | H6: 3000 | K6: 3000 | L6: =IF(B6="","",IF(H6="",0,H6)+IF(I6="",0,I6)-IF(J6="",0,J6)-IF(K6="",0,K6)) -> 0 | M6: 3000 | O6: =SUMIF('Grade 4 - Payments'!C5:C154,B6,'Grade 4 - Payments'!F5:F154) -> 3200 | P6: =IF(B6="","",IF(M6="",0,M6)-IF(N6="",0,N6)+IF(L6<0,0,IF(L6="",0,L6))-IF(O6="",0,O6)) -> -200
A7: 3 | B7: Monney Nana Aba Nyamekye | D7: 3200 | F7: 3200 | G7: =IF(B7="","",IF(D7="",0,D7)+IF(E7="",0,E7)-IF(F7="",0,F7)) -> 0 | H7: 3000 | K7: 3000 | L7: =IF(B7="","",IF(H7="",0,H7)+IF(I7="",0,I7)-IF(J7="",0,J7)-IF(K7="",0,K7)) -> 0 | M7: 3000 | O7: =SUMIF('Grade 4 - Payments'!C5:C154,B7,'Grade 4 - Payments'!F5:F154) -> 3200 | P7: =IF(B7="","",IF(M7="",0,M7)-IF(N7="",0,N7)+IF(L7<0,0,IF(L7="",0,L7))-IF(O7="",0,O7)) -> -200
A8: 4 | B8: Owusu Okyem Emmanuella | D8: 3200 | E8: 3050 | F8: 3650 | G8: =IF(B8="","",IF(D8="",0,D8)+IF(E8="",0,E8)-IF(F8="",0,F8)) -> 2600 | I8: 2420 | L8: =IF(B8="","",IF(H8="",0,H8)+IF(I8="",0,I8)-IF(J8="",0,J8)-IF(K8="",0,K8)) -> 2420 | M8: 0 | O8: =SUMIF('Grade 4 - Payments'!C5:C154,B8,'Grade 4 - Payments'!F5:F154) -> 750 | P8: =IF(B8="","",IF(M8="",0,M8)-IF(N8="",0,N8)+IF(L8<0,0,IF(L8="",0,L8))-IF(O8="",0,O8)) -> 1670 | Q8: Prior year BF GHS 3,050; no T2 fee charged — GHS 2,420 arrears
A9: 5 | G9: =IF(B9="","",0) | L9: =IF(B9="","",0) | P9: =IF(B9="","",0)
A10: 6 | G10: =IF(B10="","",0) | L10: =IF(B10="","",0) | P10: =IF(B10="","",0)
A11: 7 | G11: =IF(B11="","",0) | L11: =IF(B11="","",0) | P11: =IF(B11="","",0)
A12: 8 | G12: =IF(B12="","",0) | L12: =IF(B12="","",0) | P12: =IF(B12="","",0)
A13: 9 | G13: =IF(B13="","",0) | L13: =IF(B13="","",0) | P13: =IF(B13="","",0)
A14: 10 | G14: =IF(B14="","",0) | L14: =IF(B14="","",0) | P14: =IF(B14="","",0)
A15: 11 | G15: =IF(B15="","",0) | L15: =IF(B15="","",0) | P15: =IF(B15="","",0)
A16: 12 | G16: =IF(B16="","",0) | L16: =IF(B16="","",0) | P16: =IF(B16="","",0)
A17: 13 | G17: =IF(B17="","",0) | L17: =IF(B17="","",0) | P17: =IF(B17="","",0)
A18: 14 | G18: =IF(B18="","",0) | L18: =IF(B18="","",0) | P18: =IF(B18="","",0)
B19: TOTALS | D19: =SUM(D5:D18) -> 12650 | E19: =SUM(E5:E18) -> 3050 | F19: =SUM(F5:F18) -> 12566.67 | G19: =SUM(G5:G18) -> 3133.33 | H19: =SUM(H5:H18) -> 9000 | I19: =SUM(I5:I18) -> 2420 | J19: =SUM(J5:J18) -> 150 | K19: =SUM(K5:K18) -> 8850 | ... P19: =SUM(P5:P18) -> 4120
B20: Collection Rate: | F20: T1: | G20: =IF(D19+E19=0,1,F19/(D19+E19)) -> 0.80042484 | K20: T2: | L20: =IF(H19+I19-J19=0,1,K19/(H19+I19-J19)) -> 0.78527063 | O20: =SUMIF('Grade 4 - Payments'!C5:C154,B20,'Grade 4 - Payments'!F5:F154) -> 0

Sheet Grade 4 - Payments
A1: Grade 4: Nightingales — PAYMENT RECEIPTS LOG (Term 3, 2025/26: 21 Apr – 24 Jul 2026) | P1: Djaba Larko Rhema
A2: Payment deadline: 30 June 2026 | Enter one row per payment | T3 Paid on class register auto-updates via SUMIFS | P2: Mortty Elikem Galen
A3: TRANSACTION DETAILS | G3: PAYMENT | J3: VERIFICATION | P3: Monney Nana Aba Nyamekye
A4: Date | B4: Receipt No. | C4: Pupil Name | D4: Term | E4: Week | F4: Amount (GHS) | G4: Payment Method | H4: Received By | I4: Running Total | J4: Verified | K4: Notes | P4: Owusu Okyem Emmanuella
A5: 46156 | B5: 1072 | C5: Mortty Elikem Galen | D5: Term 3 | E5: Wk 4 (12 May) | F5: 3200 | G5: Cash | H5: Dorcas Matilda Akosua Kusi | I5: =IF(F5="","",F5) -> 3200
A6: 46142 | B6: 1077 | C6: Owusu Okyem Emmanuella | D6: Term 1 Arrears | E6: Wk 2 (28 Apr) | F6: 500 | G6: MTN MoMo | H6: Dorcas Matilda Akosua Kusi | I6: =IF(F6="","",IF(I5="",F6,I5+F6)) -> 3700
A7: 46136 | B7: 1098 | C7: Monney Nana Aba Nyamekye | D7: Term 3 | E7: Wk 1 (21 Apr) | F7: 1000 | G7: Bank Transfer | H7: Dorcas Matilda Akosua Kusi | I7: =IF(F7="","",IF(I6="",F7,I6+F7)) -> 4700
A8: 46167 | B8: 1101 | C8: Monney Nana Aba Nyamekye | D8: Term 3 | E8: Wk 6 (26 May) | F8: 2200 | G8: Bank Transfer | H8: Dorcas Matilda Akosua Kusi | I8: =IF(F8="","",IF(I7="",F8,I7+F8)) -> 6900
A9: 46177 | B9: 1108 | C9: Owusu Okyem Emmanuella | D9: Term 1 Arrears | E9: Wk 7 (02 Jun) | F9: 250 | G9: MTN MoMo | H9: Dorcas Matilda Akosua Kusi | I9: =IF(F9="","",IF(I8="",F9,I8+F9)) -> 7150
I10: =IF(F10="","",IF(I9="",F10,I9+F10))
I11: =IF(F11="","",IF(I10="",F11,I10+F11))
I12: =IF(F12="","",IF(I11="",F12,I11+F12))
I13: =IF(F13="","",IF(I12="",F13,I12+F13))
I14: =IF(F14="","",IF(I13="",F14,I13+F14))
I15: =IF(F15="","",IF(I14="",F15,I14+F15))
I16: =IF(F16="","",IF(I15="",F16,I15+F16))
I17: =IF(F17="","",IF(I16="",F17,I16+F17))
I18: =IF(F18="","",IF(I17="",F18,I17+F18))
I19: =IF(F19="","",IF(I18="",F19,I18+F19))
I20: =IF(F20="","",IF(I19="",F20,I19+F20))
I21: =IF(F21="","",IF(I20="",F21,I20+F21))
... I154: =IF(F154="","",IF(I153="",F154,I153+F154))
A157: WEEKLY COLLECTION SUMMARY (auto-calculated from payment log)
A158: Week | B158: Week Starting | C158: Entries | D158: Cash | E158: MoMo (All) | F158: Bank Transfer | G158: Cheque | H158: Week Total | I158: Cumulative | J158: vs Deadline | K158: Notes
A159: Wk 1 (21 Apr) | B159: 46133 | C159: =COUNTIF(E5:E154,"Wk 1 (21 Apr)") -> 1 | D159: =SUMPRODUCT((E5:E154="Wk 1 (21 Apr)")*(G5:G154="Cash")*(F5:F154)) -> 0 | E159: =SUMPRODUCT((E5:E154="Wk 1 (21 Apr)")*((G5:G154="MTN MoMo")+(G5:G154="Vodafone Cash")+(G5:G154="AirtelTigo Money"))*(F5:F154)) -> 0 | F159: =SUMPRODUCT((E5:E154="Wk 1 (21 Apr)")*(G5:G154="Bank Transfer")*(F5:F154)) -> 1000 | G159: =SUMPRODUCT((E5:E154="Wk 1 (21 Apr)")*(G5:G154="Cheque")*(F5:F154)) -> 0 | H159: =SUM(D159:G159) -> 1000 | I159: =H159 -> 1000
A160: Wk 2 (28 Apr) | B160: 46140 | C160: =COUNTIF(E5:E154,"Wk 2 (28 Apr)") -> 1 | D160: =SUMPRODUCT((E5:E154="Wk 2 (28 Apr)")*(G5:G154="Cash")*(F5:F154)) -> 0 | E160: =SUMPRODUCT((E5:E154="Wk 2 (28 Apr)")*((G5:G154="MTN MoMo")+(G5:G154="Vodafone Cash")+(G5:G154="AirtelTigo Money"))*(F5:F154)) -> 500 | F160: =SUMPRODUCT((E5:E154="Wk 2 (28 Apr)")*(G5:G154="Bank Transfer")*(F5:F154)) -> 0 | G160: =SUMPRODUCT((E5:E154="Wk 2 (28 Apr)")*(G5:G154="Cheque")*(F5:F154)) -> 0 | H160: =SUM(D160:G160) -> 500 | I160: =I159+H160 -> 1500
A161: Wk 3 (05 May) | B161: 46147 | C161: =COUNTIF(E5:E154,"Wk 3 (05 May)") -> 0 | D161: =SUMPRODUCT((E5:E154="Wk 3 (05 May)")*(G5:G154="Cash")*(F5:F154)) -> 0 | E161: =SUMPRODUCT((E5:E154="Wk 3 (05 May)")*((G5:G154="MTN MoMo")+(G5:G154="Vodafone Cash")+(G5:G154="AirtelTigo Money"))*(F5:F154)) -> 0 | F161: =SUMPRODUCT((E5:E154="Wk 3 (05 May)")*(G5:G154="Bank Transfer")*(F5:F154)) -> 0 | G161: =SUMPRODUCT((E5:E154="Wk 3 (05 May)")*(G5:G154="Cheque")*(F5:F154)) -> 0 | H161: =SUM(D161:G161) -> 0 | I161: =I160+H161 -> 1500
A162: Wk 4 (12 May) | B162: 46154 | C162: =COUNTIF(E5:E154,"Wk 4 (12 May)") -> 1 | D162: =SUMPRODUCT((E5:E154="Wk 4 (12 May)")*(G5:G154="Cash")*(F5:F154)) -> 3200 | E162: =SUMPRODUCT((E5:E154="Wk 4 (12 May)")*((G5:G154="MTN MoMo")+(G5:G154="Vodafone Cash")+(G5:G154="AirtelTigo Money"))*(F5:F154)) -> 0 | F162: =SUMPRODUCT((E5:E154="Wk 4 (12 May)")*(G5:G154="Bank Transfer")*(F5:F154)) -> 0 | G162: =SUMPRODUCT((E5:E154="Wk 4 (12 May)")*(G5:G154="Cheque")*(F5:F154)) -> 0 | H162: =SUM(D162:G162) -> 3200 | I162: =I161+H162 -> 4700
A163: Wk 5 (19 May) | B163: 46161 | C163: =COUNTIF(E5:E154,"Wk 5 (19 May)") -> 0 | D163: =SUMPRODUCT((E5:E154="Wk 5 (19 May)")*(G5:G154="Cash")*(F5:F154)) -> 0 | E163: =SUMPRODUCT((E5:E154="Wk 5 (19 May)")*((G5:G154="MTN MoMo")+(G5:G154="Vodafone Cash")+(G5:G154="AirtelTigo Money"))*(F5:F154)) -> 0 | F163: =SUMPRODUCT((E5:E154="Wk 5 (19 May)")*(G5:G154="Bank Transfer")*(F5:F154)) -> 0 | G163: =SUMPRODUCT((E5:E154="Wk 5 (19 May)")*(G5:G154="Cheque")*(F5:F154)) -> 0 | H163: =SUM(D163:G163) -> 0 | I163: =I162+H163 -> 4700
A164: Wk 6 (26 May) | B164: 46168 | C164: =COUNTIF(E5:E154,"Wk 6 (26 May)") -> 1 | D164: =SUMPRODUCT((E5:E154="Wk 6 (26 May)")*(G5:G154="Cash")*(F5:F154)) -> 0 | E164: =SUMPRODUCT((E5:E154="Wk 6 (26 May)")*((G5:G154="MTN MoMo")+(G5:G154="Vodafone Cash")+(G5:G154="AirtelTigo Money"))*(F5:F154)) -> 0 | F164: =SUMPRODUCT((E5:E154="Wk 6 (26 May)")*(G5:G154="Bank Transfer")*(F5:F154)) -> 2200 | G164: =SUMPRODUCT((E5:E154="Wk 6 (26 May)")*(G5:G154="Cheque")*(F5:F154)) -> 0 | H164: =SUM(D164:G164) -> 2200 | I164: =I163+H164 -> 6900
A165: Wk 7 (02 Jun) | B165: 46175 | C165: =COUNTIF(E5:E154,"Wk 7 (02 Jun)") -> 1 | D165: =SUMPRODUCT((E5:E154="Wk 7 (02 Jun)")*(G5:G154="Cash")*(F5:F154)) -> 0 | E165: =SUMPRODUCT((E5:E154="Wk 7 (02 Jun)")*((G5:G154="MTN MoMo")+(G5:G154="Vodafone Cash")+(G5:G154="AirtelTigo Money"))*(F5:F154)) -> 250 | F165: =SUMPRODUCT((E5:E154="Wk 7 (02 Jun)")*(G5:G154="Bank Transfer")*(F5:F154)) -> 0 | G165: =SUMPRODUCT((E5:E154="Wk 7 (02 Jun)")*(G5:G154="Cheque")*(F5:F154)) -> 0 | H165: =SUM(D165:G165) -> 250 | I165: =I164+H165 -> 7150
A166: Wk 8 (09 Jun) | B166: 46182 | C166: =COUNTIF(E5:E154,"Wk 8 (09 Jun)") -> 0 | D166: =SUMPRODUCT((E5:E154="Wk 8 (09 Jun)")*(G5:G154="Cash")*(F5:F154)) -> 0 | E166: =SUMPRODUCT((E5:E154="Wk 8 (09 Jun)")*((G5:G154="MTN MoMo")+(G5:G154="Vodafone Cash")+(G5:G154="AirtelTigo Money"))*(F5:F154)) -> 0 | F166: =SUMPRODUCT((E5:E154="Wk 8 (09 Jun)")*(G5:G154="Bank Transfer")*(F5:F154)) -> 0 | G166: =SUMPRODUCT((E5:E154="Wk 8 (09 Jun)")*(G5:G154="Cheque")*(F5:F154)) -> 0 | H166: =SUM(D166:G166) -> 0 | I166: =I165+H166 -> 7150
A167: Wk 9 (16 Jun) | B167: 46189 | C167: =COUNTIF(E5:E154,"Wk 9 (16 Jun)") -> 0 | D167: =SUMPRODUCT((E5:E154="Wk 9 (16 Jun)")*(G5:G154="Cash")*(F5:F154)) -> 0 | E167: =SUMPRODUCT((E5:E154="Wk 9 (16 Jun)")*((G5:G154="MTN MoMo")+(G5:G154="Vodafone Cash")+(G5:G154="AirtelTigo Money"))*(F5:F154)) -> 0 | F167: =SUMPRODUCT((E5:E154="Wk 9 (16 Jun)")*(G5:G154="Bank Transfer")*(F5:F154)) -> 0 | G167: =SUMPRODUCT((E5:E154="Wk 9 (16 Jun)")*(G5:G154="Cheque")*(F5:F154)) -> 0 | H167: =SUM(D167:G167) -> 0 | I167: =I166+H167 -> 7150
A168: Wk 10 (23 Jun) | B168: 46196 | C168: =COUNTIF(E5:E154,"Wk 10 (23 Jun)") -> 0 | D168: =SUMPRODUCT((E5:E154="Wk 10 (23 Jun)")*(G5:G154="Cash")*(F5:F154)) -> 0 | E168: =SUMPRODUCT((E5:E154="Wk 10 (23 Jun)")*((G5:G154="MTN MoMo")+(G5:G154="Vodafone Cash")+(G5:G154="AirtelTigo Money"))*(F5:F154)) -> 0 | F168: =SUMPRODUCT((E5:E154="Wk 10 (23 Jun)")*(G5:G154="Bank Transfer")*(F5:F154)) -> 0 | G168: =SUMPRODUCT((E5:E154="Wk 10 (23 Jun)")*(G5:G154="Cheque")*(F5:F154)) -> 0 | H168: =SUM(D168:G168) -> 0 | I168: =I167+H168 -> 7150
A169: Wk 11 (30 Jun) | B169: 46203 | C169: =COUNTIF(E5:E154,"Wk 11 (30 Jun)") -> 0 | D169: =SUMPRODUCT((E5:E154="Wk 11 (30 Jun)")*(G5:G154="Cash")*(F5:F154)) -> 0 | E169: =SUMPRODUCT((E5:E154="Wk 11 (30 Jun)")*((G5:G154="MTN MoMo")+(G5:G154="Vodafone Cash")+(G5:G154="AirtelTigo Money"))*(F5:F154)) -> 0 | F169: =SUMPRODUCT((E5:E154="Wk 11 (30 Jun)")*(G5:G154="Bank Transfer")*(F5:F154)) -> 0 | G169: =SUMPRODUCT((E5:E154="Wk 11 (30 Jun)")*(G5:G154="Cheque")*(F5:F154)) -> 0 | H169: =SUM(D169:G169) -> 0 | I169: =I168+H169 -> 7150
A170: Wk 12 (07 Jul) | B170: 46210 | C170: =COUNTIF(E5:E154,"Wk 12 (07 Jul)") -> 0 | D170: =SUMPRODUCT((E5:E154="Wk 12 (07 Jul)")*(G5:G154="Cash")*(F5:F154)) -> 0 | E170: =SUMPRODUCT((E5:E154="Wk 12 (07 Jul)")*((G5:G154="MTN MoMo")+(G5:G154="Vodafone Cash")+(G5:G154="AirtelTigo Money"))*(F5:F154)) -> 0 | F170: =SUMPRODUCT((E5:E154="Wk 12 (07 Jul)")*(G5:G154="Bank Transfer")*(F5:F154)) -> 0 | G170: =SUMPRODUCT((E5:E154="Wk 12 (07 Jul)")*(G5:G154="Cheque")*(F5:F154)) -> 0 | H170: =SUM(D170:G170) -> 0 | I170: =I169+H170 -> 7150 | J170: PAST DEADLINE
A171: Wk 13 (14 Jul) | B171: 46217 | C171: =COUNTIF(E5:E154,"Wk 13 (14 Jul)") -> 0 | D171: =SUMPRODUCT((E5:E154="Wk 13 (14 Jul)")*(G5:G154="Cash")*(F5:F154)) -> 0 | E171: =SUMPRODUCT((E5:E154="Wk 13 (14 Jul)")*((G5:G154="MTN MoMo")+(G5:G154="Vodafone Cash")+(G5:G154="AirtelTigo Money"))*(F5:F154)) -> 0 | F171: =SUMPRODUCT((E5:E154="Wk 13 (14 Jul)")*(G5:G154="Bank Transfer")*(F5:F154)) -> 0 | G171: =SUMPRODUCT((E5:E154="Wk 13 (14 Jul)")*(G5:G154="Cheque")*(F5:F154)) -> 0 | H171: =SUM(D171:G171) -> 0 | I171: =I170+H171 -> 7150 | J171: PAST DEADLINE
A172: Wk 14 (21 Jul) | B172: 46224 | C172: =COUNTIF(E5:E154,"Wk 14 (21 Jul)") -> 0 | D172: =SUMPRODUCT((E5:E154="Wk 14 (21 Jul)")*(G5:G154="Cash")*(F5:F154)) -> 0 | E172: =SUMPRODUCT((E5:E154="Wk 14 (21 Jul)")*((G5:G154="MTN MoMo")+(G5:G154="Vodafone Cash")+(G5:G154="AirtelTigo Money"))*(F5:F154)) -> 0 | F172: =SUMPRODUCT((E5:E154="Wk 14 (21 Jul)")*(G5:G154="Bank Transfer")*(F5:F154)) -> 0 | G172: =SUMPRODUCT((E5:E154="Wk 14 (21 Jul)")*(G5:G154="Cheque")*(F5:F154)) -> 0 | H172: =SUM(D172:G172) -> 0 | I172: =I171+H172 -> 7150 | J172: PAST DEADLINE
A173: TERM 3 TOTAL | C173: =SUM(C159:C172) -> 5 | D173: =SUM(D159:D172) -> 3200 | E173: =SUM(E159:E172) -> 750 | F173: =SUM(F159:F172) -> 3200 | G173: =SUM(G159:G172) -> 0 | H173: =SUM(H159:H172) -> 7150
A176: MONTHLY COLLECTION SUMMARY
A177: Month | B177: No. of Payments | C177: Cash | D177: MoMo (All) | E177: Bank Transfer | F177: Cheque | G177: Month Total | H177: Cumulative | I177: Target % | J177: Actual % | K177: Notes
A178: Apr | B178: =SUMPRODUCT((MONTH(A5:A154)=4)*(A5:A154<>"")) -> 2 | C178: =SUMPRODUCT((MONTH(A5:A154)=4)*(G5:G154="Cash")*(F5:F154)) -> 0 | D178: =SUMPRODUCT((MONTH(A5:A154)=4)*((G5:G154="MTN MoMo")+(G5:G154="Vodafone Cash")+(G5:G154="AirtelTigo Money"))*(F5:F154)) -> 500 | E178: =SUMPRODUCT((MONTH(A5:A154)=4)*(G5:G154="Bank Transfer")*(F5:F154)) -> 1000 | F178: =SUMPRODUCT((MONTH(A5:A154)=4)*(G5:G154="Cheque")*(F5:F154)) -> 0 | G178: =SUM(C178:F178) -> 1500 | H178: =G178 -> 1500 | I178: 0.3
A179: May | B179: =SUMPRODUCT((MONTH(A5:A154)=5)*(A5:A154<>"")) -> 2 | C179: =SUMPRODUCT((MONTH(A5:A154)=5)*(G5:G154="Cash")*(F5:F154)) -> 3200 | D179: =SUMPRODUCT((MONTH(A5:A154)=5)*((G5:G154="MTN MoMo")+(G5:G154="Vodafone Cash")+(G5:G154="AirtelTigo Money"))*(F5:F154)) -> 0 | E179: =SUMPRODUCT((MONTH(A5:A154)=5)*(G5:G154="Bank Transfer")*(F5:F154)) -> 2200 | F179: =SUMPRODUCT((MONTH(A5:A154)=5)*(G5:G154="Cheque")*(F5:F154)) -> 0 | G179: =SUM(C179:F179) -> 5400 | H179: =H178+G179 -> 6900 | I179: 0.65
A180: Jun | B180: =SUMPRODUCT((MONTH(A5:A154)=6)*(A5:A154<>"")) -> 1 | C180: =SUMPRODUCT((MONTH(A5:A154)=6)*(G5:G154="Cash")*(F5:F154)) -> 0 | D180: =SUMPRODUCT((MONTH(A5:A154)=6)*((G5:G154="MTN MoMo")+(G5:G154="Vodafone Cash")+(G5:G154="AirtelTigo Money"))*(F5:F154)) -> 250 | E180: =SUMPRODUCT((MONTH(A5:A154)=6)*(G5:G154="Bank Transfer")*(F5:F154)) -> 0 | F180: =SUMPRODUCT((MONTH(A5:A154)=6)*(G5:G154="Cheque")*(F5:F154)) -> 0 | G180: =SUM(C180:F180) -> 250 | H180: =H179+G180 -> 7150 | I180: 1
A181: Jul | B181: =SUMPRODUCT((MONTH(A5:A154)=7)*(A5:A154<>"")) -> 0 | C181: =SUMPRODUCT((MONTH(A5:A154)=7)*(G5:G154="Cash")*(F5:F154)) -> 0 | D181: =SUMPRODUCT((MONTH(A5:A154)=7)*((G5:G154="MTN MoMo")+(G5:G154="Vodafone Cash")+(G5:G154="AirtelTigo Money"))*(F5:F154)) -> 0 | E181: =SUMPRODUCT((MONTH(A5:A154)=7)*(G5:G154="Bank Transfer")*(F5:F154)) -> 0 | F181: =SUMPRODUCT((MONTH(A5:A154)=7)*(G5:G154="Cheque")*(F5:F154)) -> 0 | G181: =SUM(C181:F181) -> 0 | H181: =H180+G181 -> 7150 | I181: 1
A182: TOTAL | B182: =SUM(B178:B181) -> 5 | C182: =SUM(C178:C181) -> 3200 | D182: =SUM(D178:D181) -> 750 | E182: =SUM(E178:E181) -> 3200 | F182: =SUM(F178:F181) -> 0 | G182: =SUM(G178:G181) -> 7150

Sheet Grade 5 - Falcons
A1: Grade 5: Falcons — Speed | Agility | Annual: GHS 8,500 | Termly: GHS 3,000
A3: PUPIL DETAILS | D3: TERM 1 (COMPLETED) | H3: TERM 2 (COMPLETED) | M3: TERM 3 (ACTIVE — arrears from T1/T2 included) | Q3: NOTES
A4: No. | B4: Pupil Name | C4: Discount Type | D4: T1 Fee | E4: T1 Arrears BF | F4: T1 Paid | G4: T1 Balance | H4: T2 Fee | I4: T2 Arrears BF | J4: T2 Discount | K4: T2 Paid | L4: T2 Balance | M4: T3 Fee | N4: T3 Discount | O4: T3 Paid | P4: T3 Balance | Q4: Remarks / Waiver Notes
A5: 1 | B5: Akrofi-Quarcoo Ethan Siisi Jeremy | D5: 3200 | F5: 3200 | G5: =IF(B5="","",IF(D5="",0,D5)+IF(E5="",0,E5)-IF(F5="",0,F5)) -> 0 | H5: 3000 | K5: 3000 | L5: =IF(B5="","",IF(H5="",0,H5)+IF(I5="",0,I5)-IF(J5="",0,J5)-IF(K5="",0,K5)) -> 0 | M5: 3000 | O5: 1500 | P5: =IF(B5="","",IF(M5="",0,M5)-IF(N5="",0,N5)+IF(L5<0,0,IF(L5="",0,L5))-IF(O5="",0,O5)) -> 1500
A6: 2 | B6: Djaba Nana Kwame Lartey Leroy | D6: 3200 | F6: 2116.67 | G6: =IF(B6="","",IF(D6="",0,D6)+IF(E6="",0,E6)-IF(F6="",0,F6)) -> 1083.33 | H6: 3000 | K6: 3000 | L6: =IF(B6="","",IF(H6="",0,H6)+IF(I6="",0,I6)-IF(J6="",0,J6)-IF(K6="",0,K6)) -> 0 | M6: 3000 | O6: =SUMIF('Grade 5 - Payments'!C5:C154,B6,'Grade 5 - Payments'!F5:F154) -> 0 | P6: =IF(B6="","",IF(M6="",0,M6)-IF(N6="",0,N6)+IF(L6<0,0,IF(L6="",0,L6))-IF(O6="",0,O6)) -> 3000
A7: 3 | B7: Harmony Owusu | C7: Staff Child | D7: 1500 | F7: 500 | G7: =IF(B7="","",IF(D7="",0,D7)+IF(E7="",0,E7)-IF(F7="",0,F7)) -> 1000 | H7: 3000 | I7: 1000 | J7: 3000 | K7: 1000 | L7: =IF(B7="","",IF(H7="",0,H7)+IF(I7="",0,I7)-IF(J7="",0,J7)-IF(K7="",0,K7)) -> 0 | M7: 3000 | N7: 3000 | O7: =SUMIF('Grade 5 - Payments'!C5:C154,B7,'Grade 5 - Payments'!F5:F154) -> 0 | P7: =IF(B7="","",IF(M7="",0,M7)-IF(N7="",0,N7)+IF(L7<0,0,IF(L7="",0,L7))-IF(O7="",0,O7)) -> 0 | Q7: Staff child — T1 partial (GHS 500 of 1,500); T2 settled incl. arrears
A8: 4 | G8: =IF(B8="","",0) | L8: =IF(B8="","",0) | P8: =IF(B8="","",0)
A9: 5 | G9: =IF(B9="","",0) | L9: =IF(B9="","",0) | P9: =IF(B9="","",0)
A10: 6 | G10: =IF(B10="","",0) | L10: =IF(B10="","",0) | P10: =IF(B10="","",0)
A11: 7 | G11: =IF(B11="","",0) | L11: =IF(B11="","",0) | P11: =IF(B11="","",0)
A12: 8 | G12: =IF(B12="","",0) | L12: =IF(B12="","",0) | P12: =IF(B12="","",0)
A13: 9 | G13: =IF(B13="","",0) | L13: =IF(B13="","",0) | P13: =IF(B13="","",0)
A14: 10 | G14: =IF(B14="","",0) | L14: =IF(B14="","",0) | P14: =IF(B14="","",0)
A15: 11 | G15: =IF(B15="","",0) | L15: =IF(B15="","",0) | P15: =IF(B15="","",0)
A16: 12 | G16: =IF(B16="","",0) | L16: =IF(B16="","",0) | P16: =IF(B16="","",0)
A17: 13 | G17: =IF(B17="","",0) | L17: =IF(B17="","",0) | P17: =IF(B17="","",0)
B18: TOTALS | D18: =SUM(D5:D17) -> 7900 | E18: =SUM(E5:E17) -> 0 | F18: =SUM(F5:F17) -> 5816.67 | G18: =SUM(G5:G17) -> 2083.33 | H18: =SUM(H5:H17) -> 9000 | I18: =SUM(I5:I17) -> 1000 | J18: =SUM(J5:J17) -> 3000 | K18: =SUM(K5:K17) -> 7000 | ... P18: =SUM(P5:P17) -> 4500
B19: Collection Rate: | F19: T1: | G19: =IF(D18+E18=0,1,F18/(D18+E18)) -> 0.73628734 | K19: T2: | L19: =IF(H18+I18-J18=0,1,K18/(H18+I18-J18)) -> 1 | O19: =SUMIF('Grade 5 - Payments'!C5:C154,B19,'Grade 5 - Payments'!F5:F154) -> 0

Sheet Grade 5 - Payments
A1: Grade 5: Falcons — PAYMENT RECEIPTS LOG (Term 3, 2025/26: 21 Apr – 24 Jul 2026) | P1: Akrofi-Quarcoo Ethan S.J.
A2: Payment deadline: 30 June 2026 | Enter one row per payment | T3 Paid on class register auto-updates via SUMIFS | P2: Djaba Nana Kwame Lartey L.
A3: TRANSACTION DETAILS | G3: PAYMENT | J3: VERIFICATION | P3: Harmony Owusu
A4: Date | B4: Receipt No. | C4: Pupil Name | D4: Term | E4: Week | F4: Amount (GHS) | G4: Payment Method | H4: Received By | I4: Running Total | J4: Verified | K4: Notes
A5: 46132 | B5: 1041 | C5: Akrofi-Quarcoo Ethan S.J. | D5: Term 3 | E5: Wk 1 (21 Apr) | F5: 1500 | G5: Bank Transfer | H5: Dorcas Matilda Akosua Kusi | I5: =IF(F5="","",F5) -> 1500
A6: 46163 | B6: 1081 | C6: Akrofi-Quarcoo Ethan S.J. | D6: Term 3 | E6: Wk 5 (19 May) | F6: 1700 | G6: Bank Transfer | H6: Dorcas Matilda Akosua Kusi | I6: =IF(F6="","",IF(I5="",F6,I5+F6)) -> 3200
I7: =IF(F7="","",IF(I6="",F7,I6+F7))
I8: =IF(F8="","",IF(I7="",F8,I7+F8))
I9: =IF(F9="","",IF(I8="",F9,I8+F9))
I10: =IF(F10="","",IF(I9="",F10,I9+F10))
I11: =IF(F11="","",IF(I10="",F11,I10+F11))
I12: =IF(F12="","",IF(I11="",F12,I11+F12))
I13: =IF(F13="","",IF(I12="",F13,I12+F13))
I14: =IF(F14="","",IF(I13="",F14,I13+F14))
I15: =IF(F15="","",IF(I14="",F15,I14+F15))
I16: =IF(F16="","",IF(I15="",F16,I15+F16))
I17: =IF(F17="","",IF(I16="",F17,I16+F17))
I18: =IF(F18="","",IF(I17="",F18,I17+F18))
... I154: =IF(F154="","",IF(I153="",F154,I153+F154))
A157: WEEKLY COLLECTION SUMMARY (auto-calculated from payment log)
A158: Week | B158: Week Starting | C158: Entries | D158: Cash | E158: MoMo (All) | F158: Bank Transfer | G158: Cheque | H158: Week Total | I158: Cumulative | J158: vs Deadline | K158: Notes
A159: Wk 1 (21 Apr) | B159: 46133 | C159: =COUNTIF(E5:E154,"Wk 1 (21 Apr)") -> 1 | D159: =SUMPRODUCT((E5:E154="Wk 1 (21 Apr)")*(G5:G154="Cash")*(F5:F154)) -> 0 | E159: =SUMPRODUCT((E5:E154="Wk 1 (21 Apr)")*((G5:G154="MTN MoMo")+(G5:G154="Vodafone Cash")+(G5:G154="AirtelTigo Money"))*(F5:F154)) -> 0 | F159: =SUMPRODUCT((E5:E154="Wk 1 (21 Apr)")*(G5:G154="Bank Transfer")*(F5:F154)) -> 1500 | G159: =SUMPRODUCT((E5:E154="Wk 1 (21 Apr)")*(G5:G154="Cheque")*(F5:F154)) -> 0 | H159: =SUM(D159:G159) -> 1500 | I159: =H159 -> 1500
A160: Wk 2 (28 Apr) | B160: 46140 | C160: =COUNTIF(E5:E154,"Wk 2 (28 Apr)") -> 0 | D160: =SUMPRODUCT((E5:E154="Wk 2 (28 Apr)")*(G5:G154="Cash")*(F5:F154)) -> 0 | E160: =SUMPRODUCT((E5:E154="Wk 2 (28 Apr)")*((G5:G154="MTN MoMo")+(G5:G154="Vodafone Cash")+(G5:G154="AirtelTigo Money"))*(F5:F154)) -> 0 | F160: =SUMPRODUCT((E5:E154="Wk 2 (28 Apr)")*(G5:G154="Bank Transfer")*(F5:F154)) -> 0 | G160: =SUMPRODUCT((E5:E154="Wk 2 (28 Apr)")*(G5:G154="Cheque")*(F5:F154)) -> 0 | H160: =SUM(D160:G160) -> 0 | I160: =I159+H160 -> 1500
A161: Wk 3 (05 May) | B161: 46147 | C161: =COUNTIF(E5:E154,"Wk 3 (05 May)") -> 0 | D161: =SUMPRODUCT((E5:E154="Wk 3 (05 May)")*(G5:G154="Cash")*(F5:F154)) -> 0 | E161: =SUMPRODUCT((E5:E154="Wk 3 (05 May)")*((G5:G154="MTN MoMo")+(G5:G154="Vodafone Cash")+(G5:G154="AirtelTigo Money"))*(F5:F154)) -> 0 | F161: =SUMPRODUCT((E5:E154="Wk 3 (05 May)")*(G5:G154="Bank Transfer")*(F5:F154)) -> 0 | G161: =SUMPRODUCT((E5:E154="Wk 3 (05 May)")*(G5:G154="Cheque")*(F5:F154)) -> 0 | H161: =SUM(D161:G161) -> 0 | I161: =I160+H161 -> 1500
A162: Wk 4 (12 May) | B162: 46154 | C162: =COUNTIF(E5:E154,"Wk 4 (12 May)") -> 0 | D162: =SUMPRODUCT((E5:E154="Wk 4 (12 May)")*(G5:G154="Cash")*(F5:F154)) -> 0 | E162: =SUMPRODUCT((E5:E154="Wk 4 (12 May)")*((G5:G154="MTN MoMo")+(G5:G154="Vodafone Cash")+(G5:G154="AirtelTigo Money"))*(F5:F154)) -> 0 | F162: =SUMPRODUCT((E5:E154="Wk 4 (12 May)")*(G5:G154="Bank Transfer")*(F5:F154)) -> 0 | G162: =SUMPRODUCT((E5:E154="Wk 4 (12 May)")*(G5:G154="Cheque")*(F5:F154)) -> 0 | H162: =SUM(D162:G162) -> 0 | I162: =I161+H162 -> 1500
A163: Wk 5 (19 May) | B163: 46161 | C163: =COUNTIF(E5:E154,"Wk 5 (19 May)") -> 1 | D163: =SUMPRODUCT((E5:E154="Wk 5 (19 May)")*(G5:G154="Cash")*(F5:F154)) -> 0 | E163: =SUMPRODUCT((E5:E154="Wk 5 (19 May)")*((G5:G154="MTN MoMo")+(G5:G154="Vodafone Cash")+(G5:G154="AirtelTigo Money"))*(F5:F154)) -> 0 | F163: =SUMPRODUCT((E5:E154="Wk 5 (19 May)")*(G5:G154="Bank Transfer")*(F5:F154)) -> 1700 | G163: =SUMPRODUCT((E5:E154="Wk 5 (19 May)")*(G5:G154="Cheque")*(F5:F154)) -> 0 | H163: =SUM(D163:G163) -> 1700 | I163: =I162+H163 -> 3200
A164: Wk 6 (26 May) | B164: 46168 | C164: =COUNTIF(E5:E154,"Wk 6 (26 May)") -> 0 | D164: =SUMPRODUCT((E5:E154="Wk 6 (26 May)")*(G5:G154="Cash")*(F5:F154)) -> 0 | E164: =SUMPRODUCT((E5:E154="Wk 6 (26 May)")*((G5:G154="MTN MoMo")+(G5:G154="Vodafone Cash")+(G5:G154="AirtelTigo Money"))*(F5:F154)) -> 0 | F164: =SUMPRODUCT((E5:E154="Wk 6 (26 May)")*(G5:G154="Bank Transfer")*(F5:F154)) -> 0 | G164: =SUMPRODUCT((E5:E154="Wk 6 (26 May)")*(G5:G154="Cheque")*(F5:F154)) -> 0 | H164: =SUM(D164:G164) -> 0 | I164: =I163+H164 -> 3200
A165: Wk 7 (02 Jun) | B165: 46175 | C165: =COUNTIF(E5:E154,"Wk 7 (02 Jun)") -> 0 | D165: =SUMPRODUCT((E5:E154="Wk 7 (02 Jun)")*(G5:G154="Cash")*(F5:F154)) -> 0 | E165: =SUMPRODUCT((E5:E154="Wk 7 (02 Jun)")*((G5:G154="MTN MoMo")+(G5:G154="Vodafone Cash")+(G5:G154="AirtelTigo Money"))*(F5:F154)) -> 0 | F165: =SUMPRODUCT((E5:E154="Wk 7 (02 Jun)")*(G5:G154="Bank Transfer")*(F5:F154)) -> 0 | G165: =SUMPRODUCT((E5:E154="Wk 7 (02 Jun)")*(G5:G154="Cheque")*(F5:F154)) -> 0 | H165: =SUM(D165:G165) -> 0 | I165: =I164+H165 -> 3200
A166: Wk 8 (09 Jun) | B166: 46182 | C166: =COUNTIF(E5:E154,"Wk 8 (09 Jun)") -> 0 | D166: =SUMPRODUCT((E5:E154="Wk 8 (09 Jun)")*(G5:G154="Cash")*(F5:F154)) -> 0 | E166: =SUMPRODUCT((E5:E154="Wk 8 (09 Jun)")*((G5:G154="MTN MoMo")+(G5:G154="Vodafone Cash")+(G5:G154="AirtelTigo Money"))*(F5:F154)) -> 0 | F166: =SUMPRODUCT((E5:E154="Wk 8 (09 Jun)")*(G5:G154="Bank Transfer")*(F5:F154)) -> 0 | G166: =SUMPRODUCT((E5:E154="Wk 8 (09 Jun)")*(G5:G154="Cheque")*(F5:F154)) -> 0 | H166: =SUM(D166:G166) -> 0 | I166: =I165+H166 -> 3200
A167: Wk 9 (16 Jun) | B167: 46189 | C167: =COUNTIF(E5:E154,"Wk 9 (16 Jun)") -> 0 | D167: =SUMPRODUCT((E5:E154="Wk 9 (16 Jun)")*(G5:G154="Cash")*(F5:F154)) -> 0 | E167: =SUMPRODUCT((E5:E154="Wk 9 (16 Jun)")*((G5:G154="MTN MoMo")+(G5:G154="Vodafone Cash")+(G5:G154="AirtelTigo Money"))*(F5:F154)) -> 0 | F167: =SUMPRODUCT((E5:E154="Wk 9 (16 Jun)")*(G5:G154="Bank Transfer")*(F5:F154)) -> 0 | G167: =SUMPRODUCT((E5:E154="Wk 9 (16 Jun)")*(G5:G154="Cheque")*(F5:F154)) -> 0 | H167: =SUM(D167:G167) -> 0 | I167: =I166+H167 -> 3200
A168: Wk 10 (23 Jun) | B168: 46196 | C168: =COUNTIF(E5:E154,"Wk 10 (23 Jun)") -> 0 | D168: =SUMPRODUCT((E5:E154="Wk 10 (23 Jun)")*(G5:G154="Cash")*(F5:F154)) -> 0 | E168: =SUMPRODUCT((E5:E154="Wk 10 (23 Jun)")*((G5:G154="MTN MoMo")+(G5:G154="Vodafone Cash")+(G5:G154="AirtelTigo Money"))*(F5:F154)) -> 0 | F168: =SUMPRODUCT((E5:E154="Wk 10 (23 Jun)")*(G5:G154="Bank Transfer")*(F5:F154)) -> 0 | G168: =SUMPRODUCT((E5:E154="Wk 10 (23 Jun)")*(G5:G154="Cheque")*(F5:F154)) -> 0 | H168: =SUM(D168:G168) -> 0 | I168: =I167+H168 -> 3200
A169: Wk 11 (30 Jun) | B169: 46203 | C169: =COUNTIF(E5:E154,"Wk 11 (30 Jun)") -> 0 | D169: =SUMPRODUCT((E5:E154="Wk 11 (30 Jun)")*(G5:G154="Cash")*(F5:F154)) -> 0 | E169: =SUMPRODUCT((E5:E154="Wk 11 (30 Jun)")*((G5:G154="MTN MoMo")+(G5:G154="Vodafone Cash")+(G5:G154="AirtelTigo Money"))*(F5:F154)) -> 0 | F169: =SUMPRODUCT((E5:E154="Wk 11 (30 Jun)")*(G5:G154="Bank Transfer")*(F5:F154)) -> 0 | G169: =SUMPRODUCT((E5:E154="Wk 11 (30 Jun)")*(G5:G154="Cheque")*(F5:F154)) -> 0 | H169: =SUM(D169:G169) -> 0 | I169: =I168+H169 -> 3200
